Workbook

Sheet Dashboard
A2: Lifelong learning income dashboard
A3: UK comparable CPD/CE income | 2024/25 | HESA HE-BCI provider returns
A5: UK income (£m) | F5: HE providers | K5: Learner days | Q5: Top provider | R5: CPD/CE (£m)
A6: =SUM('UK providers'!I7:I212)/1000 | F6: =COUNTA('UK providers'!A7:A212) | K6: =SUM('UK providers'!J7:J212) | Q6: =INDEX('UK providers'!$Q$7:$Q$212,MATCH(1,'UK providers'!$P$7:$P$212,0)) | R6: =INDEX('UK providers'!$K$7:$K$212,MATCH(1,'UK providers'!$P$7:$P$212,0))
Q7: =INDEX('UK providers'!$Q$7:$Q$212,MATCH(2,'UK providers'!$P$7:$P$212,0)) | R7: =INDEX('UK providers'!$K$7:$K$212,MATCH(2,'UK providers'!$P$7:$P$212,0))
Q8: =INDEX('UK providers'!$Q$7:$Q$212,MATCH(3,'UK providers'!$P$7:$P$212,0)) | R8: =INDEX('UK providers'!$K$7:$K$212,MATCH(3,'UK providers'!$P$7:$P$212,0))
A9: CPD/CE is a defined part of lifelong learning. These HE providers extend beyond universities. The supplied file contains one year, so a UK HESA income growth trend is unavailable. | Q9: =INDEX('UK providers'!$Q$7:$Q$212,MATCH(4,'UK providers'!$P$7:$P$212,0)) | R9: =INDEX('UK providers'!$K$7:$K$212,MATCH(4,'UK providers'!$P$7:$P$212,0))
Q10: =INDEX('UK providers'!$Q$7:$Q$212,MATCH(5,'UK providers'!$P$7:$P$212,0)) | R10: =INDEX('UK providers'!$K$7:$K$212,MATCH(5,'UK providers'!$P$7:$P$212,0))
Q11: =INDEX('UK providers'!$Q$7:$Q$212,MATCH(6,'UK providers'!$P$7:$P$212,0)) | R11: =INDEX('UK providers'!$K$7:$K$212,MATCH(6,'UK providers'!$P$7:$P$212,0))
A12: UK income by research cohort | I12: Customer mix | Q12: =INDEX('UK providers'!$Q$7:$Q$212,MATCH(7,'UK providers'!$P$7:$P$212,0)) | R12: =INDEX('UK providers'!$K$7:$K$212,MATCH(7,'UK providers'!$P$7:$P$212,0))
Q13: =INDEX('UK providers'!$Q$7:$Q$212,MATCH(8,'UK providers'!$P$7:$P$212,0)) | R13: =INDEX('UK providers'!$K$7:$K$212,MATCH(8,'UK providers'!$P$7:$P$212,0))
A14: Cohort | D14: Providers | F14: Income (£m) | I14: Customer | M14: Income (£m) | Q14: =INDEX('UK providers'!$Q$7:$Q$212,MATCH(9,'UK providers'!$P$7:$P$212,0)) | R14: =INDEX('UK providers'!$K$7:$K$212,MATCH(9,'UK providers'!$P$7:$P$212,0))
A15: Russell Group | D15: =COUNTIF('UK providers'!$C$7:$C$212,A15) | F15: =SUMIF('UK providers'!$C$7:$C$212,A15,'UK providers'!$K$7:$K$212) | I15: Individuals | M15: =SUM('UK providers'!H7:H212)/1000 | Q15: =INDEX('UK providers'!$Q$7:$Q$212,MATCH(10,'UK providers'!$P$7:$P$212,0)) | R15: =INDEX('UK providers'!$K$7:$K$212,MATCH(10,'UK providers'!$P$7:$P$212,0))
A16: Additional UK sample | D16: =COUNTIF('UK providers'!$C$7:$C$212,A16) | F16: =SUMIF('UK providers'!$C$7:$C$212,A16,'UK providers'!$K$7:$K$212) | I16: Non-commercial | M16: =SUM('UK providers'!G7:G212)/1000
A17: Other HE provider | D17: =COUNTIF('UK providers'!$C$7:$C$212,A17) | F17: =SUMIF('UK providers'!$C$7:$C$212,A17,'UK providers'!$K$7:$K$212) | I17: Other commercial | M17: =SUM('UK providers'!F7:F212)/1000
I18: SMEs | M18: =SUM('UK providers'!E7:E212)/1000 | Q18: Customer | R18: CPD/CE (£m)
A19: Share from individual learners | F19: =SUM('UK providers'!H7:H212)/SUM('UK providers'!I7:I212) | Q19: =I15 | R19: =M15
Q20: =I16 | R20: =M16
Q21: =I17 | R21: =M17
Q22: =I18 | R22: =M18
A42: Australian revenue and growth: seven of the top 10 institutions
A43: Separate measures in AUD millions. Melbourne is the Business School entity. Periods and definitions differ; amounts must not be aggregated. Three institutions have no comparable numeric row.
A46: Institution | D46: Reported metric | I46: Current period | K46: AUD m | M46: Growth
A47: ='Revenue evidence'!B32 | D47: ='Revenue evidence'!D32 | I47: ='Revenue evidence'!H32 | K47: ='Revenue evidence'!I32 | M47: ='Revenue evidence'!J32
A48: ='Revenue evidence'!B33 | D48: ='Revenue evidence'!D33 | I48: ='Revenue evidence'!H33 | K48: ='Revenue evidence'!I33 | M48: ='Revenue evidence'!J33
A49: ='Revenue evidence'!B34 | D49: ='Revenue evidence'!D34 | I49: ='Revenue evidence'!H34 | K49: ='Revenue evidence'!I34 | M49: ='Revenue evidence'!J34
A50: ='Revenue evidence'!B37 | D50: ='Revenue evidence'!D37 | I50: ='Revenue evidence'!H37 | K50: ='Revenue evidence'!I37 | M50: ='Revenue evidence'!J37
A51: ='Revenue evidence'!B38 | D51: ='Revenue evidence'!D38 | I51: ='Revenue evidence'!H38 | K51: ='Revenue evidence'!I38 | M51: ='Revenue evidence'!J38
A52: ='Revenue evidence'!B40 | D52: ='Revenue evidence'!D40 | I52: ='Revenue evidence'!H40 | K52: ='Revenue evidence'!I40 | M52: ='Revenue evidence'!J40
A53: ='Revenue evidence'!B41 | D53: ='Revenue evidence'!D41 | I53: ='Revenue evidence'!H41 | K53: ='Revenue evidence'!I41 | M53: ='Revenue evidence'!J41
A56: Experiential-learning research coverage (strict-definition review; detail in 'EL dashboard')
A57: Institutions in scope / reviewed | F57: =COUNTA('EL institution summary'!$A$7:$A$130) | I57: Current qualifying schemes | M57: =COUNTIF('EL scheme register'!$AJ$7:$AJ$610,"Yes")
A58: With ≥1 current qualifying scheme | F58: =COUNTIF('EL institution summary'!$N$7:$N$130,">0") | I58: Institutions fully reviewed | M58: =COUNTIF('EL institution summary'!$H$7:$H$130,"Complete")
A60: Qualifying = project-based, group working and connected to a real external organisation on the same route, with current delivery confirmed. The legacy scheme sample (152 frameworks/examples) is retained in 'Legacy schemes (v3)'. Lifelong-learning revenue above is NOT revenue from these schemes.

Sheet EL dashboard
A2: Experiential learning dashboard: collaborative employer-connected projects
A3: Findings within the researched 124-institution sample (purposive, not random) — not estimates of national prevalence. A qualifying scheme = project-based AND group working AND connected to a real external organisation (all Yes on the same route) with current delivery confirmed; umbrellas with counted children are not double-counted.
A6: Institutions in scope | C6: Fully reviewed | E6: Partially reviewed | H6: Not yet reviewed | J6: With ≥1 current qualifying scheme
A7: =COUNTA('EL institution summary'!$A$7:$A$130) | C7: =COUNTIF('EL institution summary'!$H$7:$H$130,"Complete") | E7: =COUNTIF('EL institution summary'!$H$7:$H$130,"Partial") | H7: =COUNTIF('EL institution summary'!$H$7:$H$130,"Not started") | J7: =COUNTIF('EL institution summary'!$N$7:$N$130,">0")
J8: denominator = reviewed (full + partial)
A10: Distinct current qualifying schemes | C10: Records in scheme register | E10: Exclusion / near-miss records | H10: Source rows (claim-level) | J10: Reviewed institutions with none verified
A11: =COUNTIF('EL scheme register'!$AJ$7:$AJ$610,"Yes") | C11: =COUNTA('EL scheme register'!$D$7:$D$610) | E11: =COUNTA('EL exclusions & gaps'!$A$7:$A$5000) | H11: =COUNTA('EL sources'!$A$7:$A$20000) | J11: =COUNTIFS('EL institution summary'!$H$7:$H$130,"<>Not started",'EL institution summary'!$N$7:$N$130,0)
J12: "no qualifying scheme verified through the documented search"
A15: Current qualifying schemes by academic reach | H15: Breakdown by country / region group
A16: Academic reach | B16: Schemes | C16: Institutions with ≥1 | D16: Share of qualifying schemes | H16: Region group | I16: In scope | J16: Reviewed (full+partial) | K16: With ≥1 qualifying | L16: Qualifying schemes | M16: University-wide qualifying
A17: University-wide | B17: =COUNTIFS('EL scheme register'!$C$7:$C$610,A17,'EL scheme register'!$AJ$7:$AJ$610,"Yes") | C17: =COUNTIF('EL institution summary'!$I$7:$I$130,">0") | D17: =IF(SUM($B$17:$B$21)=0,"n/a",B17/SUM($B$17:$B$21)) | H17: UK – Russell Group | I17: =COUNTIF('EL institution summary'!$E$7:$E$130,H17) | J17: =COUNTIFS('EL institution summary'!$E$7:$E$130,H17,'EL institution summary'!$H$7:$H$130,"<>Not started") | K17: =COUNTIFS('EL institution summary'!$E$7:$E$130,H17,'EL institution summary'!$N$7:$N$130,">0") | L17: =COUNTIFS('EL scheme register'!$AP$7:$AP$610,H17,'EL scheme register'!$AJ$7:$AJ$610,"Yes") | M17: =COUNTIFS('EL scheme register'!$AP$7:$AP$610,H17,'EL scheme register'!$AJ$7:$AJ$610,"Yes",'EL scheme register'!$C$7:$C$610,"University-wide")
A18: Cross-faculty | B18: =COUNTIFS('EL scheme register'!$C$7:$C$610,A18,'EL scheme register'!$AJ$7:$AJ$610,"Yes") | C18: =COUNTIF('EL institution summary'!$J$7:$J$130,">0") | D18: =IF(SUM($B$17:$B$21)=0,"n/a",B18/SUM($B$17:$B$21)) | H18: UK – additional | I18: =COUNTIF('EL institution summary'!$E$7:$E$130,H18) | J18: =COUNTIFS('EL institution summary'!$E$7:$E$130,H18,'EL institution summary'!$H$7:$H$130,"<>Not started") | K18: =COUNTIFS('EL institution summary'!$E$7:$E$130,H18,'EL institution summary'!$N$7:$N$130,">0") | L18: =COUNTIFS('EL scheme register'!$AP$7:$AP$610,H18,'EL scheme register'!$AJ$7:$AJ$610,"Yes") | M18: =COUNTIFS('EL scheme register'!$AP$7:$AP$610,H18,'EL scheme register'!$AJ$7:$AJ$610,"Yes",'EL scheme register'!$C$7:$C$610,"University-wide")
A19: Faculty/school | B19: =COUNTIFS('EL scheme register'!$C$7:$C$610,A19,'EL scheme register'!$AJ$7:$AJ$610,"Yes") | C19: =COUNTIF('EL institution summary'!$K$7:$K$130,">0") | D19: =IF(SUM($B$17:$B$21)=0,"n/a",B19/SUM($B$17:$B$21)) | H19: Australia | I19: =COUNTIF('EL institution summary'!$E$7:$E$130,H19) | J19: =COUNTIFS('EL institution summary'!$E$7:$E$130,H19,'EL institution summary'!$H$7:$H$130,"<>Not started") | K19: =COUNTIFS('EL institution summary'!$E$7:$E$130,H19,'EL institution summary'!$N$7:$N$130,">0") | L19: =COUNTIFS('EL scheme register'!$AP$7:$AP$610,H19,'EL scheme register'!$AJ$7:$AJ$610,"Yes") | M19: =COUNTIFS('EL scheme register'!$AP$7:$AP$610,H19,'EL scheme register'!$AJ$7:$AJ$610,"Yes",'EL scheme register'!$C$7:$C$610,"University-wide")
A20: Programme/course | B20: =COUNTIFS('EL scheme register'!$C$7:$C$610,A20,'EL scheme register'!$AJ$7:$AJ$610,"Yes") | C20: =COUNTIF('EL institution summary'!$L$7:$L$130,">0") | D20: =IF(SUM($B$17:$B$21)=0,"n/a",B20/SUM($B$17:$B$21)) | H20: US | I20: =COUNTIF('EL institution summary'!$E$7:$E$130,H20) | J20: =COUNTIFS('EL institution summary'!$E$7:$E$130,H20,'EL institution summary'!$H$7:$H$130,"<>Not started") | K20: =COUNTIFS('EL institution summary'!$E$7:$E$130,H20,'EL institution summary'!$N$7:$N$130,">0") | L20: =COUNTIFS('EL scheme register'!$AP$7:$AP$610,H20,'EL scheme register'!$AJ$7:$AJ$610,"Yes") | M20: =COUNTIFS('EL scheme register'!$AP$7:$AP$610,H20,'EL scheme register'!$AJ$7:$AJ$610,"Yes",'EL scheme register'!$C$7:$C$610,"University-wide")
A21: Unclear | B21: =COUNTIFS('EL scheme register'!$C$7:$C$610,A21,'EL scheme register'!$AJ$7:$AJ$610,"Yes") | C21: =COUNTIF('EL institution summary'!$M$7:$M$130,">0") | D21: =IF(SUM($B$17:$B$21)=0,"n/a",B21/SUM($B$17:$B$21)) | H21: EU | I21: =COUNTIF('EL institution summary'!$E$7:$E$130,H21) | J21: =COUNTIFS('EL institution summary'!$E$7:$E$130,H21,'EL institution summary'!$H$7:$H$130,"<>Not started") | K21: =COUNTIFS('EL institution summary'!$E$7:$E$130,H21,'EL institution summary'!$N$7:$N$130,">0") | L21: =COUNTIFS('EL scheme register'!$AP$7:$AP$610,H21,'EL scheme register'!$AJ$7:$AJ$610,"Yes") | M21: =COUNTIFS('EL scheme register'!$AP$7:$AP$610,H21,'EL scheme register'!$AJ$7:$AJ$610,"Yes",'EL scheme register'!$C$7:$C$610,"University-wide")
A22: Total | B22: =SUM(B17:B21) | C22: =COUNTIF('EL institution summary'!$N$7:$N$130,">0") | H22: Total | I22: =SUM(I17:I21) | J22: =SUM(J17:J21) | K22: =SUM(K17:K21) | L22: =SUM(L17:L21) | M22: =SUM(M17:M21)
A24: University-wide qualifying schemes: optional access vs compulsory provision
A25: Participation requirement | B25: Schemes | C25: Institutions | H25: By country
A26: Compulsory for all students (at stated level) | B26: =COUNTIFS('EL scheme register'!$C$7:$C$610,"University-wide",'EL scheme register'!$Q$7:$Q$610,A26,'EL scheme register'!$AJ$7:$AJ$610,"Yes") | C26: =SUMPRODUCT(('EL institution summary'!$A$7:$A$130<>"")/COUNTIF('EL institution summary'!$A$7:$A$130,'EL institution summary'!$A$7:$A$130&"")*(COUNTIFS('EL scheme register'!$A$7:$A$610,'EL institution summary'!$A$7:$A$130,'EL scheme register'!$C$7:$C$610,"University-wide",'EL scheme register'!$Q$7:$Q$610,A26,'EL scheme register'!$AJ$7:$AJ$610,"Yes")>0)) | H26: Country | I26: In scope | J26: Reviewed | K26: With ≥1 qualifying | L26: Qualifying schemes
A27: Compulsory within specified programmes | B27: =COUNTIFS('EL scheme register'!$C$7:$C$610,"University-wide",'EL scheme register'!$Q$7:$Q$610,A27,'EL scheme register'!$AJ$7:$AJ$610,"Yes") | C27: =SUMPRODUCT(('EL institution summary'!$A$7:$A$130<>"")/COUNTIF('EL institution summary'!$A$7:$A$130,'EL institution summary'!$A$7:$A$130&"")*(COUNTIFS('EL scheme register'!$A$7:$A$610,'EL institution summary'!$A$7:$A$130,'EL scheme register'!$C$7:$C$610,"University-wide",'EL scheme register'!$Q$7:$Q$610,A27,'EL scheme register'!$AJ$7:$AJ$610,"Yes")>0)) | H27: Australia | I27: =COUNTIF('EL institution summary'!$C$7:$C$130,H27) | J27: =COUNTIFS('EL institution summary'!$C$7:$C$130,H27,'EL institution summary'!$H$7:$H$130,"<>Not started") | K27: =COUNTIFS('EL institution summary'!$C$7:$C$130,H27,'EL institution summary'!$N$7:$N$130,">0") | L27: =COUNTIFS('EL scheme register'!$AO$7:$AO$610,H27,'EL scheme register'!$AJ$7:$AJ$610,"Yes")
A28: Optional/elective | B28: =COUNTIFS('EL scheme register'!$C$7:$C$610,"University-wide",'EL scheme register'!$Q$7:$Q$610,A28,'EL scheme register'!$AJ$7:$AJ$610,"Yes") | C28: =SUMPRODUCT(('EL institution summary'!$A$7:$A$130<>"")/COUNTIF('EL institution summary'!$A$7:$A$130,'EL institution summary'!$A$7:$A$130&"")*(COUNTIFS('EL scheme register'!$A$7:$A$610,'EL institution summary'!$A$7:$A$130,'EL scheme register'!$C$7:$C$610,"University-wide",'EL scheme register'!$Q$7:$Q$610,A28,'EL scheme register'!$AJ$7:$AJ$610,"Yes")>0)) | H28: UK | I28: =COUNTIF('EL institution summary'!$C$7:$C$130,H28) | J28: =COUNTIFS('EL institution summary'!$C$7:$C$130,H28,'EL institution summary'!$H$7:$H$130,"<>Not started") | K28: =COUNTIFS('EL institution summary'!$C$7:$C$130,H28,'EL institution summary'!$N$7:$N$130,">0") | L28: =COUNTIFS('EL scheme register'!$AO$7:$AO$610,H28,'EL scheme register'!$AJ$7:$AJ$610,"Yes")
A29: Selective/competitive | B29: =COUNTIFS('EL scheme register'!$C$7:$C$610,"University-wide",'EL scheme register'!$Q$7:$Q$610,A29,'EL scheme register'!$AJ$7:$AJ$610,"Yes") | C29: =SUMPRODUCT(('EL institution summary'!$A$7:$A$130<>"")/COUNTIF('EL institution summary'!$A$7:$A$130,'EL institution summary'!$A$7:$A$130&"")*(COUNTIFS('EL scheme register'!$A$7:$A$610,'EL institution summary'!$A$7:$A$130,'EL scheme register'!$C$7:$C$610,"University-wide",'EL scheme register'!$Q$7:$Q$610,A29,'EL scheme register'!$AJ$7:$AJ$610,"Yes")>0)) | H29: US | I29: =COUNTIF('EL institution summary'!$C$7:$C$130,H29) | J29: =COUNTIFS('EL institution summary'!$C$7:$C$130,H29,'EL institution summary'!$H$7:$H$130,"<>Not started") | K29: =COUNTIFS('EL institution summary'!$C$7:$C$130,H29,'EL institution summary'!$N$7:$N$130,">0") | L29: =COUNTIFS('EL scheme register'!$AO$7:$AO$610,H29,'EL scheme register'!$AJ$7:$AJ$610,"Yes")
A30: Unclear | B30: =COUNTIFS('EL scheme register'!$C$7:$C$610,"University-wide",'EL scheme register'!$Q$7:$Q$610,A30,'EL scheme register'!$AJ$7:$AJ$610,"Yes") | C30: =SUMPRODUCT(('EL institution summary'!$A$7:$A$130<>"")/COUNTIF('EL institution summary'!$A$7:$A$130,'EL institution summary'!$A$7:$A$130&"")*(COUNTIFS('EL scheme register'!$A$7:$A$610,'EL institution summary'!$A$7:$A$130,'EL scheme register'!$C$7:$C$610,"University-wide",'EL scheme register'!$Q$7:$Q$610,A30,'EL scheme register'!$AJ$7:$AJ$610,"Yes")>0)) | H30: Belgium | I30: =COUNTIF('EL institution summary'!$C$7:$C$130,H30) | J30: =COUNTIFS('EL institution summary'!$C$7:$C$130,H30,'EL institution summary'!$H$7:$H$130,"<>Not started") | K30: =COUNTIFS('EL institution summary'!$C$7:$C$130,H30,'EL institution summary'!$N$7:$N$130,">0") | L30: =COUNTIFS('EL scheme register'!$AO$7:$AO$610,H30,'EL scheme register'!$AJ$7:$AJ$610,"Yes")
H31: Denmark | I31: =COUNTIF('EL institution summary'!$C$7:$C$130,H31) | J31: =COUNTIFS('EL institution summary'!$C$7:$C$130,H31,'EL institution summary'!$H$7:$H$130,"<>Not started") | K31: =COUNTIFS('EL institution summary'!$C$7:$C$130,H31,'EL institution summary'!$N$7:$N$130,">0") | L31: =COUNTIFS('EL scheme register'!$AO$7:$AO$610,H31,'EL scheme register'!$AJ$7:$AJ$610,"Yes")
A32: Current qualifying schemes by external partner type (business-linked vs public/community) | H32: Finland | I32: =COUNTIF('EL institution summary'!$C$7:$C$130,H32) | J32: =COUNTIFS('EL institution summary'!$C$7:$C$130,H32,'EL institution summary'!$H$7:$H$130,"<>Not started") | K32: =COUNTIFS('EL institution summary'!$C$7:$C$130,H32,'EL institution summary'!$N$7:$N$130,">0") | L32: =COUNTIFS('EL scheme register'!$AO$7:$AO$610,H32,'EL scheme register'!$AJ$7:$AJ$610,"Yes")
A33: Partner type | B33: Schemes | C33: Institutions | H33: France | I33: =COUNTIF('EL institution summary'!$C$7:$C$130,H33) | J33: =COUNTIFS('EL institution summary'!$C$7:$C$130,H33,'EL institution summary'!$H$7:$H$130,"<>Not started") | K33: =COUNTIFS('EL institution summary'!$C$7:$C$130,H33,'EL institution summary'!$N$7:$N$130,">0") | L33: =COUNTIFS('EL scheme register'!$AO$7:$AO$610,H33,'EL scheme register'!$AJ$7:$AJ$610,"Yes")
A34: Business/commercial | B34: =COUNTIFS('EL scheme register'!$AB$7:$AB$610,A34,'EL scheme register'!$AJ$7:$AJ$610,"Yes") | C34: =SUMPRODUCT(('EL institution summary'!$A$7:$A$130<>"")/COUNTIF('EL institution summary'!$A$7:$A$130,'EL institution summary'!$A$7:$A$130&"")*(COUNTIFS('EL scheme register'!$A$7:$A$610,'EL institution summary'!$A$7:$A$130,'EL scheme register'!$AB$7:$AB$610,A34,'EL scheme register'!$AJ$7:$AJ$610,"Yes")>0)) | H34: Germany | I34: =COUNTIF('EL institution summary'!$C$7:$C$130,H34) | J34: =COUNTIFS('EL institution summary'!$C$7:$C$130,H34,'EL institution summary'!$H$7:$H$130,"<>Not started") | K34: =COUNTIFS('EL institution summary'!$C$7:$C$130,H34,'EL institution summary'!$N$7:$N$130,">0") | L34: =COUNTIFS('EL scheme register'!$AO$7:$AO$610,H34,'EL scheme register'!$AJ$7:$AJ$610,"Yes")
A35: Public sector | B35: =COUNTIFS('EL scheme register'!$AB$7:$AB$610,A35,'EL scheme register'!$AJ$7:$AJ$610,"Yes") | C35: =SUMPRODUCT(('EL institution summary'!$A$7:$A$130<>"")/COUNTIF('EL institution summary'!$A$7:$A$130,'EL institution summary'!$A$7:$A$130&"")*(COUNTIFS('EL scheme register'!$A$7:$A$610,'EL institution summary'!$A$7:$A$130,'EL scheme register'!$AB$7:$AB$610,A35,'EL scheme register'!$AJ$7:$AJ$610,"Yes")>0)) | H35: Ireland | I35: =COUNTIF('EL institution summary'!$C$7:$C$130,H35) | J35: =COUNTIFS('EL institution summary'!$C$7:$C$130,H35,'EL institution summary'!$H$7:$H$130,"<>Not started") | K35: =COUNTIFS('EL institution summary'!$C$7:$C$130,H35,'EL institution summary'!$N$7:$N$130,">0") | L35: =COUNTIFS('EL scheme register'!$AO$7:$AO$610,H35,'EL scheme register'!$AJ$7:$AJ$610,"Yes")
A36: Charity/community | B36: =COUNTIFS('EL scheme register'!$AB$7:$AB$610,A36,'EL scheme register'!$AJ$7:$AJ$610,"Yes") | C36: =SUMPRODUCT(('EL institution summary'!$A$7:$A$130<>"")/COUNTIF('EL institution summary'!$A$7:$A$130,'EL institution summary'!$A$7:$A$130&"")*(COUNTIFS('EL scheme register'!$A$7:$A$610,'EL institution summary'!$A$7:$A$130,'EL scheme register'!$AB$7:$AB$610,A36,'EL scheme register'!$AJ$7:$AJ$610,"Yes")>0)) | H36: Italy | I36: =COUNTIF('EL institution summary'!$C$7:$C$130,H36) | J36: =COUNTIFS('EL institution summary'!$C$7:$C$130,H36,'EL institution summary'!$H$7:$H$130,"<>Not started") | K36: =COUNTIFS('EL institution summary'!$C$7:$C$130,H36,'EL institution summary'!$N$7:$N$130,">0") | L36: =COUNTIFS('EL scheme register'!$AO$7:$AO$610,H36,'EL scheme register'!$AJ$7:$AJ$610,"Yes")
A37: Mixed | B37: =COUNTIFS('EL scheme register'!$AB$7:$AB$610,A37,'EL scheme register'!$AJ$7:$AJ$610,"Yes") | C37: =SUMPRODUCT(('EL institution summary'!$A$7:$A$130<>"")/COUNTIF('EL institution summary'!$A$7:$A$130,'EL institution summary'!$A$7:$A$130&"")*(COUNTIFS('EL scheme register'!$A$7:$A$610,'EL institution summary'!$A$7:$A$130,'EL scheme register'!$AB$7:$AB$610,A37,'EL scheme register'!$AJ$7:$AJ$610,"Yes")>0)) | H37: Netherlands | I37: =COUNTIF('EL institution summary'!$C$7:$C$130,H37) | J37: =COUNTIFS('EL institution summary'!$C$7:$C$130,H37,'EL institution summary'!$H$7:$H$130,"<>Not started") | K37: =COUNTIFS('EL institution summary'!$C$7:$C$130,H37,'EL institution summary'!$N$7:$N$130,">0") | L37: =COUNTIFS('EL scheme register'!$AO$7:$AO$610,H37,'EL scheme register'!$AJ$7:$AJ$610,"Yes")
A38: Other | B38: =COUNTIFS('EL scheme register'!$AB$7:$AB$610,A38,'EL scheme register'!$AJ$7:$AJ$610,"Yes") | C38: =SUMPRODUCT(('EL institution summary'!$A$7:$A$130<>"")/COUNTIF('EL institution summary'!$A$7:$A$130,'EL institution summary'!$A$7:$A$130&"")*(COUNTIFS('EL scheme register'!$A$7:$A$610,'EL institution summary'!$A$7:$A$130,'EL scheme register'!$AB$7:$AB$610,A38,'EL scheme register'!$AJ$7:$AJ$610,"Yes")>0)) | H38: Spain | I38: =COUNTIF('EL institution summary'!$C$7:$C$130,H38) | J38: =COUNTIFS('EL institution summary'!$C$7:$C$130,H38,'EL institution summary'!$H$7:$H$130,"<>Not started") | K38: =COUNTIFS('EL institution summary'!$C$7:$C$130,H38,'EL institution summary'!$N$7:$N$130,">0") | L38: =COUNTIFS('EL scheme register'!$AO$7:$AO$610,H38,'EL scheme register'!$AJ$7:$AJ$610,"Yes")
A39: Unclear | B39: =COUNTIFS('EL scheme register'!$AB$7:$AB$610,A39,'EL scheme register'!$AJ$7:$AJ$610,"Yes") | C39: =SUMPRODUCT(('EL institution summary'!$A$7:$A$130<>"")/COUNTIF('EL institution summary'!$A$7:$A$130,'EL institution summary'!$A$7:$A$130&"")*(COUNTIFS('EL scheme register'!$A$7:$A$610,'EL institution summary'!$A$7:$A$130,'EL scheme register'!$AB$7:$AB$610,A39,'EL scheme register'!$AJ$7:$AJ$610,"Yes")>0)) | H39: Sweden | I39: =COUNTIF('EL institution summary'!$C$7:$C$130,H39) | J39: =COUNTIFS('EL institution summary'!$C$7:$C$130,H39,'EL institution summary'!$H$7:$H$130,"<>Not started") | K39: =COUNTIFS('EL institution summary'!$C$7:$C$130,H39,'EL institution summary'!$N$7:$N$130,">0") | L39: =COUNTIFS('EL scheme register'!$AO$7:$AO$610,H39,'EL scheme register'!$AJ$7:$AJ$610,"Yes")
A40: None | B40: =COUNTIFS('EL scheme register'!$AB$7:$AB$610,A40,'EL scheme register'!$AJ$7:$AJ$610,"Yes") | C40: =SUMPRODUCT(('EL institution summary'!$A$7:$A$130<>"")/COUNTIF('EL institution summary'!$A$7:$A$130,'EL institution summary'!$A$7:$A$130&"")*(COUNTIFS('EL scheme register'!$A$7:$A$610,'EL institution summary'!$A$7:$A$130,'EL scheme register'!$AB$7:$AB$610,A40,'EL scheme register'!$AJ$7:$AJ$610,"Yes")>0))
A42: Evidence status of all register records (counted schemes only; umbrellas excluded)
A43: Category | B43: Records
A44: Meets all three; current delivery confirmed | B44: =COUNTIFS('EL scheme register'!$AF$7:$AF$610,"Meets all three",'EL scheme register'!$AG$7:$AG$610,"Current delivery confirmed",'EL scheme register'!$AI$7:$AI$610,"Yes")
A45: Meets all three; current status unclear | B45: =COUNTIFS('EL scheme register'!$AF$7:$AF$610,"Meets all three",'EL scheme register'!$AG$7:$AG$610,"Current status unclear",'EL scheme register'!$AI$7:$AI$610,"Yes")
A46: Meets all three; historical / paused only | B46: =COUNTIFS('EL scheme register'!$AF$7:$AF$610,"Meets all three",'EL scheme register'!$AG$7:$AG$610,"Historical delivery only",'EL scheme register'!$AI$7:$AI$610,"Yes")+COUNTIFS('EL scheme register'!$AF$7:$AF$610,"Meets all three",'EL scheme register'!$AG$7:$AG$610,"Paused/discontinued",'EL scheme register'!$AI$7:$AI$610,"Yes")
A47: Meets all three; announced / forthcoming | B47: =COUNTIFS('EL scheme register'!$AF$7:$AF$610,"Meets all three",'EL scheme register'!$AG$7:$AG$610,"Announced/forthcoming",'EL scheme register'!$AI$7:$AI$610,"Yes")
A48: Potentially relevant; evidence incomplete | B48: =COUNTIFS('EL scheme register'!$AF$7:$AF$610,"Potentially relevant; evidence incomplete",'EL scheme register'!$AI$7:$AI$610,"Yes")
A49: Outside strict definition (kept in register as near-miss) | B49: =COUNTIFS('EL scheme register'!$AF$7:$AF$610,"Outside strict definition",'EL scheme register'!$AI$7:$AI$610,"Yes")
A50: memo: current qualifying schemes lasting <1 week | B50: =COUNTIFS('EL scheme register'!$AQ$7:$AQ$610,"<1 week",'EL scheme register'!$AJ$7:$AJ$610,"Yes")
A51: Excluded / near-miss / evidence-gap records (exclusions tab) | B51: =COUNTA('EL exclusions & gaps'!$A$7:$A$5000)
A52: of which from legacy research | B52: =COUNTIF('EL exclusions & gaps'!$F$7:$F$5000,"Yes")
A55: Reading the dashboard
A56: • Denominators are shown; 'with ≥1 qualifying' should be read against reviewed institutions, not the full 124 if any remain unreviewed.
A57: • University-wide = published eligibility open across the institution (subject to stated restrictions). It does not mean every student participates; compulsory university-wide provision is counted separately.
A58: • Business-linked schemes are those whose external partners are Business/commercial; Mixed schemes include business and public/charity clients. Public-sector and charity-only schemes are shown separately.
A59: • 'Evidence incomplete' = no criterion failed, but at least one is Unclear. These are not negative findings.
A60: • Evidence was gathered from search-index extracts of official pages (direct page fetching was blocked); see EL method & QC.

Sheet EL institution summary
A2: Experiential learning: institution summary
A3: One row per institution in the 124-institution sample. Counts are live formulas over 'EL scheme register' (column AJ = counted, meets all three, current).
A4: Findings within the researched sample, not national prevalence estimates. 'Not started' / 'Partial' institutions must not be read as negative findings. No composite score is used.
A6: Institution ID | B6: Institution | C6: Country | D6: Sample group | E6: Region group | F6: QS edition | G6: QS rank | H6: Review completeness | I6: Qualifying current: University-wide | J6: Qualifying current: Cross-faculty | K6: Qualifying current: Faculty/school | L6: Qualifying current: Programme/course | M6: Qualifying current: Unclear reach | N6: Qualifying current: total | O6: Evidence-incomplete records | P6: Outside-definition records in register | Q6: Exclusions / near-misses | R6: University-wide access evidenced (qualifying current scheme) | S6: Compulsory university-wide provision evidenced | T6: Main qualifying schemes | U6: Distribution across faculty areas (qualifying current) | V6: How embedded the provision appears | W6: Concise assessment | X6: Material gaps and unresolved questions
A7: RG01 | B7: Birmingham | C7: UK | D7: Russell Group | E7: UK – Russell Group | F7: 2027 | G7: 68 | H7: Complete | I7: =COUNTIFS('EL scheme register'!$A$7:$A$610,$A7,'EL scheme register'!$C$7:$C$610,"University-wide",'EL scheme register'!$AJ$7:$AJ$610,"Yes") | J7: =COUNTIFS('EL scheme register'!$A$7:$A$610,$A7,'EL scheme register'!$C$7:$C$610,"Cross-faculty",'EL scheme register'!$AJ$7:$AJ$610,"Yes") | K7: =COUNTIFS('EL scheme register'!$A$7:$A$610,$A7,'EL scheme register'!$C$7:$C$610,"Faculty/school",'EL scheme register'!$AJ$7:$AJ$610,"Yes") | L7: =COUNTIFS('EL scheme register'!$A$7:$A$610,$A7,'EL scheme register'!$C$7:$C$610,"Programme/course",'EL scheme register'!$AJ$7:$AJ$610,"Yes") | M7: =COUNTIFS('EL scheme register'!$A$7:$A$610,$A7,'EL scheme register'!$C$7:$C$610,"Unclear",'EL scheme register'!$AJ$7:$AJ$610,"Yes") | N7: =SUM(I7:M7) | O7: =COUNTIFS('EL scheme register'!$A$7:$A$610,$A7,'EL scheme register'!$AF$7:$AF$610,"Potentially relevant; evidence incomplete",'EL scheme register'!$AI$7:$AI$610,"Yes") | P7: =COUNTIFS('EL scheme register'!$A$7:$A$610,$A7,'EL scheme register'!$AF$7:$AF$610,"Outside strict definition") | Q7: =COUNTIF('EL exclusions & gaps'!$B$7:$B$5000,$A7) | R7: Yes | S7: Not evidenced | T7: The Birmingham Project [University-wide]; Masters Consultancy Challenge (MCC) [University-wide]; Impact Challenge [University-wide]; Capgemini Community Challenge [Cross-faculty] | U7: Central provision: 3; Business/management: 1; Engineering/computing: 1; Science: 1 | V7: Several distributed routes | W7: Birmingham has several distributed live-project routes. Most are short, extracurricular and centrally run, with smaller programme-embedded provision in the Business School. - Central (Careers Network): - The Birmingham Project is open to all first-year undergraduates on the Edgbaston campus. It is optional, non-credit and recorded as pass/fail on the transcript. Interdisciplinary teams spend one full-time week in June on challenges set by 7–8 employer partners in 2026 (e.g. HSBC, Siemens, Transport for West Midlands, West Midlands Combined Authority). Each challenge has an industry professional, and teams finish with a group video presentation to industry and academics. More than 2,000 students have taken part since 2013. - The Masters Consultancy Challenge is selective and open to taught postgraduates. Interdisciplinary groups work for 3 weeks on a Turner & Townsend challenge and present to an industry and University panel. - The Impact Challenge is a paid, week-long programme for widening-participation finalists and penultimate-year students. Teams work on employer-set projects, mostly for charities and social enterprises. - Business School: - The Capgemini Community Challenge is | X7: Further departmental instances likely. Engineering group design projects lack evidence of industry-set briefs. Current-year evidence missing for SMC MSc and Company Projects. Maths Mathematical Challenge module partner/team format unverified. Education, Psychology and Biosciences only lightly searched. Birmingham Project partner count conflict (7 vs 8). Capgemini eligibility conflict.
A8: RG02 | B8: Bristol | C8: UK | D8: Russell Group | E8: UK – Russell Group | F8: 2027 | G8: 57 | H8: Complete | I8: =COUNTIFS('EL scheme register'!$A$7:$A$610,$A8,'EL scheme register'!$C$7:$C$610,"University-wide",'EL scheme register'!$AJ$7:$AJ$610,"Yes") | J8: =COUNTIFS('EL scheme register'!$A$7:$A$610,$A8,'EL scheme register'!$C$7:$C$610,"Cross-faculty",'EL scheme register'!$AJ$7:$AJ$610,"Yes") | K8: =COUNTIFS('EL scheme register'!$A$7:$A$610,$A8,'EL scheme register'!$C$7:$C$610,"Faculty/school",'EL scheme register'!$AJ$7:$AJ$610,"Yes") | L8: =COUNTIFS('EL scheme register'!$A$7:$A$610,$A8,'EL scheme register'!$C$7:$C$610,"Programme/course",'EL scheme register'!$AJ$7:$AJ$610,"Yes") | M8: =COUNTIFS('EL scheme register'!$A$7:$A$610,$A8,'EL scheme register'!$C$7:$C$610,"Unclear",'EL scheme register'!$AJ$7:$AJ$610,"Yes") | N8: =SUM(I8:M8) | O8: =COUNTIFS('EL scheme register'!$A$7:$A$610,$A8,'EL scheme register'!$AF$7:$AF$610,"Potentially relevant; evidence incomplete",'EL scheme register'!$AI$7:$AI$610,"Yes") | P8: =COUNTIFS('EL scheme register'!$A$7:$A$610,$A8,'EL scheme register'!$AF$7:$AF$610,"Outside strict definition") | Q8: =COUNTIF('EL exclusions & gaps'!$B$7:$B$5000,$A8) | R8: Not evidenced | S8: Not evidenced | T8: Mathematical and Data Modelling 3 (SEMT30005) [Programme/course]; Management Consultancy (EFIM30064) [Programme/course]; Business School Micro-Internship programme [Faculty/school]; The Marketing Applied Extended Project (AEP) - applied group route (MSc Marketing) (MGRCM0040) [Programme/course]; Human Rights Law Clinic (Human Rights Implementation Centre) [Faculty/school] | U8: Business/management: 3; Engineering/computing: 1; Other (law, health, design, architecture…): 1 | V8: Several distributed routes | W8: Bristol has no university-wide, compulsory employer-project scheme; qualifying provision is distributed across schools, with the Industrial Liaison Office (Faculty of Science and Engineering) acting as the main broker of client briefs. Verified current routes. Engineering Mathematics' Mathematical and Data Modelling 3 (2026/27) puts groups of 4-6 on three six-week problems, two supplied by industrial partners. The Business School's final-year Management Consultancy (EFIM30064, 2025/26) places groups of 4-6 on briefs from outside organisations, mostly charities. The Business School Micro-Internship (200 Masters places, 3 weeks, extracurricular) assigns random teams to an industry client. The MSc Marketing applied project (small group, external commercial/third-sector partners) and the Law School's selective Human Rights Law Clinic (student-led teams researching to partner briefs, ~70 members) are also current. Credible but not currently evidenced. Undergraduate Software Engineering Project and MSc Summer Team Project (client-proposed, teams of 4-6) rest on undated ILO pages; Geography's Consultancy Project (3-5 student teams, external clients) appears only in a mislabelled catalogue | X8: Further departmental instances likely (Aerospace/Electrical MEng industrial group design projects, Computer Science AI software team project, other MSc business projects, Veterinary/Medicine/Dentistry/Architecture community or client projects not found). Unit catalogue results often carry unreliable future year labels (2031-2038) so several units lack genuine current-year evidence. Partner names and cohort sizes mostly unpublished. Humanities/social science client-team units not found. 38 searches used; Open Unit lists not examined unit by unit.
A9: RG03 | B9: Cambridge | C9: UK | D9: Russell Group | E9: UK – Russell Group | F9: 2027 | G9: 6 | H9: Complete | I9: =COUNTIFS('EL scheme register'!$A$7:$A$610,$A9,'EL scheme register'!$C$7:$C$610,"University-wide",'EL scheme register'!$AJ$7:$AJ$610,"Yes") | J9: =COUNTIFS('EL scheme register'!$A$7:$A$610,$A9,'EL scheme register'!$C$7:$C$610,"Cross-faculty",'EL scheme register'!$AJ$7:$AJ$610,"Yes") | K9: =COUNTIFS('EL scheme register'!$A$7:$A$610,$A9,'EL scheme register'!$C$7:$C$610,"Faculty/school",'EL scheme register'!$AJ$7:$AJ$610,"Yes") | L9: =COUNTIFS('EL scheme register'!$A$7:$A$610,$A9,'EL scheme register'!$C$7:$C$610,"Programme/course",'EL scheme register'!$AJ$7:$AJ$610,"Yes") | M9: =COUNTIFS('EL scheme register'!$A$7:$A$610,$A9,'EL scheme register'!$C$7:$C$610,"Unclear",'EL scheme register'!$AJ$7:$AJ$610,"Yes") | N9: =SUM(I9:M9) | O9: =COUNTIFS('EL scheme register'!$A$7:$A$610,$A9,'EL scheme register'!$AF$7:$AF$610,"Potentially relevant; evidence incomplete",'EL scheme register'!$AI$7:$AI$610,"Yes") | P9: =COUNTIFS('EL scheme register'!$A$7:$A$610,$A9,'EL scheme register'!$AF$7:$AF$610,"Outside strict definition") | Q9: =COUNTIF('EL exclusions & gaps'!$B$7:$B$5000,$A9) | R9: Not evidenced | S9: Not evidenced | T9: MBA Global Consulting Project (GCP) [Programme/course]; MBA Cambridge Venture Project (CVP) [Programme/course]; MFin Group Consulting Project (GCP) [Programme/course]; MPhil in Management: Management Consulting Project [Programme/course]; Management Studies Tripos (MST) consulting project [Programme/course]; MPhil in Technology Policy: Final Group Project [Programme/course]; Computer Science Tripos Part IB Group Project [Programme/course] | U9: Business/management: 6; Engineering/computing: 2 | V9: Several distributed routes | W9: Cambridge has no institution-wide employer-project scheme; provision is concentrated in a few programme-embedded routes. Cambridge Judge Business School runs the densest set: the MBA Global Consulting Project (4-5 students, ~4 weeks, hosts such as WHO and Uber) and Cambridge Venture Project (5-6 students, ~6 weeks, local businesses), the MFin Group Consulting Project, the MPhil in Management Consulting Project, the undergraduate Management Studies Tripos project (teams of 3-4 for external organisations), and the MPhil in Technology Policy Final Group Project (clients including Cabinet Office, Ofcom, Arm). Each is part of a degree, uses a central client-proposal process with 2026/27 calls, and relies on external organisations as clients who receive the output. Outside business, the Computer Science Tripos Part IB group project is the standout: a compulsory seven-week team project for an assigned industry client, with 2026 clients including Nokia Bell Labs and Bending Spoons. Further routes exist in Engineering (IfM MET/ISMM company projects, ESD MPhil Client Project), Bioscience Enterprise and Public Policy/Conservation Leadership, but these lack dated current evidence. The universi | X9: Further departmental instances likely (other MPhils, Engineering Part IIA group projects, Chemical Engineering, Medicine, Architecture, Law, Education not individually searched). Credit/weighting and 'compulsory' wording not retrieved for most JBS projects (inferred from core-curriculum placement). MET/ISMM, ESD, MBE, Bennett PAE and Conservation Leadership need dated 2025/26-2026/27 corroboration. Student societies (180 Degrees Consulting, Cambridge Consulting Network) and Cambridge Hub not verified. WebFetch unavailable; all evidence is search-index extract/paraphrase.
A10: RG04 | B10: Cardiff | C10: UK | D10: Russell Group | E10: UK – Russell Group | F10: 2027 | G10: 179 | H10: Complete | I10: =COUNTIFS('EL scheme register'!$A$7:$A$610,$A10,'EL scheme register'!$C$7:$C$610,"University-wide",'EL scheme register'!$AJ$7:$AJ$610,"Yes") | J10: =COUNTIFS('EL scheme register'!$A$7:$A$610,$A10,'EL scheme register'!$C$7:$C$610,"Cross-faculty",'EL scheme register'!$AJ$7:$AJ$610,"Yes") | K10: =COUNTIFS('EL scheme register'!$A$7:$A$610,$A10,'EL scheme register'!$C$7:$C$610,"Faculty/school",'EL scheme register'!$AJ$7:$AJ$610,"Yes") | L10: =COUNTIFS('EL scheme register'!$A$7:$A$610,$A10,'EL scheme register'!$C$7:$C$610,"Programme/course",'EL scheme register'!$AJ$7:$AJ$610,"Yes") | M10: =COUNTIFS('EL scheme register'!$A$7:$A$610,$A10,'EL scheme register'!$C$7:$C$610,"Unclear",'EL scheme register'!$AJ$7:$AJ$610,"Yes") | N10: =SUM(I10:M10) | O10: =COUNTIFS('EL scheme register'!$A$7:$A$610,$A10,'EL scheme register'!$AF$7:$AF$610,"Potentially relevant; evidence incomplete",'EL scheme register'!$AI$7:$AI$610,"Yes") | P10: =COUNTIFS('EL scheme register'!$A$7:$A$610,$A10,'EL scheme register'!$AF$7:$AF$610,"Outside strict definition") | Q10: =COUNTIF('EL exclusions & gaps'!$B$7:$B$5000,$A10) | R10: Not evidenced | S10: Not evidenced | T10: BSc Applied Software Engineering: client-based team projects (National Software Academy) [Programme/course] | U10: Engineering/computing: 1 | V10: Several distributed routes | W10: Cardiff has employer-linked group project provision concentrated in computing and the Business School (mostly postgraduate). No university-wide route was verified. - Clearest current route: the National Software Academy's BSc Applied Software Engineering builds team client projects into the degree. Teams build software for real private, public and third-sector clients over projects of about four weeks, meeting clients fortnightly (2026-entry page). - Business School: - The MSc Strategic Entrepreneurship and Innovation New Venture Plan (BST413, 40 credits; optional instead of a dissertation) assigns each group a real company client that sets the brief. - The MBA Management Consultancy elective, co-run with PA Consulting, sends teams to Welsh charities (e.g. Tenovus Cancer Care, WCVA). - The current status of both is undated. - The MBA live/Accelerator project (corporate client) and the MSc Business Management Consultancy Challenge (charity clients only 'may') are incomplete on group work or external coverage. - Planning: MSc Spatial Planning Live Project CPT831 has real clients such as planning authorities (group work unconfirmed). An older UG group consultancy module (CP0210) is ev | X10: Review is Partial (see partial_remaining). Key gaps: health schools not searched; science covered by one search only; group structure for MBA live project, MSc SPD Live Project and architecture live projects; whether MSc Business Management Consultancy Challenge always has an external client; dated 2025/26 evidence for Business School routes; whether engineering MSc group projects routinely have company partners and on which programmes; Bremen-Cardiff eligibility and any external problem owner; Student Enterprise annual report content; FinTech Wales Skills Challenge and Public Value Hackathon format. Further departmental instances are likely (e.g. NSA MSc Software Engineering, Computer Science MSc, Journalism). Reduced-depth round: WebFetch returned 403 for cardiff.ac.uk so no page text was obtained; health schools and Journalism remain unverified after one search.
A11: RG05 | B11: Durham | C11: UK | D11: Russell Group | E11: UK – Russell Group | F11: 2027 | G11: 85 | H11: Complete | I11: =COUNTIFS('EL scheme register'!$A$7:$A$610,$A11,'EL scheme register'!$C$7:$C$610,"University-wide",'EL scheme register'!$AJ$7:$AJ$610,"Yes") | J11: =COUNTIFS('EL scheme register'!$A$7:$A$610,$A11,'EL scheme register'!$C$7:$C$610,"Cross-faculty",'EL scheme register'!$AJ$7:$AJ$610,"Yes") | K11: =COUNTIFS('EL scheme register'!$A$7:$A$610,$A11,'EL scheme register'!$C$7:$C$610,"Faculty/school",'EL scheme register'!$AJ$7:$AJ$610,"Yes") | L11: =COUNTIFS('EL scheme register'!$A$7:$A$610,$A11,'EL scheme register'!$C$7:$C$610,"Programme/course",'EL scheme register'!$AJ$7:$AJ$610,"Yes") | M11: =COUNTIFS('EL scheme register'!$A$7:$A$610,$A11,'EL scheme register'!$C$7:$C$610,"Unclear",'EL scheme register'!$AJ$7:$AJ$610,"Yes") | N11: =SUM(I11:M11) | O11: =COUNTIFS('EL scheme register'!$A$7:$A$610,$A11,'EL scheme register'!$AF$7:$AF$610,"Potentially relevant; evidence incomplete",'EL scheme register'!$AI$7:$AI$610,"Yes") | P11: =COUNTIFS('EL scheme register'!$A$7:$A$610,$A11,'EL scheme register'!$AF$7:$AF$610,"Outside strict definition") | Q11: =COUNTIF('EL exclusions & gaps'!$B$7:$B$5000,$A11) | R11: Not evidenced | S11: Not evidenced | T11: COMP2281 Software Engineering (Year 2 team project with external organisation) (COMP2281) [Programme/course]; GEOL4091 Earth Sciences into Industry (GEOL4091) [Programme/course] | U11: Engineering/computing: 1; Science: 1 | V11: Several distributed routes | W11: Durham's verified employer-linked group project provision is distributed across departments rather than institution-wide, with a small central employer-facing offer. The clearest current routes are two curricular modules: COMP2281 Software Engineering (compulsory Year 2 Computer Science teams build a substantial software project in partnership with an external organisation; listed available 2025/26) and GEOL4091 Earth Sciences into Industry (optional Level 4 group project in which a client, typically an external organisation, sets the problem and deliverables and receives the groups' presented solution; 60% group report, listed 2025/26). The Physics Team Project (PHYS3581) fits closely (teams of up to six, 8 weeks, client brief, presentation to clients such as Procter & Gamble and Mantis Vacuum Systems) but problems are set by 'staff or local industry', so the external share is unproven. The central Mini Consultancy Competition (three-week, employer-set issue, three student teams) is documented only on an employer page, with no student eligibility or dated cohort. Engineering's pair-based Industrial Problem Solving live company project is only evidenced to 2019; the year-long Engin | X11: Search limit reached before checking Participatory Action Research (SOCI43715) and further arts/social science, education, health and law clinic provision. Further departmental instances likely (Engineering design/capstone with Industrial Partnership Committee partners, Biosciences, Psychology, Education). Central Mini Consultancy Competition lacks student-side eligibility, date and cohort evidence. Many sources are undated module/course pages or search-summary paraphrases of them; page contents were not opened directly. Resume pass (2026-10-13, 3 searches): Mini Consultancy student-side selection/team details still not found (employer-side page only: 3 teams, 3 weeks); MSc Business Analytics team vs individual still unconfirmed; PHYS3581 external share not stated.
A12: RG06 | B12: Edinburgh | C12: UK | D12: Russell Group | E12: UK – Russell Group | F12: 2027 | G12: 35 | H12: Complete | I12: =COUNTIFS('EL scheme register'!$A$7:$A$610,$A12,'EL scheme register'!$C$7:$C$610,"University-wide",'EL scheme register'!$AJ$7:$AJ$610,"Yes") | J12: =COUNTIFS('EL scheme register'!$A$7:$A$610,$A12,'EL scheme register'!$C$7:$C$610,"Cross-faculty",'EL scheme register'!$AJ$7:$AJ$610,"Yes") | K12: =COUNTIFS('EL scheme register'!$A$7:$A$610,$A12,'EL scheme register'!$C$7:$C$610,"Faculty/school",'EL scheme register'!$AJ$7:$AJ$610,"Yes") | L12: =COUNTIFS('EL scheme register'!$A$7:$A$610,$A12,'EL scheme register'!$C$7:$C$610,"Programme/course",'EL scheme register'!$AJ$7:$AJ$610,"Yes") | M12: =COUNTIFS('EL scheme register'!$A$7:$A$610,$A12,'EL scheme register'!$C$7:$C$610,"Unclear",'EL scheme register'!$AJ$7:$AJ$610,"Yes") | N12: =SUM(I12:M12) | O12: =COUNTIFS('EL scheme register'!$A$7:$A$610,$A12,'EL scheme register'!$AF$7:$AF$610,"Potentially relevant; evidence incomplete",'EL scheme register'!$AI$7:$AI$610,"Yes") | P12: =COUNTIFS('EL scheme register'!$A$7:$A$610,$A12,'EL scheme register'!$AF$7:$AF$610,"Outside strict definition") | Q12: =COUNTIF('EL exclusions & gaps'!$B$7:$B$5000,$A12) | R12: Not evidenced | S12: Not evidenced | T12: Students as Change Agents (EFIE08003) / EFI Change Agents (EFIE08006) (EFIE08003 / EFIE08006) [Unclear]; Sustainable Business Consultancy Projects (MSc Global Strategy and Sustainability) (CMSE11573) [Programme/course]; Enterprise Consultancy Project (BUST10120), Undergraduate Enterprise Consultancy (BUST10120) [Programme/course]; Client Consulting Project (EFIE11118), MSc Creative Industries (EFIE11118) [Programme/course]; LLM Human Rights Clinic (LLM in Human Rights) [Programme/course] | U12: Arts/humanities/social sciences: 3; Business/management: 2; Other (law, health, design, architecture…): 2; Central provision: 1 | V12: Several distributed routes | W12: Edinburgh has no institution-wide employer-project programme in operation. The one university-wide scheme, Students as Change Agents (SACHA), survives only as a 20-credit EFI course (EFIE08003 / EFIE08006) in which small interdisciplinary teams work on a challenge set by an external partner and present outputs to it; the Careers co-curricular route is paused. Whether the elective is open university-wide or restricted to the EFI Interdisciplinary Futures MA is unresolved. The densest provision is distributed in the Business School: live-client team consultancies for MSc Global Strategy and Sustainability (teams of 5-6, ten weeks, current in the 2026/27 catalogue), MSc Entrepreneurship and Innovation, MSc Climate Change Finance and Investment, the MBA (consultancy project and a one-week charity consultancy), and an undergraduate Enterprise Consultancy Project (2025/26) for a new local business. Clients propose challenges, attend scoping and presentations, and receive reports; several of these pages are undated or last evidenced before 2025. EFI MSc Creative Industries has a compulsory Client Consulting Project (cultural-organisation client, 2025/26) and a Team Project that mixes clie | X12: Further departmental instances likely (ECA live-brief modules, Business School and EFI courses not individually checked, Engineering/Informatics sponsor projects). Currency not confirmed for MCiP, Climate Change Consulting, MBA projects, Freedom of Expression Clinic, GeoSciences Outreach. SACHA/EFI Change Agents eligibility conflict. No participation numbers published. Search ceiling approached (~40); Medicine/Veterinary/Social Sciences/Moray House only lightly searched.
A13: RG07 | B13: Exeter | C13: UK | D13: Russell Group | E13: UK – Russell Group | F13: 2027 | G13: 136 | H13: Complete | I13: =COUNTIFS('EL scheme register'!$A$7:$A$610,$A13,'EL scheme register'!$C$7:$C$610,"University-wide",'EL scheme register'!$AJ$7:$AJ$610,"Yes") | J13: =COUNTIFS('EL scheme register'!$A$7:$A$610,$A13,'EL scheme register'!$C$7:$C$610,"Cross-faculty",'EL scheme register'!$AJ$7:$AJ$610,"Yes") | K13: =COUNTIFS('EL scheme register'!$A$7:$A$610,$A13,'EL scheme register'!$C$7:$C$610,"Faculty/school",'EL scheme register'!$AJ$7:$AJ$610,"Yes") | L13: =COUNTIFS('EL scheme register'!$A$7:$A$610,$A13,'EL scheme register'!$C$7:$C$610,"Programme/course",'EL scheme register'!$AJ$7:$AJ$610,"Yes") | M13: =COUNTIFS('EL scheme register'!$A$7:$A$610,$A13,'EL scheme register'!$C$7:$C$610,"Unclear",'EL scheme register'!$AJ$7:$AJ$610,"Yes") | N13: =SUM(I13:M13) | O13: =COUNTIFS('EL scheme register'!$A$7:$A$610,$A13,'EL scheme register'!$AF$7:$AF$610,"Potentially relevant; evidence incomplete",'EL scheme register'!$AI$7:$AI$610,"Yes") | P13: =COUNTIFS('EL scheme register'!$A$7:$A$610,$A13,'EL scheme register'!$AF$7:$AF$610,"Outside strict definition") | Q13: =COUNTIF('EL exclusions & gaps'!$B$7:$B$5000,$A13) | R13: Not evidenced | S13: Not evidenced | T13: Business Project (MSc Management) (BEMM149) [Programme/course] | U13: Business/management: 1 | V13: Unclear | W13: Exeter has two university-wide extracurricular routes. Embedded programme provision is mainly in the Business School. Review incomplete (search budget exhausted). - Grand Challenges (legacy): a free June project week open to all undergraduates. Groups of normally 4-8 design solutions to themed real-world challenges and present them to expert panels. 2026 challenge pages confirm current delivery. External input is largely experts giving lectures or sitting in the audience, so C is Unclear. The exception is a 2026 Industry-led Enquiry Group with Amazon Web Services, but AWS's exact role was not evidenced. - Future17 (legacy, with QS): open to undergraduates in year 2 or later and to PGT students. International teams of 6-8 spend 12 weeks on challenges set by partner organisations; 31 organisations offered 44 challenges in one round. A partner representative sits on the assessment panel. It can be taken for 15 credits via APEL or without credit. It meets all three criteria, but the latest dated cohort is about 2024/25, so its status is unclear. - Business School: the compulsory BEMM149 Business Project on MSc Management is a group consultancy project on a partner's brief, with a repor | X13: Other area unsearched; AHSS barely searched; dated current evidence missing for Future17 and BEMM149; AWS role in Grand Challenges; ECMM427 customer; group format for BEP3020, MSc MBA consulting option, Sports Consultancy Project; One Planet MBA team challenges; further departmental instances likely (engineering, business MSc programmes). Medicine/Health, Psychology, Sport not separately searched; reduced-depth mode.
A14: RG08 | B14: Glasgow | C14: UK | D14: Russell Group | E14: UK – Russell Group | F14: 2027 | G14: 80 | H14: Complete | I14: =COUNTIFS('EL scheme register'!$A$7:$A$610,$A14,'EL scheme register'!$C$7:$C$610,"University-wide",'EL scheme register'!$AJ$7:$AJ$610,"Yes") | J14: =COUNTIFS('EL scheme register'!$A$7:$A$610,$A14,'EL scheme register'!$C$7:$C$610,"Cross-faculty",'EL scheme register'!$AJ$7:$AJ$610,"Yes") | K14: =COUNTIFS('EL scheme register'!$A$7:$A$610,$A14,'EL scheme register'!$C$7:$C$610,"Faculty/school",'EL scheme register'!$AJ$7:$AJ$610,"Yes") | L14: =COUNTIFS('EL scheme register'!$A$7:$A$610,$A14,'EL scheme register'!$C$7:$C$610,"Programme/course",'EL scheme register'!$AJ$7:$AJ$610,"Yes") | M14: =COUNTIFS('EL scheme register'!$A$7:$A$610,$A14,'EL scheme register'!$C$7:$C$610,"Unclear",'EL scheme register'!$AJ$7:$AJ$610,"Yes") | N14: =SUM(I14:M14) | O14: =COUNTIFS('EL scheme register'!$A$7:$A$610,$A14,'EL scheme register'!$AF$7:$AF$610,"Potentially relevant; evidence incomplete",'EL scheme register'!$AI$7:$AI$610,"Yes") | P14: =COUNTIFS('EL scheme register'!$A$7:$A$610,$A14,'EL scheme register'!$AF$7:$AF$610,"Outside strict definition") | Q14: =COUNTIF('EL exclusions & gaps'!$B$7:$B$5000,$A14) | R14: Not evidenced | S14: Not evidenced | T14: MBA Group Consultancy Project (BUS5052) [Programme/course]; Integrating Business and Management in Practice (MGT4091) [Programme/course]; International Management Solutions (MGT5181) [Programme/course]; Team Project 3 (Software Team Project) (COMPSCI3004) [Programme/course] | U14: Business/management: 3; Engineering/computing: 1 | V14: Several distributed routes | W14: Glasgow's qualifying provision is programme-embedded, concentrated in the Adam Smith Business School with one computing route; nothing university-wide was verified. - MBA Group Consultancy Project (BUS5052, 2026-27): MBA groups manage a client and respond to a client brief over ~70 hours in two weeks; group report (65%) and 30-minute presentation (35%). - International Management Solutions (MGT5181, 2026-27): MSc International Business teams run a live consultancy for firms seeking to internationalise; group report and presentation; client introduction meeting. - Integrating Business and Management in Practice (MGT4091, 2025-26): Honours capstone in one intensive week; groups meet a live client and present recommendations to them. Probably the Honours core 'integrative experiential learning course', but not confirmed. - Team Project 3 (COMPSCI3004, 2026-27): 30-credit, year-long third-year team software project for real customers who submit projects and select teams. Customer sector and internal/external mix are not stated. - Entrepreneurial Ventures Management & Growth (MGT4019): teams of 4-5 consult for real charity/social-enterprise clients with consultant mentors; current deliv | X14: Compulsory vs optional status unknown for S2-S5. Client names/sectors not evidenced (S5 customer type unclear). MGT4091 link to the UG 'Small Business Consultancy Project' course card unconfirmed. MGT4019 current delivery unconfirmed. Engineering design/industrial projects, MSc Environment & Sustainable Development consultancy, College of Social Sciences consultation projects not verified (reduced-depth). Further departmental instances likely.
A15: RG09 | B15: Imperial College London | C15: UK | D15: Russell Group | E15: UK – Russell Group | F15: 2027 | G15: 2 | H15: Complete | I15: =COUNTIFS('EL scheme register'!$A$7:$A$610,$A15,'EL scheme register'!$C$7:$C$610,"University-wide",'EL scheme register'!$AJ$7:$AJ$610,"Yes") | J15: =COUNTIFS('EL scheme register'!$A$7:$A$610,$A15,'EL scheme register'!$C$7:$C$610,"Cross-faculty",'EL scheme register'!$AJ$7:$AJ$610,"Yes") | K15: =COUNTIFS('EL scheme register'!$A$7:$A$610,$A15,'EL scheme register'!$C$7:$C$610,"Faculty/school",'EL scheme register'!$AJ$7:$AJ$610,"Yes") | L15: =COUNTIFS('EL scheme register'!$A$7:$A$610,$A15,'EL scheme register'!$C$7:$C$610,"Programme/course",'EL scheme register'!$AJ$7:$AJ$610,"Yes") | M15: =COUNTIFS('EL scheme register'!$A$7:$A$610,$A15,'EL scheme register'!$C$7:$C$610,"Unclear",'EL scheme register'!$AJ$7:$AJ$610,"Yes") | N15: =SUM(I15:M15) | O15: =COUNTIFS('EL scheme register'!$A$7:$A$610,$A15,'EL scheme register'!$AF$7:$AF$610,"Potentially relevant; evidence incomplete",'EL scheme register'!$AI$7:$AI$610,"Yes") | P15: =COUNTIFS('EL scheme register'!$A$7:$A$610,$A15,'EL scheme register'!$AF$7:$AF$610,"Outside strict definition") | Q15: =COUNTIF('EL exclusions & gaps'!$B$7:$B$5000,$A15) | R15: Not evidenced | S15: Not evidenced | T15: Strategic Marketing Consulting Project (BUSI70292) [Programme/course]; MSc Business Analytics & AI Consulting Project (capstone option) [Programme/course]; MSc Management Consulting Project [Programme/course]; Hounslow Heath Project (MSc Environmental Technology: Environmental Assessment and Management option) [Programme/course] | U15: Business/management: 3; Science: 1 | V15: Several distributed routes | W15: Imperial's strongest employer-linked group provision sits in the Business School and a few engineering/environment programmes, with no institution-wide scheme found. The Business School's MSc Group Consulting Projects (June-July 2026 call; 4-5 weeks; teams of 5-7 from seven MSc programmes) take real briefs from companies, which are free to participate; students bid for them and present recommendations to a panel including company representatives. These run as elective capstone options (e.g. Strategic Marketing Consulting Project BUSI70292, 10 ECTS; Business Analytics & AI; Management; Economics & Strategy; Climate Change, Management & Finance). The MBA equivalent (Perspectives on Practice) is individual. In science, the MSc Environmental Technology (EAM option) Hounslow Heath project is a group technical report for Hounslow Borough Council with team presentations to the client (2025-26 specification). In engineering, the EEE third-year MEng group project (industry-proposed, groups of 5-7, industrial and academic supervisors) and the Computing Year 3 Software Engineering Group Project (customers, many industry-proposed) are strong leads, but current-year delivery or share of externa | X15: Further departmental instances likely (e.g. Bioengineering, Materials, Chemical Engineering, Earth Science, Physics/Chemistry industry projects, Faculty of Medicine). Extracurricular employer-set challenges (Careers competitions such as Accuracy Business Cup, Siemens/Sony) and the Imperial College Consultancy Society not verified. Credit weightings, module codes and cohort sizes mostly not extracted (search summaries only; no verbatim page quotes for most). Current-year evidence needed for S5, S6, S7, S9, S10. UROP/internship routes were not examined (individual).
A16: RG10 | B16: King’s College London | C16: UK | D16: Russell Group | E16: UK – Russell Group | F16: 2027 | G16: 37 | H16: Complete | I16: =COUNTIFS('EL scheme register'!$A$7:$A$610,$A16,'EL scheme register'!$C$7:$C$610,"University-wide",'EL scheme register'!$AJ$7:$AJ$610,"Yes") | J16: =COUNTIFS('EL scheme register'!$A$7:$A$610,$A16,'EL scheme register'!$C$7:$C$610,"Cross-faculty",'EL scheme register'!$AJ$7:$AJ$610,"Yes") | K16: =COUNTIFS('EL scheme register'!$A$7:$A$610,$A16,'EL scheme register'!$C$7:$C$610,"Faculty/school",'EL scheme register'!$AJ$7:$AJ$610,"Yes") | L16: =COUNTIFS('EL scheme register'!$A$7:$A$610,$A16,'EL scheme register'!$C$7:$C$610,"Programme/course",'EL scheme register'!$AJ$7:$AJ$610,"Yes") | M16: =COUNTIFS('EL scheme register'!$A$7:$A$610,$A16,'EL scheme register'!$C$7:$C$610,"Unclear",'EL scheme register'!$AJ$7:$AJ$610,"Yes") | N16: =SUM(I16:M16) | O16: =COUNTIFS('EL scheme register'!$A$7:$A$610,$A16,'EL scheme register'!$AF$7:$AF$610,"Potentially relevant; evidence incomplete",'EL scheme register'!$AI$7:$AI$610,"Yes") | P16: =COUNTIFS('EL scheme register'!$A$7:$A$610,$A16,'EL scheme register'!$AF$7:$AF$610,"Outside strict definition") | Q16: =COUNTIF('EL exclusions & gaps'!$B$7:$B$5000,$A16) | R16: Not evidenced | S16: Not evidenced | T16: King's Business School Consultancy (Strategy consultancy support for London enterprises; originally Business Consultancy Scheme) [Faculty/school] | U16: Business/management: 1 | V16: Several distributed routes | W16: King's College London (partial review) has live-client project provision spread across the Business School, Informatics and central civic and careers units. Some routes are confirmed to involve group working; for others it is unverified. - Fully qualifying, current: The King's Business School Consultancy places teams of 3-4 final-year economics, business and management undergraduates with up to 15 local enterprises. Teams deliver a presentation and written recommendations, and a summer 2026 call is open. - Qualifying but undated: On the MSc Advanced Software Engineering, teams build software for external partners, including public-sector challenges with AWS mentors (Richmond and Wandsworth Councils). The Careers Insights Programme runs 2-week group virtual micro-internships on employer-proposed briefs for final-year undergraduates across all nine faculties. - Live clients, group working unclear: Informatics' Knowledge Exchange Projects (over 90 since 2022; partners set the brief, join supervision and receive the software; up to five students per brief; 2025/26 confirmed). PPM Consultancy (NHS trusts, Hackney, charities; Jan-Apr 2026). The MSc International Management Business Consu | X16: Science, AHSS and other searched lightly (1-2 queries each); further departmental instances likely. Group-working evidence missing for KEPs, PPM Consultancy, IM Business Consulting Project and the GHRM Benifex project. Dated current-year evidence missing for Insights, MSc ASE partner project and Civic Challenge. Whether Insights and CLA are open to all students or targeted at under-represented groups. KBS Consultancy timing inconsistency (summer 2026 vs w/c 30 November). Further departmental instances likely (e.g. KBS MSc capstones, SSPP charity projects, Policy Institute).
A17: RG11 | B17: Leeds | C17: UK | D17: Russell Group | E17: UK – Russell Group | F17: 2027 | G17: 77 | H17: Complete | I17: =COUNTIFS('EL scheme register'!$A$7:$A$610,$A17,'EL scheme register'!$C$7:$C$610,"University-wide",'EL scheme register'!$AJ$7:$AJ$610,"Yes") | J17: =COUNTIFS('EL scheme register'!$A$7:$A$610,$A17,'EL scheme register'!$C$7:$C$610,"Cross-faculty",'EL scheme register'!$AJ$7:$AJ$610,"Yes") | K17: =COUNTIFS('EL scheme register'!$A$7:$A$610,$A17,'EL scheme register'!$C$7:$C$610,"Faculty/school",'EL scheme register'!$AJ$7:$AJ$610,"Yes") | L17: =COUNTIFS('EL scheme register'!$A$7:$A$610,$A17,'EL scheme register'!$C$7:$C$610,"Programme/course",'EL scheme register'!$AJ$7:$AJ$610,"Yes") | M17: =COUNTIFS('EL scheme register'!$A$7:$A$610,$A17,'EL scheme register'!$C$7:$C$610,"Unclear",'EL scheme register'!$AJ$7:$AJ$610,"Yes") | N17: =SUM(I17:M17) | O17: =COUNTIFS('EL scheme register'!$A$7:$A$610,$A17,'EL scheme register'!$AF$7:$AF$610,"Potentially relevant; evidence incomplete",'EL scheme register'!$AI$7:$AI$610,"Yes") | P17: =COUNTIFS('EL scheme register'!$A$7:$A$610,$A17,'EL scheme register'!$AF$7:$AF$610,"Outside strict definition") | Q17: =COUNTIF('EL exclusions & gaps'!$B$7:$B$5000,$A17) | R17: Yes | S17: Not evidenced | T17: LUBS3013 Enterprise Consultancy (Leeds Enterprise Consultancy Project) (LUBS3013) [University-wide]; Leeds Global Industry Programme (postgraduate) [University-wide]; EPS Embedded Virtual Work Experience [Faculty/school]; MECH5080M Team Project (MEng major team project with industrial partner) (MECH5080M) [Programme/course]; FOAH5000M Engaging the Modern City: The Civic Researcher (FOAH5000M) [Unclear] | U17: Business/management: 2; Central provision: 2; Science: 2; Arts/humanities/social sciences: 2; Engineering/computing: 2; Other (law, health, design, architecture…): 1 | V17: Several distributed routes | W17: Leeds has several verified employer-linked group project routes, distributed across schools rather than run through one university-wide scheme. The widest are two Discovery-eligible or central routes: LUBS3013 Enterprise Consultancy (final-year undergraduates from across the University work in teams on consultancy briefs from small businesses and social enterprises, graded partly by a group client report) and the Leeds Global Industry Programme (multidisciplinary teams of 5-8 taught postgraduates produce a consultancy report for a live company brief; EPS students take an eight-week embedded equivalent in teams of five). Within degrees, the MEng Team Project (MECH5080M, 45 credits, groups of 3-6 mentored by industry collaborators acting as customers) is compulsory in mechanical-engineering MEng programmes, and the civil engineering Year 4 design project has industrial partners acting as client (undated evidence). In arts and humanities, FOAH5000M Civic Researcher has interdisciplinary groups negotiating briefs with Leeds cultural and third-sector bodies, with external leads on the assessment panel; the Arts Management MA has a partner-brief group module. Business school routes inclu | X17: Further departmental instances likely (Electronic Engineering, Aerospace/Mechatronics variants, Geography/Environment, Education, Cerebra pro bono programme, School of Media and Communication, Computer Science industrial MSc projects). Not searched in detail: Physics/Chemistry/Biology group projects other than via Enterprise Consultancy; Maths/Statistics MSc projects (co-supervised individual projects found, group unclear). Participation numbers mostly unpublished; several pages undated so current delivery uncertain for S5, S7, S8, S9. Search budget exceeded the ~40 target (about 50 searches) to cover six areas.
A18: RG12 | B18: Liverpool | C18: UK | D18: Russell Group | E18: UK – Russell Group | F18: 2027 | G18: 139 | H18: Complete | I18: =COUNTIFS('EL scheme register'!$A$7:$A$610,$A18,'EL scheme register'!$C$7:$C$610,"University-wide",'EL scheme register'!$AJ$7:$AJ$610,"Yes") | J18: =COUNTIFS('EL scheme register'!$A$7:$A$610,$A18,'EL scheme register'!$C$7:$C$610,"Cross-faculty",'EL scheme register'!$AJ$7:$AJ$610,"Yes") | K18: =COUNTIFS('EL scheme register'!$A$7:$A$610,$A18,'EL scheme register'!$C$7:$C$610,"Faculty/school",'EL scheme register'!$AJ$7:$AJ$610,"Yes") | L18: =COUNTIFS('EL scheme register'!$A$7:$A$610,$A18,'EL scheme register'!$C$7:$C$610,"Programme/course",'EL scheme register'!$AJ$7:$AJ$610,"Yes") | M18: =COUNTIFS('EL scheme register'!$A$7:$A$610,$A18,'EL scheme register'!$C$7:$C$610,"Unclear",'EL scheme register'!$AJ$7:$AJ$610,"Yes") | N18: =SUM(I18:M18) | O18: =COUNTIFS('EL scheme register'!$A$7:$A$610,$A18,'EL scheme register'!$AF$7:$AF$610,"Potentially relevant; evidence incomplete",'EL scheme register'!$AI$7:$AI$610,"Yes") | P18: =COUNTIFS('EL scheme register'!$A$7:$A$610,$A18,'EL scheme register'!$AF$7:$AF$610,"Outside strict definition") | Q18: =COUNTIF('EL exclusions & gaps'!$B$7:$B$5000,$A18) | R18: Yes | S18: Not evidenced | T18: The Big Events Challenge with Culture Liverpool [Unclear]; Sustainable Innovation Challenge [University-wide]; Professional Projects and Employability in Mathematics (MATH390) [Programme/course] | U18: Central provision: 2; Science: 1 | V18: Several distributed routes | W18: Liverpool shows qualifying provision in several distinct places rather than a single institution-wide scheme. Centrally, Careers and Employability runs extracurricular employer team challenges under Launchpad (the Big Events Challenge with Culture Liverpool, March 2026, a two-day challenge; and the annual Sustainable Innovation Challenge, 2026 brief with Manchester City FC and partner universities). Both are selective, short and not credit-bearing; the Sustainable Innovation Challenge is open across the University with priority for EQ+ students. A central 'Real-World Challenges in Curriculum' offer invites employers to embed projects in modules, but no list of participating modules is published. The strongest curricular routes are programme-level: MATH390 (Mathematical Sciences, optional Year 3, groups on employer-set projects with employer input on reports and Q&A), Geography and Planning's client-based group modules (ENVS467 compulsory in MPlan/MCD with named council and charity clients; Environmental Planning and Management Project), a Management School HRM Consultancy Day (one day, Enterprise Mobility, BDO, Hilton, March 2025), and an EEE module with industry-panel pitches. The | X18: Further departmental instances likely (engineering, computer science, medicine, dentistry, veterinary science, nursing/allied health, biosciences, chemistry, physics, music/arts, politics) were not searched in depth. Many module pages undated; legacy Grand Challenges page not surfaced in search. Group working unresolved for MBA, MKIB306, Project Partners and architecture studio. Partner types for several routes unspecified. No participation numbers published. 39 searches used.
... A36: AU06 | B36: Queensland | C36: Australia | D36: Australia top 10 | E36: Australia | F36: 2027 | G36: 40 | H36: Complete | I36: =COUNTIFS('EL scheme register'!$A$7:$A$610,$A36,'EL scheme register'!$C$7:$C$610,"University-wide",'EL scheme register'!$AJ$7:$AJ$610,"Yes") | J36: =COUNTIFS('EL scheme register'!$A$7:$A$610,$A36,'EL scheme register'!$C$7:$C$610,"Cross-faculty",'EL scheme register'!$AJ$7:$AJ$610,"Yes") | K36: =COUNTIFS('EL scheme register'!$A$7:$A$610,$A36,'EL scheme register'!$C$7:$C$610,"Faculty/school",'EL scheme register'!$AJ$7:$AJ$610,"Yes") | L36: =COUNTIFS('EL scheme register'!$A$7:$A$610,$A36,'EL scheme register'!$C$7:$C$610,"Programme/course",'EL scheme register'!$AJ$7:$AJ$610,"Yes") | M36: =COUNTIFS('EL scheme register'!$A$7:$A$610,$A36,'EL scheme register'!$C$7:$C$610,"Unclear",'EL scheme register'!$AJ$7:$AJ$610,"Yes") | N36: =SUM(I36:M36) | O36: =COUNTIFS('EL scheme register'!$A$7:$A$610,$A36,'EL scheme register'!$AF$7:$AF$610,"Potentially relevant; evidence incomplete",'EL scheme register'!$AI$7:$AI$610,"Yes") | P36: =COUNTIFS('EL scheme register'!$A$7:$A$610,$A36,'EL scheme register'!$AF$7:$AF$610,"Outside strict definition") | Q36: =COUNTIF('EL exclusions & gaps'!$B$7:$B$5000,$A36) | R36: Yes | S36: Not evidenced | T36: Practera SAIEP - Industry Experience Projects [University-wide]; Industry Consulting Project (Business Industry Consultancy Project) (RBUS3888; RBUS4888; RBUS7888; BSAN7215) [Faculty/school]; Learning by Doing in a Disruptive World (PBEL3000) [Faculty/school]; Impact Academy 1: Discovering New Solutions for Complex Problems (MGTS7820) [Programme/course]; Sustainability Strategy and Leadership Capstone (TIMS7334) [Programme/course]; Team Project (Bachelor of Advanced Finance and Economics (Honours)) (FINM4411) [Programme/course] | U36: Business/management: 5; Central provision: 1 | V36: Several distributed routes | W36: University of Queensland (reduced-depth review). The verified provision sits mainly in Business, Economics and Law, plus two central extracurricular routes. - BEL Industry Consulting Project (RBUS3888/4888/7888, BSAN7215): selective final-year course (GPA 4.0+, by application). Project teams with an assigned mentor answer a brief from an industry partner, such as Cancer Council Queensland or Netball Queensland, and deliver a team report to the client. Applications are open for 2026-27. - PBEL3000 Learning by Doing in a Disruptive World: application-only undergraduate capstone. Teams of 3-5 pitch to an industry partner, who gives feedback, and write an industry report. Last offered Summer Semester 2025. - MBA Impact Academy 1 (MGTS7820, 2026): teams take sponsor-set real problems and present to the sponsors. It appears to replace the MGTS7818 Industry Engagement Capstone, last evidenced in 2024. Past MBA partners include Suncorp, Anglicare and Queensland Police. - Central: Practera SAIEP offers two-week virtual team projects for any UQ student, with briefs from real employers and client feedback. It is short and selective. The Ventures Industry Challenge is university-wide but only | X36: Further departmental capstones in Science, HASS, engineering disciplines and architecture likely exist but were not found at reduced depth; Ventures Industry Challenge external-partner role unclear; PBEL3000 2026-27 offering unconfirmed; MGTS7818 likely replaced; FINM4411 verified only via search extract; TIMS7334/HRSS4210 partner type unclear; no participation numbers for most routes.
A37: AU07 | B37: Western Australia | C37: Australia | D37: Australia top 10 | E37: Australia | F37: 2027 | G37: 77 | H37: Not started | I37: =COUNTIFS('EL scheme register'!$A$7:$A$610,$A37,'EL scheme register'!$C$7:$C$610,"University-wide",'EL scheme register'!$AJ$7:$AJ$610,"Yes") | J37: =COUNTIFS('EL scheme register'!$A$7:$A$610,$A37,'EL scheme register'!$C$7:$C$610,"Cross-faculty",'EL scheme register'!$AJ$7:$AJ$610,"Yes") | K37: =COUNTIFS('EL scheme register'!$A$7:$A$610,$A37,'EL scheme register'!$C$7:$C$610,"Faculty/school",'EL scheme register'!$AJ$7:$AJ$610,"Yes") | L37: =COUNTIFS('EL scheme register'!$A$7:$A$610,$A37,'EL scheme register'!$C$7:$C$610,"Programme/course",'EL scheme register'!$AJ$7:$AJ$610,"Yes") | M37: =COUNTIFS('EL scheme register'!$A$7:$A$610,$A37,'EL scheme register'!$C$7:$C$610,"Unclear",'EL scheme register'!$AJ$7:$AJ$610,"Yes") | N37: =SUM(I37:M37) | O37: =COUNTIFS('EL scheme register'!$A$7:$A$610,$A37,'EL scheme register'!$AF$7:$AF$610,"Potentially relevant; evidence incomplete",'EL scheme register'!$AI$7:$AI$610,"Yes") | P37: =COUNTIFS('EL scheme register'!$A$7:$A$610,$A37,'EL scheme register'!$AF$7:$AF$610,"Outside strict definition") | Q37: =COUNTIF('EL exclusions & gaps'!$B$7:$B$5000,$A37) | R37: Not reviewed | S37: Not reviewed | V37: Not reviewed
A38: AU08 | B38: Adelaide University | C38: Australia | D38: Australia top 10 | E38: Australia | F38: 2027 | G38: 79 | H38: Not started | I38: =COUNTIFS('EL scheme register'!$A$7:$A$610,$A38,'EL scheme register'!$C$7:$C$610,"University-wide",'EL scheme register'!$AJ$7:$AJ$610,"Yes") | J38: =COUNTIFS('EL scheme register'!$A$7:$A$610,$A38,'EL scheme register'!$C$7:$C$610,"Cross-faculty",'EL scheme register'!$AJ$7:$AJ$610,"Yes") | K38: =COUNTIFS('EL scheme register'!$A$7:$A$610,$A38,'EL scheme register'!$C$7:$C$610,"Faculty/school",'EL scheme register'!$AJ$7:$AJ$610,"Yes") | L38: =COUNTIFS('EL scheme register'!$A$7:$A$610,$A38,'EL scheme register'!$C$7:$C$610,"Programme/course",'EL scheme register'!$AJ$7:$AJ$610,"Yes") | M38: =COUNTIFS('EL scheme register'!$A$7:$A$610,$A38,'EL scheme register'!$C$7:$C$610,"Unclear",'EL scheme register'!$AJ$7:$AJ$610,"Yes") | N38: =SUM(I38:M38) | O38: =COUNTIFS('EL scheme register'!$A$7:$A$610,$A38,'EL scheme register'!$AF$7:$AF$610,"Potentially relevant; evidence incomplete",'EL scheme register'!$AI$7:$AI$610,"Yes") | P38: =COUNTIFS('EL scheme register'!$A$7:$A$610,$A38,'EL scheme register'!$AF$7:$AF$610,"Outside strict definition") | Q38: =COUNTIF('EL exclusions & gaps'!$B$7:$B$5000,$A38) | R38: Not reviewed | S38: Not reviewed | V38: Not reviewed
A39: AU09 | B39: University of Technology Sydney | C39: Australia | D39: Australia top 10 | E39: Australia | F39: 2027 | G39: 87 | H39: Complete | I39: =COUNTIFS('EL scheme register'!$A$7:$A$610,$A39,'EL scheme register'!$C$7:$C$610,"University-wide",'EL scheme register'!$AJ$7:$AJ$610,"Yes") | J39: =COUNTIFS('EL scheme register'!$A$7:$A$610,$A39,'EL scheme register'!$C$7:$C$610,"Cross-faculty",'EL scheme register'!$AJ$7:$AJ$610,"Yes") | K39: =COUNTIFS('EL scheme register'!$A$7:$A$610,$A39,'EL scheme register'!$C$7:$C$610,"Faculty/school",'EL scheme register'!$AJ$7:$AJ$610,"Yes") | L39: =COUNTIFS('EL scheme register'!$A$7:$A$610,$A39,'EL scheme register'!$C$7:$C$610,"Programme/course",'EL scheme register'!$AJ$7:$AJ$610,"Yes") | M39: =COUNTIFS('EL scheme register'!$A$7:$A$610,$A39,'EL scheme register'!$C$7:$C$610,"Unclear",'EL scheme register'!$AJ$7:$AJ$610,"Yes") | N39: =SUM(I39:M39) | O39: =COUNTIFS('EL scheme register'!$A$7:$A$610,$A39,'EL scheme register'!$AF$7:$AF$610,"Potentially relevant; evidence incomplete",'EL scheme register'!$AI$7:$AI$610,"Yes") | P39: =COUNTIFS('EL scheme register'!$A$7:$A$610,$A39,'EL scheme register'!$AF$7:$AF$610,"Outside strict definition") | Q39: =COUNTIF('EL exclusions & gaps'!$B$7:$B$5000,$A39) | R39: Yes | S39: Not evidenced | T39: Transdisciplinary (TD) Electives (e.g. 95002/95010 TD: Reframing, remixing, reimagining society (UNICEF Australia); 95005 Shaping Technologies that Shape Us (Microsoft); 95004 (ServiceRocket); 95006 (City of Sydney); 95008 (Miro); Pathways to Societal Transitions (Lane Cove Council)) [University-wide]; Industry Innovation Project [Programme/course]; UTS Shopfront Community Program – community projects in coursework (Various participating coursework subjects (not identified)) [Unclear] | U39: Central provision: 3 | V39: Several distributed routes | W39: UTS (reduced-depth, all six areas queried). Qualifying or near-qualifying routes were found centrally and in one faculty. TD Electives (TD School, 8 subjects, 6-8cp): the student page states each elective has "a real-world challenge presented by an industry partner organisation" and "Collaborate in teams with students from all faculties"; partners (UNICEF Australia, City of Sydney, Microsoft, Miro, Lane Cove Council, ServiceRocket in 2026) co-design the challenge, mentor and give feedback. Optional, open to undergraduates except BCII students. Industry Innovation Project (BCII final year): 13-week teams of 5-7 with partner mentors. UTS Shopfront brokers charity/community projects into coursework as team consultancies, but host subjects are unidentified. Software Development Studio (FEIT): teams of 4-6 deliver prototypes for industry-posed briefs over 12 weeks with weekly industry mentors; optional, listed FEIT degrees; page undated (copyright 2026) so current delivery unconfirmed. Strategic Communication capstone: semester-long real-client brief; team format not stated. Business, engineering capstone, design and science instances were seen only as titles or snippets. Provision is d | X39: Business School capstones, engineering/IT capstones, Mechanical and Mechatronic Design studio, Strategic Design Studio: not verified beyond snippets; further departmental instances likely. Shopfront host subjects and Industry Innovation Project core status unresolved. SDS and Strategic Communication lack dated delivery evidence. Law and health: no live-client team subject surfaced (one combined search only). 2026 handbook assessment for TD Electives not retrieved.
A40: AU10 | B40: RMIT | C40: Australia | D40: Australia top 10 | E40: Australia | F40: 2027 | G40: 119 | H40: Complete | I40: =COUNTIFS('EL scheme register'!$A$7:$A$610,$A40,'EL scheme register'!$C$7:$C$610,"University-wide",'EL scheme register'!$AJ$7:$AJ$610,"Yes") | J40: =COUNTIFS('EL scheme register'!$A$7:$A$610,$A40,'EL scheme register'!$C$7:$C$610,"Cross-faculty",'EL scheme register'!$AJ$7:$AJ$610,"Yes") | K40: =COUNTIFS('EL scheme register'!$A$7:$A$610,$A40,'EL scheme register'!$C$7:$C$610,"Faculty/school",'EL scheme register'!$AJ$7:$AJ$610,"Yes") | L40: =COUNTIFS('EL scheme register'!$A$7:$A$610,$A40,'EL scheme register'!$C$7:$C$610,"Programme/course",'EL scheme register'!$AJ$7:$AJ$610,"Yes") | M40: =COUNTIFS('EL scheme register'!$A$7:$A$610,$A40,'EL scheme register'!$C$7:$C$610,"Unclear",'EL scheme register'!$AJ$7:$AJ$610,"Yes") | N40: =SUM(I40:M40) | O40: =COUNTIFS('EL scheme register'!$A$7:$A$610,$A40,'EL scheme register'!$AF$7:$AF$610,"Potentially relevant; evidence incomplete",'EL scheme register'!$AI$7:$AI$610,"Yes") | P40: =COUNTIFS('EL scheme register'!$A$7:$A$610,$A40,'EL scheme register'!$AF$7:$AF$610,"Outside strict definition") | Q40: =COUNTIF('EL exclusions & gaps'!$B$7:$B$5000,$A40) | R40: Not evidenced | S40: Not evidenced | T40: Impact Academy 1 (Bachelor of Business (Professional Practice) core subject) (Unclear) [Programme/course] | U40: Business/management: 1 | V40: Several distributed routes | W40: RMIT has no single university-wide employer project scheme. Its WIL page describes industry-sponsored projects 'often in teams' but says requirements vary by course. Qualifying routes sit in programmes. The strongest is Impact Academy 1, a core subject of the Bachelor of Business (Professional Practice), where teams answer a real challenge set by a live industry partner's client. Other client-facing group routes are a software engineering project with an industry partner as client (teams, one semester), a Year 3 PR capstone commissioned by industry, government or community partners, and a cross-faculty Buyer Behaviour client project in the Associate Degree in Business (2023 evidence). Engineering runs a year-long capstone with industry-proposed projects, a three-party WIL agreement and a 22 October 2026 showcase. Team structure and the share of industry-sponsored projects are not stated, so group and employer criteria are Unclear. Medibank and Red Cross group challenges in the Bachelor of Business (IPBP) are named from a 2023-era page and not shown to be standard. Only Impact Academy 1 has current-delivery corroboration (degree intakes and 2027 fee) and meets all three criteria. Se | X40: Subject-level handbook pages (credit, year, current offering) not opened for any scheme; Impact Academy 2 details not read (WebFetch truncated); PR capstone and Bachelor of Science capstone text not reached (pages >100k characters, only first 100k read); engineering team structure and proportion of industry-sponsored capstones; Science (COSC2408) current status; design/architecture/interior design live studios, Cyber Ready CIC, MBIT project and other departmental instances likely exist and were not researched in reduced-depth mode; law/health not found. Retrieval: WebFetch worked directly (page text) for most pages; no curl fallback needed.
A41: UK01 | B41: Bath | C41: UK | D41: Additional UK sample | E41: UK – additional | F41: 2027 | G41: 125 | H41: Complete | I41: =COUNTIFS('EL scheme register'!$A$7:$A$610,$A41,'EL scheme register'!$C$7:$C$610,"University-wide",'EL scheme register'!$AJ$7:$AJ$610,"Yes") | J41: =COUNTIFS('EL scheme register'!$A$7:$A$610,$A41,'EL scheme register'!$C$7:$C$610,"Cross-faculty",'EL scheme register'!$AJ$7:$AJ$610,"Yes") | K41: =COUNTIFS('EL scheme register'!$A$7:$A$610,$A41,'EL scheme register'!$C$7:$C$610,"Faculty/school",'EL scheme register'!$AJ$7:$AJ$610,"Yes") | L41: =COUNTIFS('EL scheme register'!$A$7:$A$610,$A41,'EL scheme register'!$C$7:$C$610,"Programme/course",'EL scheme register'!$AJ$7:$AJ$610,"Yes") | M41: =COUNTIFS('EL scheme register'!$A$7:$A$610,$A41,'EL scheme register'!$C$7:$C$610,"Unclear",'EL scheme register'!$AJ$7:$AJ$610,"Yes") | N41: =SUM(I41:M41) | O41: =COUNTIFS('EL scheme register'!$A$7:$A$610,$A41,'EL scheme register'!$AF$7:$AF$610,"Potentially relevant; evidence incomplete",'EL scheme register'!$AI$7:$AI$610,"Yes") | P41: =COUNTIFS('EL scheme register'!$A$7:$A$610,$A41,'EL scheme register'!$AF$7:$AF$610,"Outside strict definition") | Q41: =COUNTIF('EL exclusions & gaps'!$B$7:$B$5000,$A41) | R41: Not evidenced | S41: Not evidenced | V41: Several distributed routes | W41: Bath's relevant provision is distributed and mostly postgraduate. The University-wide Vertically Integrated Projects (250 students in 11 interdisciplinary teams in 2025/26, open to UG, PG and doctoral students, largely extracurricular) are group research projects, but external organisations only 'may' contribute, so the employer criterion is unclear. In Engineering & Design, the MEng Group Design and Business Project has third-year teams working about 14 weeks on company-supplied briefs (Airbus, NCC, UKAEA and others named) and presenting to the company, but compulsory status, credit, and current-year delivery were not verified. In the School of Management, MSc Practice Track (teams with an external client, 7-8 weeks in summer, optional) and a six-week MSc Consulting Project with a local organisation are team client projects; the postgraduate consultancy option in several other MSc/MA courses can be done alone or in a group. A short employer-set Big Team Challenge and the student-run 180 Degrees Consulting are also recorded. Most pages are undated (some link to 2027 entry), so current delivery is largely unconfirmed. No science or arts-led qualifying scheme was verified. | X41: Dated 2025/26-2026/27 delivery for S2-S7; MBA Multi-Project Suite page; unit credit for MEng GDBP; Big Team Challenge page text; further departmental instances (Education MA, IR MSc, Sport Management) likely; no direct page text beyond ~7 fetches.
A42: UK02 | B42: St Andrews | C42: UK | D42: Additional UK sample | E42: UK – additional | F42: 2027 | G42: 115 | H42: Complete | I42: =COUNTIFS('EL scheme register'!$A$7:$A$610,$A42,'EL scheme register'!$C$7:$C$610,"University-wide",'EL scheme register'!$AJ$7:$AJ$610,"Yes") | J42: =COUNTIFS('EL scheme register'!$A$7:$A$610,$A42,'EL scheme register'!$C$7:$C$610,"Cross-faculty",'EL scheme register'!$AJ$7:$AJ$610,"Yes") | K42: =COUNTIFS('EL scheme register'!$A$7:$A$610,$A42,'EL scheme register'!$C$7:$C$610,"Faculty/school",'EL scheme register'!$AJ$7:$AJ$610,"Yes") | L42: =COUNTIFS('EL scheme register'!$A$7:$A$610,$A42,'EL scheme register'!$C$7:$C$610,"Programme/course",'EL scheme register'!$AJ$7:$AJ$610,"Yes") | M42: =COUNTIFS('EL scheme register'!$A$7:$A$610,$A42,'EL scheme register'!$C$7:$C$610,"Unclear",'EL scheme register'!$AJ$7:$AJ$610,"Yes") | N42: =SUM(I42:M42) | O42: =COUNTIFS('EL scheme register'!$A$7:$A$610,$A42,'EL scheme register'!$AF$7:$AF$610,"Potentially relevant; evidence incomplete",'EL scheme register'!$AI$7:$AI$610,"Yes") | P42: =COUNTIFS('EL scheme register'!$A$7:$A$610,$A42,'EL scheme register'!$AF$7:$AF$610,"Outside strict definition") | Q42: =COUNTIF('EL exclusions & gaps'!$B$7:$B$5000,$A42) | R42: Not evidenced | S42: Not evidenced | V42: Isolated departmental provision | W42: St Andrews (reduced-depth review, six areas queried): no scheme was verified that meets all three criteria with a documented external client and current delivery. - VIP: credit-bearing mixed-discipline research teams (applications for 2026/27 confirmed). Fetching the projects page shows 19 projects, none naming an external partner, so C is Unclear. Faculty eligibility is not stated (legacy row says Arts and Science). - STEP: online 7-week team consulting projects in 2026, but the clients are University Schools and units (internal, C = No). - CS3099: year-3 team software project with Experian and Skyscanner involvement reported in 2025, role unspecified. - Management MSc: advertises consultancy projects with local organisations, but no corresponding compulsory module or group structure was found. - Playfair: student-run pro bono consultancy with teams of 5-6 and external clients, but evidence is secondary and undated and it is not a University scheme. Science, humanities/social science, Medicine, Divinity and Law yielded no external-client team routes. Provision is isolated and mostly internal or research-led. | X42: Further departmental instances may exist but were not found in reduced-depth search. Open items: VIP faculty eligibility and external partners per project; CS3099 partner role and whether compulsory; the Management MSc module behind 'consultancy projects'; Playfair current status and eligibility; ScotGEM Agents of Change group/partner role; Law and Divinity only lightly searched (one combined query); one query per area only.
A43: UK03 | B43: Lancaster | C43: UK | D43: Additional UK sample | E43: UK – additional | F43: 2027 | G43: 164 | H43: Complete | I43: =COUNTIFS('EL scheme register'!$A$7:$A$610,$A43,'EL scheme register'!$C$7:$C$610,"University-wide",'EL scheme register'!$AJ$7:$AJ$610,"Yes") | J43: =COUNTIFS('EL scheme register'!$A$7:$A$610,$A43,'EL scheme register'!$C$7:$C$610,"Cross-faculty",'EL scheme register'!$AJ$7:$AJ$610,"Yes") | K43: =COUNTIFS('EL scheme register'!$A$7:$A$610,$A43,'EL scheme register'!$C$7:$C$610,"Faculty/school",'EL scheme register'!$AJ$7:$AJ$610,"Yes") | L43: =COUNTIFS('EL scheme register'!$A$7:$A$610,$A43,'EL scheme register'!$C$7:$C$610,"Programme/course",'EL scheme register'!$AJ$7:$AJ$610,"Yes") | M43: =COUNTIFS('EL scheme register'!$A$7:$A$610,$A43,'EL scheme register'!$C$7:$C$610,"Unclear",'EL scheme register'!$AJ$7:$AJ$610,"Yes") | N43: =SUM(I43:M43) | O43: =COUNTIFS('EL scheme register'!$A$7:$A$610,$A43,'EL scheme register'!$AF$7:$AF$610,"Potentially relevant; evidence incomplete",'EL scheme register'!$AI$7:$AI$610,"Yes") | P43: =COUNTIFS('EL scheme register'!$A$7:$A$610,$A43,'EL scheme register'!$AF$7:$AF$610,"Outside strict definition") | Q43: =COUNTIF('EL exclusions & gaps'!$B$7:$B$5000,$A43) | R43: Not evidenced | S43: Not evidenced | T43: Company-based group project (MSc Advanced Management, Consulting and Change) [Programme/course]; Action project / consultancy project (MSc Project Management) [Programme/course]; Company Commissioned Dissertation (MSc Digital and Social Media Marketing) [Programme/course] | U43: Business/management: 3 | V43: Several distributed routes | W43: Lancaster's relevant provision is concentrated in programme-embedded, faculty-level routes rather than a single institution-wide scheme. The Lancaster Award is a co-curricular recognition scheme and was excluded as such. Business (strongest): LUMS runs a Company Projects framework in which external companies (Companies House-registered, trading 1+ year, 5-10 hours commitment) supply live briefs to small student teams. Programme routes include the final-year Research Consultancy Project in Marketing degrees, the MBA Consultancy and Corporate Challenges, a Management MSc company project (teams of four), an Advanced Management, Consulting and Change MSc group project, the MSc Project Management action project (groups of two to three), and the Digital and Social Media Marketing MSc company-commissioned dissertation. The LUMS Careers Projects Team reports 668 students and 160+ employer partners since 2023. A two-day April 2026 hackathon had Heathrow as client. Engineering and science: MEng ENGR 445 group projects (teams of 4-6, real company problems) and Physics Industrial Group Projects (groups of 3-6, company briefs, 25% of year-3 marks) qualify. Arts and design: Design Consultancy (r | X43: Further departmental instances likely (other LUMS UG modules, Chemistry, LEC, Statistics/STOR-i, Medical School and Health not searched). Most evidence is search-summary paraphrase of undated pages; UG routes lack dated 2025/26 delivery evidence. Criminology live-project claim from search summary not verified. Policy Law Clinic with Environmental Law Foundation and Executive MBA consultancy challenge need checking. Search budget approx 38 searches.
A44: UK04 | B44: Loughborough | C44: UK | D44: Additional UK sample | E44: UK – additional | F44: 2027 | G44: 203 | H44: Complete | I44: =COUNTIFS('EL scheme register'!$A$7:$A$610,$A44,'EL scheme register'!$C$7:$C$610,"University-wide",'EL scheme register'!$AJ$7:$AJ$610,"Yes") | J44: =COUNTIFS('EL scheme register'!$A$7:$A$610,$A44,'EL scheme register'!$C$7:$C$610,"Cross-faculty",'EL scheme register'!$AJ$7:$AJ$610,"Yes") | K44: =COUNTIFS('EL scheme register'!$A$7:$A$610,$A44,'EL scheme register'!$C$7:$C$610,"Faculty/school",'EL scheme register'!$AJ$7:$AJ$610,"Yes") | L44: =COUNTIFS('EL scheme register'!$A$7:$A$610,$A44,'EL scheme register'!$C$7:$C$610,"Programme/course",'EL scheme register'!$AJ$7:$AJ$610,"Yes") | M44: =COUNTIFS('EL scheme register'!$A$7:$A$610,$A44,'EL scheme register'!$C$7:$C$610,"Unclear",'EL scheme register'!$AJ$7:$AJ$610,"Yes") | N44: =SUM(I44:M44) | O44: =COUNTIFS('EL scheme register'!$A$7:$A$610,$A44,'EL scheme register'!$AF$7:$AF$610,"Potentially relevant; evidence incomplete",'EL scheme register'!$AI$7:$AI$610,"Yes") | P44: =COUNTIFS('EL scheme register'!$A$7:$A$610,$A44,'EL scheme register'!$AF$7:$AF$610,"Outside strict definition") | Q44: =COUNTIF('EL exclusions & gaps'!$B$7:$B$5000,$A44) | R44: Yes | S44: Not evidenced | T44: Collaborative Project (Loughborough University London) [Programme/course]; Talent Match Consultancy Programme [University-wide] | U44: Central provision: 2; Business/management: 1; Engineering/computing: 1; Arts/humanities/social sciences: 1 | V44: Several distributed routes | W44: Loughborough University (UK04) has several distributed employer-linked team routes but no single institution-wide scheme. The most widely accessible curricular route is the Collaborative Project at Loughborough University London (15 credits; 2026 show with nine partners including Sports Interactive, West Ham United Foundation and The Commonwealth Secretariat), where multidisciplinary teams solve partner-set challenges. In the Business School, MSc programmes include a 45-credit Industry Experience Project, a group project for a client company (named clients: GB Snowsport, Cross Country Trains, Vector Consumer, TISA) and the MBA has a team Consultancy Project; both lack dated 2025/26 delivery evidence. Physics runs year-3 and final-year group projects with industrial partners (NLA Blue, IBM, BEIS examples), the Wolfson School offers company-set group projects in years 2 and 4, Design and Creative Arts runs company-brief projects and a compulsory UX Industry Project with team briefs presented to the company, and ABCE runs Cross-School Design Weeks with an industry panel. Centrally, the Talent Match Consultancy Programme (August 2026) puts selected students and recent graduates into pa | X44: No university-wide curricular scheme found; most evidence is undated programme pages. Not verified: dated 2025/26 delivery for S2, S3, S5-S8, S10; Physics compulsory status and team sizes; Wolfson link to Integrated Industrial Group Projects module; Computer Science group-project clients; Managing Innovation (MBA) team format; undergraduate Business School live-client modules; further departmental instances likely (e.g. Sport Business/Marketing London programmes, Civil Engineering group design projects, Design final-year projects, Mechanical/Aeronautical group projects). Search results were summaries, mostly not verbatim quotes.
A45: UK05 | B45: Aberdeen | C45: UK | D45: Additional UK sample | E45: UK – additional | F45: 2027 | G45: 288 | H45: Complete | I45: =COUNTIFS('EL scheme register'!$A$7:$A$610,$A45,'EL scheme register'!$C$7:$C$610,"University-wide",'EL scheme register'!$AJ$7:$AJ$610,"Yes") | J45: =COUNTIFS('EL scheme register'!$A$7:$A$610,$A45,'EL scheme register'!$C$7:$C$610,"Cross-faculty",'EL scheme register'!$AJ$7:$AJ$610,"Yes") | K45: =COUNTIFS('EL scheme register'!$A$7:$A$610,$A45,'EL scheme register'!$C$7:$C$610,"Faculty/school",'EL scheme register'!$AJ$7:$AJ$610,"Yes") | L45: =COUNTIFS('EL scheme register'!$A$7:$A$610,$A45,'EL scheme register'!$C$7:$C$610,"Programme/course",'EL scheme register'!$AJ$7:$AJ$610,"Yes") | M45: =COUNTIFS('EL scheme register'!$A$7:$A$610,$A45,'EL scheme register'!$C$7:$C$610,"Unclear",'EL scheme register'!$AJ$7:$AJ$610,"Yes") | N45: =SUM(I45:M45) | O45: =COUNTIFS('EL scheme register'!$A$7:$A$610,$A45,'EL scheme register'!$AF$7:$AF$610,"Potentially relevant; evidence incomplete",'EL scheme register'!$AI$7:$AI$610,"Yes") | P45: =COUNTIFS('EL scheme register'!$A$7:$A$610,$A45,'EL scheme register'!$AF$7:$AF$610,"Outside strict definition") | Q45: =COUNTIF('EL exclusions & gaps'!$B$7:$B$5000,$A45) | R45: Not evidenced | S45: Not evidenced | T45: Engineering Work Experience (ED251A) [Faculty/school] | U45: Engineering/computing: 1 | V45: Several distributed routes | W45: Aberdeen has a small set of curricular routes where students work in teams on projects for outside organisations; none is verified as current for 2025/26 or later except ED251A and ED3537 (catalogue entries). - PD2503 Work-Based Learning: Team Projects with Employer Partners (Level 2, 15 credits, any undergraduate discipline). Students apply and are interviewed, then work in a team on a live project: the draft plan is signed off by the sponsor, with a group report (40%) and a pitch. The page fetched is headed 2024-2025; 23 students enrolled at the January 2025 launch. Delivery after that is not confirmed. - ED251A Engineering Work Experience (2025/26 catalogue, 15 credits): group consultancy project for a local engineering organisation, assessed by group report and group presentation; open to Level 2 students with Engineering studied. - ED3537 Employer-led Interdisciplinary Project (2025/26 catalogue, 30 credits, Level 3/4, any undergraduate programme): small-group consultancy-style project; the host-organisation role is not shown on the 2025/26 page, so employer connection is Unclear. - ED3536 Working Together (Arts & Social Sciences, group project from a local business or charity | X45: Current (2025/26-2026/27) delivery of PD2503 and ED3536 not confirmed; sponsor sectors/named partners not published on the pages read; ED251A compulsory status unknown; ED3537 host role on current page not shown; Grad Challenge page 404; ABDN Internships seven-week employer-project strand unverified; Business School, science, law and health yielded no verified current group-client routes (reduced-depth, ~8 searches/fetches in this resume). Further departmental instances likely.
A46: UK06 | B46: Reading | C46: UK | D46: Additional UK sample | E46: UK – additional | F46: 2027 | G46: 196 | H46: Complete | I46: =COUNTIFS('EL scheme register'!$A$7:$A$610,$A46,'EL scheme register'!$C$7:$C$610,"University-wide",'EL scheme register'!$AJ$7:$AJ$610,"Yes") | J46: =COUNTIFS('EL scheme register'!$A$7:$A$610,$A46,'EL scheme register'!$C$7:$C$610,"Cross-faculty",'EL scheme register'!$AJ$7:$AJ$610,"Yes") | K46: =COUNTIFS('EL scheme register'!$A$7:$A$610,$A46,'EL scheme register'!$C$7:$C$610,"Faculty/school",'EL scheme register'!$AJ$7:$AJ$610,"Yes") | L46: =COUNTIFS('EL scheme register'!$A$7:$A$610,$A46,'EL scheme register'!$C$7:$C$610,"Programme/course",'EL scheme register'!$AJ$7:$AJ$610,"Yes") | M46: =COUNTIFS('EL scheme register'!$A$7:$A$610,$A46,'EL scheme register'!$C$7:$C$610,"Unclear",'EL scheme register'!$AJ$7:$AJ$610,"Yes") | N46: =SUM(I46:M46) | O46: =COUNTIFS('EL scheme register'!$A$7:$A$610,$A46,'EL scheme register'!$AF$7:$AF$610,"Potentially relevant; evidence incomplete",'EL scheme register'!$AI$7:$AI$610,"Yes") | P46: =COUNTIFS('EL scheme register'!$A$7:$A$610,$A46,'EL scheme register'!$AF$7:$AF$610,"Outside strict definition") | Q46: =COUNTIF('EL exclusions & gaps'!$B$7:$B$5000,$A46) | R46: Not evidenced | S46: Not evidenced | T46: Entrepreneurship and Innovation Consultancy Project (MMM161) [Programme/course]; Capstone Project (ECM200) (ECM200) [Programme/course]; Real Estate Opportunities (Industry Challenge) (REMF56) [Programme/course] | U46: Business/management: 3; Arts/humanities/social sciences: 1 | V46: Several distributed routes | W46: Reading's documented employer-linked group provision is concentrated in postgraduate taught programmes in Henley Business School and the Economics group, with a few undergraduate leads. Qualifying routes (current 2025/26 evidence): (1) MMM161 Entrepreneurship and Innovation Consultancy Project (40 credits, MSc Entrepreneurship and Innovation), where teams work with a real host entrepreneur over June-July and each student writes a proposal for the host; (2) ECM200 Capstone Project (20 credits), where small supervised teams produce a report/presentation for an external organisation (businesses, government agencies, NGOs, start-ups) across MSc Economics-family and Public Policy programmes; (3) REMF56 Real Estate Opportunities, whose Industry Challenge (40% of the module) has teams respond to an industry partner's brief and present to that partner. Partial evidence: Henley's MMM190 (MSc Management) and MMM194 (MSc International Business) consulting projects and the Executive MBA team projects name organisations but do not show team structure or delivery year. Typography's Real Jobs live briefs are real-client but described as one-on-one. Food Technology's New Product Development is tea | X46: Searched with ~39 queries via search-index only. Unverified: group structure and delivery year for MMM190, MMM194, Executive MBA projects; whether MMM161 is compulsory in programmes beyond MSc Entrepreneurship and Innovation; partner identity for Food NPD and Going Public; individual vs team split for Typography Real Jobs; engineering/computing (further Built Environment client modules e.g. CE2CPR, Real Estate undergraduate projects), Pharmacy/Chemistry/Biological Sciences/Meteorology, Education, Film/Theatre/Art, MSc Environmental Management expert-panel contaminated-site project (clients from industry on panel) and other Henley PG programmes were not searched in depth; further departmental instances likely.
A47: UK07 | B47: Surrey | C47: UK | D47: Additional UK sample | E47: UK – additional | F47: 2027 | G47: 246 | H47: Complete | I47: =COUNTIFS('EL scheme register'!$A$7:$A$610,$A47,'EL scheme register'!$C$7:$C$610,"University-wide",'EL scheme register'!$AJ$7:$AJ$610,"Yes") | J47: =COUNTIFS('EL scheme register'!$A$7:$A$610,$A47,'EL scheme register'!$C$7:$C$610,"Cross-faculty",'EL scheme register'!$AJ$7:$AJ$610,"Yes") | K47: =COUNTIFS('EL scheme register'!$A$7:$A$610,$A47,'EL scheme register'!$C$7:$C$610,"Faculty/school",'EL scheme register'!$AJ$7:$AJ$610,"Yes") | L47: =COUNTIFS('EL scheme register'!$A$7:$A$610,$A47,'EL scheme register'!$C$7:$C$610,"Programme/course",'EL scheme register'!$AJ$7:$AJ$610,"Yes") | M47: =COUNTIFS('EL scheme register'!$A$7:$A$610,$A47,'EL scheme register'!$C$7:$C$610,"Unclear",'EL scheme register'!$AJ$7:$AJ$610,"Yes") | N47: =SUM(I47:M47) | O47: =COUNTIFS('EL scheme register'!$A$7:$A$610,$A47,'EL scheme register'!$AF$7:$AF$610,"Potentially relevant; evidence incomplete",'EL scheme register'!$AI$7:$AI$610,"Yes") | P47: =COUNTIFS('EL scheme register'!$A$7:$A$610,$A47,'EL scheme register'!$AF$7:$AF$610,"Outside strict definition") | Q47: =COUNTIF('EL exclusions & gaps'!$B$7:$B$5000,$A47) | R47: Not evidenced | S47: Not evidenced | T47: Consulting Project (MANM448) (MANM448) [Programme/course]; Dynamics of Business Consultancy (MSc Entrepreneurship & Innovation Management) [Programme/course]; Digital Business Challenge / Digital Project Development (MANM468) (MANM468) [Programme/course]; Hospitality, Tourism and Events Consultancy / Consultancy for the Visitor Economy (MAN3164 / MAN3251) (MAN3164 (2025/6); MAN3251 (listed 2025/6 and 2026/7)) [Programme/course]; Applied Business Project (MAN3213) - Semester 1 group partner project (MAN3213) [Programme/course]; Multi-Disciplinary Design Project (ENGM001) (ENGM001) [Faculty/school] | U47: Business/management: 5; Engineering/computing: 1 | V47: Several distributed routes | W47: Surrey's qualifying provision is concentrated in Surrey Business School, with one engineering route and several extracurricular Student Enterprise programmes. In the business school, small student teams act as consultants for external client organisations in compulsory MSc modules: Consulting Project (MANM448, MSc Management; group report and presentation, client feedback), Dynamics of Business Consultancy (MSc Entrepreneurship & Innovation Management), Digital Project Development (MANM468; partner companies meet teams at least two hours a week) and, on the 2024/5 evidence, Employee Resourcing (MANM466, client-mentored). Final-year hospitality and tourism students can take a team consultancy for an industry client (MAN3164/MAN3251, e.g. London Gatwick), and the 2026/7 Applied Business Project (MAN3213) puts groups with an external start-up partner. In engineering, the MEng Multi-Disciplinary Design Project (ENGM001) puts mixed-discipline groups on briefs from industry Visiting Professors, who meet them weekly and contribute to assessment. Extracurricular IKEEP and iTEK place teams of students on SME or charity challenges, but delivery after 2022 was not verified. Access is programm | X47: Further departmental instances likely (other FEPS group design projects, MSc programmes in business school). Client names, group sizes and participation numbers mostly unpublished. Science and arts/health coverage thin (about 3 searches each). MANM466, IKEEP and iTEK lack 2025/26 evidence. Dynamics of Business Consultancy and MANM468 may overlap.
A48: UK08 | B48: Sussex | C48: UK | D48: Additional UK sample | E48: UK – additional | F48: 2027 | G48: 273 | H48: Complete | I48: =COUNTIFS('EL scheme register'!$A$7:$A$610,$A48,'EL scheme register'!$C$7:$C$610,"University-wide",'EL scheme register'!$AJ$7:$AJ$610,"Yes") | J48: =COUNTIFS('EL scheme register'!$A$7:$A$610,$A48,'EL scheme register'!$C$7:$C$610,"Cross-faculty",'EL scheme register'!$AJ$7:$AJ$610,"Yes") | K48: =COUNTIFS('EL scheme register'!$A$7:$A$610,$A48,'EL scheme register'!$C$7:$C$610,"Faculty/school",'EL scheme register'!$AJ$7:$AJ$610,"Yes") | L48: =COUNTIFS('EL scheme register'!$A$7:$A$610,$A48,'EL scheme register'!$C$7:$C$610,"Programme/course",'EL scheme register'!$AJ$7:$AJ$610,"Yes") | M48: =COUNTIFS('EL scheme register'!$A$7:$A$610,$A48,'EL scheme register'!$C$7:$C$610,"Unclear",'EL scheme register'!$AJ$7:$AJ$610,"Yes") | N48: =SUM(I48:M48) | O48: =COUNTIFS('EL scheme register'!$A$7:$A$610,$A48,'EL scheme register'!$AF$7:$AF$610,"Potentially relevant; evidence incomplete",'EL scheme register'!$AI$7:$AI$610,"Yes") | P48: =COUNTIFS('EL scheme register'!$A$7:$A$610,$A48,'EL scheme register'!$AF$7:$AF$610,"Outside strict definition") | Q48: =COUNTIF('EL exclusions & gaps'!$B$7:$B$5000,$A48) | R48: Yes | S48: Not evidenced | T48: Career Lab Student Consultancy Programme [University-wide] | U48: Central provision: 1 | V48: Several distributed routes | W48: Reduced-depth review; all six areas queried. - Central: The Career Lab Student Consultancy Programme qualifies. Final-year undergraduates and taught postgraduates apply; selected students form small multidisciplinary teams that spend 3-4 weeks (c.20 hours) working on a brief set by an external organisation (charities/NGOs, startups, large corporates such as Hastings Direct) and present recommendations to the client. It is extracurricular, bursary-paid and runs three times in 2026/27. - Business School: The PG Consultancy Project (111N1) is a 30-credit summer group live consultancy for local organisations/businesses (e.g. Management MSc dissertation alternative), but the latest dated evidence is 2024/25. The UG Marketing Consultancy Project (Capstone) is a team brief-based capstone current in 2026 but with no evidenced real client (only tips from a consulting firm). - The legacy Connector Programme is an internal student-staff partnership scheme and does not meet criterion C. Engineering (MEng Group Project, no external client evidenced), sciences, arts/social sciences, Law Clinics and BSMS/IDS yielded no verified qualifying scheme at this depth; the Career Lab programme is promoted | X48: Reduced-depth: one query per area. PG Consultancy Project (S3) lacks 2025/26+ corroboration and client sector. Marketing capstone client unknown. Law Clinics, Community Media, Chemistry Industrial Project, Business Analytics/IBD projects, Changing the Face of Consultancy untested; further departmental instances likely.
A49: UK09 | B49: Leicester | C49: UK | D49: Additional UK sample | E49: UK – additional | F49: 2027 | G49: 314 | H49: Complete | I49: =COUNTIFS('EL scheme register'!$A$7:$A$610,$A49,'EL scheme register'!$C$7:$C$610,"University-wide",'EL scheme register'!$AJ$7:$AJ$610,"Yes") | J49: =COUNTIFS('EL scheme register'!$A$7:$A$610,$A49,'EL scheme register'!$C$7:$C$610,"Cross-faculty",'EL scheme register'!$AJ$7:$AJ$610,"Yes") | K49: =COUNTIFS('EL scheme register'!$A$7:$A$610,$A49,'EL scheme register'!$C$7:$C$610,"Faculty/school",'EL scheme register'!$AJ$7:$AJ$610,"Yes") | L49: =COUNTIFS('EL scheme register'!$A$7:$A$610,$A49,'EL scheme register'!$C$7:$C$610,"Programme/course",'EL scheme register'!$AJ$7:$AJ$610,"Yes") | M49: =COUNTIFS('EL scheme register'!$A$7:$A$610,$A49,'EL scheme register'!$C$7:$C$610,"Unclear",'EL scheme register'!$AJ$7:$AJ$610,"Yes") | N49: =SUM(I49:M49) | O49: =COUNTIFS('EL scheme register'!$A$7:$A$610,$A49,'EL scheme register'!$AF$7:$AF$610,"Potentially relevant; evidence incomplete",'EL scheme register'!$AI$7:$AI$610,"Yes") | P49: =COUNTIFS('EL scheme register'!$A$7:$A$610,$A49,'EL scheme register'!$AF$7:$AF$610,"Outside strict definition") | Q49: =COUNTIF('EL exclusions & gaps'!$B$7:$B$5000,$A49) | R49: Not evidenced | S49: Not evidenced | T49: Sustainability Enterprise Partnership Project (SEPP) (NT3100) [Cross-faculty] | U49: Science: 1; Engineering/computing: 1 | V49: Several distributed routes | W49: Leicester's provision is distributed across departments rather than institution-wide. The only university-wide commitments found are frameworks: the 100-hour work-related learning guarantee (compulsory for campus-based undergraduates from 2026/27, delivered through modules and including simulations and virtual internships) and the Leicester Award. Neither evidences a group client project by itself. Qualifying specific routes: the Sustainability Enterprise Partnership Project (NT3100, 15 credits, final-year option on several science and computing degrees) puts student groups with local SMEs to audit sustainability, delivering a group report to the business (2025/26 listing). Also documented, but with current-delivery status unclear: second-year software engineering team projects typically commissioned by real clients; the Industrial Mathematics Project (MA3513, 30 credits), where groups solve problems supplied by industrial partners; the Space Science and Engineering MSc Major Project, where teams complete a Phase A mission study for an industry-supplied concept reviewed by industry experts; and a Physics MPhys ten-week group project with an industrial partner (partner role unspecif | X49: Further departmental instances likely (e.g. History, Archaeology, Education, Psychology, Pharmacy, Geography group projects were not individually searched). Current-delivery evidence missing for most routes (undated pages; entry-year course pages). Group structure unknown for Client Led Media Production, EMPAIP project and Consultancy Challenge. Client types/numbers unpublished. PA3241 Physics Industry Project and Citizens for Change not assessed in detail. Business school lacks a verified live-client group module; no search-visible participation data.
A50: UK10 | B50: Strathclyde | C50: UK | D50: Additional UK sample | E50: UK – additional | F50: 2027 | G50: 230 | H50: Complete | I50: =COUNTIFS('EL scheme register'!$A$7:$A$610,$A50,'EL scheme register'!$C$7:$C$610,"University-wide",'EL scheme register'!$AJ$7:$AJ$610,"Yes") | J50: =COUNTIFS('EL scheme register'!$A$7:$A$610,$A50,'EL scheme register'!$C$7:$C$610,"Cross-faculty",'EL scheme register'!$AJ$7:$AJ$610,"Yes") | K50: =COUNTIFS('EL scheme register'!$A$7:$A$610,$A50,'EL scheme register'!$C$7:$C$610,"Faculty/school",'EL scheme register'!$AJ$7:$AJ$610,"Yes") | L50: =COUNTIFS('EL scheme register'!$A$7:$A$610,$A50,'EL scheme register'!$C$7:$C$610,"Programme/course",'EL scheme register'!$AJ$7:$AJ$610,"Yes") | M50: =COUNTIFS('EL scheme register'!$A$7:$A$610,$A50,'EL scheme register'!$C$7:$C$610,"Unclear",'EL scheme register'!$AJ$7:$AJ$610,"Yes") | N50: =SUM(I50:M50) | O50: =COUNTIFS('EL scheme register'!$A$7:$A$610,$A50,'EL scheme register'!$AF$7:$AF$610,"Potentially relevant; evidence incomplete",'EL scheme register'!$AI$7:$AI$610,"Yes") | P50: =COUNTIFS('EL scheme register'!$A$7:$A$610,$A50,'EL scheme register'!$AF$7:$AF$610,"Outside strict definition") | Q50: =COUNTIF('EL exclusions & gaps'!$B$7:$B$5000,$A50) | R50: Not evidenced | S50: Not evidenced | T50: DMEM Industrial Group Projects (IGP) / Industrial Projects scheme [Programme/course]; Becoming an Effective Business Analyst (BEBA) experiential learning class, MSc Business Analysis & Consulting (and pathway variants) [Programme/course] | U50: Engineering/computing: 1; Business/management: 1 | V50: Several distributed routes | W50: Strathclyde has several distributed, programme-embedded client-project routes, concentrated in Engineering and the Business School, plus a university-wide VIP4SD framework whose partner role is unclear. The clearest route is the Design, Manufacturing & Engineering Management (DMEM) Industrial Group Projects: companies set outline briefs, teams of senior undergraduate and postgraduate taught students work through four client-reviewed stages to a report or prototype, and the client attends the May/August presentation day (a 9 May 2025 presentation day is recorded). It is a compulsory element within DMEM programmes (40 credits on MSc Systems Engineering Management). The MSc Civil Engineering group design project (20 credits) adds industry mentors such as Arcadis and Skanska but lacks dated currency evidence. In Strathclyde Business School, the MSc Business Analysis & Consulting class (Becoming an Effective Business Analyst) has allocated teams solving client problems; a March 2026 newsletter names Deloitte, StormID, Sphera and WB Alloys. Team consultancy modules also appear in BA Business Analysis & Technology, Marketing Works (an option on MSc Marketing) and Consultancy in Practice, | X50: Most Business School and Civil Engineering pages are undated (some roughly a decade old), so current delivery is unconfirmed for S3, S5-S9. Credit values, compulsory status and assessment splits are missing for several routes. Further departmental instances likely (Honours client projects, Management Science 4, computing/mechanical group projects, Education, Product Design). VIP4SD partner roles and eligibility/credit not retrieved. Architecture scheme wording may blend with DMEM wording.
A51: UK11 | B51: Heriot-Watt | C51: UK | D51: Additional UK sample | E51: UK – additional | F51: 2027 | G51: 325 | H51: Complete | I51: =COUNTIFS('EL scheme register'!$A$7:$A$610,$A51,'EL scheme register'!$C$7:$C$610,"University-wide",'EL scheme register'!$AJ$7:$AJ$610,"Yes") | J51: =COUNTIFS('EL scheme register'!$A$7:$A$610,$A51,'EL scheme register'!$C$7:$C$610,"Cross-faculty",'EL scheme register'!$AJ$7:$AJ$610,"Yes") | K51: =COUNTIFS('EL scheme register'!$A$7:$A$610,$A51,'EL scheme register'!$C$7:$C$610,"Faculty/school",'EL scheme register'!$AJ$7:$AJ$610,"Yes") | L51: =COUNTIFS('EL scheme register'!$A$7:$A$610,$A51,'EL scheme register'!$C$7:$C$610,"Programme/course",'EL scheme register'!$AJ$7:$AJ$610,"Yes") | M51: =COUNTIFS('EL scheme register'!$A$7:$A$610,$A51,'EL scheme register'!$C$7:$C$610,"Unclear",'EL scheme register'!$AJ$7:$AJ$610,"Yes") | N51: =SUM(I51:M51) | O51: =COUNTIFS('EL scheme register'!$A$7:$A$610,$A51,'EL scheme register'!$AF$7:$AF$610,"Potentially relevant; evidence incomplete",'EL scheme register'!$AI$7:$AI$610,"Yes") | P51: =COUNTIFS('EL scheme register'!$A$7:$A$610,$A51,'EL scheme register'!$AF$7:$AF$610,"Outside strict definition") | Q51: =COUNTIF('EL exclusions & gaps'!$B$7:$B$5000,$A51) | R51: Not evidenced | S51: Not evidenced | V51: Unclear | W51: Heriot-Watt University (reduced-depth review, all six areas queried). No qualifying scheme was verified through the documented search; five programme-level leads remain evidence-incomplete. - Engineering: staff publication describes a Year 4 multidisciplinary final year project to an industrial client's specification (S1); B39VS System Project is a team project demonstrated to industry staff (2022/23 only) (S2). - Business: MSc International Business Management ends with a 'company consultancy project' (S3); the page does not say whether it is group-based or whether the company is external, and the course listing shows only a Dissertation. EBS lists a Consultancy Bootcamp with no detail. - Textiles and Design: Design for Textiles Year 3 offers a 'collaborative industry project' as an alternative to placement (S4); Fashion Branding and Promotion cites live projects with named brands (S5). Team format and standard coverage are unstated. - Central: Global Innovation Challenge is founder-led (excluded); micro-placements excluded. - Science, social sciences/languages: only individual dissertations and placements found. None has 2025/26 or 2026/27 dated delivery evidence. | X51: Group format, external-client coverage and current-year delivery unresolved for S1-S5. Architecture/built environment, GRID team challenges and Curriculum Explorer module detail not researched (reduced depth). Further departmental instances likely.
A52: UK12 | B52: East Anglia | C52: UK | D52: Additional UK sample | E52: UK – additional | F52: 2027 | G52: 381 | H52: Complete | I52: =COUNTIFS('EL scheme register'!$A$7:$A$610,$A52,'EL scheme register'!$C$7:$C$610,"University-wide",'EL scheme register'!$AJ$7:$AJ$610,"Yes") | J52: =COUNTIFS('EL scheme register'!$A$7:$A$610,$A52,'EL scheme register'!$C$7:$C$610,"Cross-faculty",'EL scheme register'!$AJ$7:$AJ$610,"Yes") | K52: =COUNTIFS('EL scheme register'!$A$7:$A$610,$A52,'EL scheme register'!$C$7:$C$610,"Faculty/school",'EL scheme register'!$AJ$7:$AJ$610,"Yes") | L52: =COUNTIFS('EL scheme register'!$A$7:$A$610,$A52,'EL scheme register'!$C$7:$C$610,"Programme/course",'EL scheme register'!$AJ$7:$AJ$610,"Yes") | M52: =COUNTIFS('EL scheme register'!$A$7:$A$610,$A52,'EL scheme register'!$C$7:$C$610,"Unclear",'EL scheme register'!$AJ$7:$AJ$610,"Yes") | N52: =SUM(I52:M52) | O52: =COUNTIFS('EL scheme register'!$A$7:$A$610,$A52,'EL scheme register'!$AF$7:$AF$610,"Potentially relevant; evidence incomplete",'EL scheme register'!$AI$7:$AI$610,"Yes") | P52: =COUNTIFS('EL scheme register'!$A$7:$A$610,$A52,'EL scheme register'!$AF$7:$AF$610,"Outside strict definition") | Q52: =COUNTIF('EL exclusions & gaps'!$B$7:$B$5000,$A52) | R52: Not evidenced | S52: Not evidenced | T52: Executive (Part-Time) MBA: group consultancy project with an external client [Programme/course]; MEng final-year Engineering Group Project (industry client brief) [Programme/course] | U52: Business/management: 1; Engineering/computing: 1 | V52: Several distributed routes | W52: UEA's documented provision is distributed across schools rather than set by a central framework. CareerCentral invites employers to set 'live briefs' for group projects inside course modules, but names no modules or cohorts, so it is an umbrella only. The firmest routes are programme-embedded. The Executive MBA runs a group-based consultancy project of about three months in which an external client chooses the topic and receives a report and presentation (2026/27 page). The MEng engineering degrees (Mechanical, Energy, Electrical and Electronic) end with a team project that is typically based on a real industry-client brief, with a site visit and a presentation to professional engineers. These are compulsory within those programmes, not institution-wide. Weaker or incomplete routes: MComp Computing group projects (industry problem or internal research group); an Economics consulting project option with an external organisation (team format unknown); MA Media, Communication and Global Development live projects with named charities and media bodies (group working not shown); Business Management live marketing briefs for Adnams and the East Anglian Zoological Society (course-page word | X52: WebFetch returned HTTP 405 for all uea.ac.uk pages; page text was instead retrieved by direct HTTPS download (curl) on 2026-10-13 and quoted for S2, S3, S5, S7, S8, S12 and the 'other' pages. Remaining sources (S1, S4, S6, S9, S10, S11) are still search summaries. Module codes/credits, team format (Economics, MA Media, NBS MSc options), and client names missing for most routes. School of Education and Natural Sciences schools (biology, chemistry, maths) only generally queried. Further departmental instances likely.
A53: UK13 | B53: Dundee | C53: UK | D53: Additional UK sample | E53: UK – additional | F53: 2027 | G53: 447 | H53: Complete | I53: =COUNTIFS('EL scheme register'!$A$7:$A$610,$A53,'EL scheme register'!$C$7:$C$610,"University-wide",'EL scheme register'!$AJ$7:$AJ$610,"Yes") | J53: =COUNTIFS('EL scheme register'!$A$7:$A$610,$A53,'EL scheme register'!$C$7:$C$610,"Cross-faculty",'EL scheme register'!$AJ$7:$AJ$610,"Yes") | K53: =COUNTIFS('EL scheme register'!$A$7:$A$610,$A53,'EL scheme register'!$C$7:$C$610,"Faculty/school",'EL scheme register'!$AJ$7:$AJ$610,"Yes") | L53: =COUNTIFS('EL scheme register'!$A$7:$A$610,$A53,'EL scheme register'!$C$7:$C$610,"Programme/course",'EL scheme register'!$AJ$7:$AJ$610,"Yes") | M53: =COUNTIFS('EL scheme register'!$A$7:$A$610,$A53,'EL scheme register'!$C$7:$C$610,"Unclear",'EL scheme register'!$AJ$7:$AJ$610,"Yes") | N53: =SUM(I53:M53) | O53: =COUNTIFS('EL scheme register'!$A$7:$A$610,$A53,'EL scheme register'!$AF$7:$AF$610,"Potentially relevant; evidence incomplete",'EL scheme register'!$AI$7:$AI$610,"Yes") | P53: =COUNTIFS('EL scheme register'!$A$7:$A$610,$A53,'EL scheme register'!$AF$7:$AF$610,"Outside strict definition") | Q53: =COUNTIF('EL exclusions & gaps'!$B$7:$B$5000,$A53) | R53: Not evidenced | S53: Not evidenced | V53: Several distributed routes | W53: Dundee shows several distributed, programme-level client-project routes rather than an institution-wide scheme. In computing, CS32002 Industrial Team Project has student teams build software proposed by an industry client (module page: 'for an industrial client'; group portfolio, presentation, peer review). In mechanical engineering, ME32003 Engineering Design II includes a 10-week group task working directly with a local industry partner. DJCAD's Going Live (DJ52027) has students collaborate on a live brief from an industry partner, and Research Through Design (DJ53010) has a team address a brief set by an external problem holder (partner type unclear). In Dundee Business School, Marketing Research Project (BU40025) uses group consulting teams but clients may be University departments, so employer connection is unclear; other consultancy modules are individual reports. The Careers Employer Team offers MSc live projects for up to five students reporting individually. The Venture competition is enterprise-based and excluded. All module pages are undated and none was corroborated for 2025/26, so current delivery is unconfirmed (a Nov 2025 news feature does confirm business-school emp | X53: Module pages undated; no 2025/26 corroboration for any scheme. Compulsory status per programme not checked. Not tested: BE32001 biomedical engineering, Graphic Design/Illustration live briefs, DJ31015 collaborative briefs, Architecture studios, further departmental instances likely. Search used about 13 searches plus about 9 WebFetch page opens (all succeeded; no curl needed). Science/health/law minimal.
A54: UK14 | B54: Swansea | C54: UK | D54: Additional UK sample | E54: UK – additional | F54: 2027 | G54: 322 | H54: Complete | I54: =COUNTIFS('EL scheme register'!$A$7:$A$610,$A54,'EL scheme register'!$C$7:$C$610,"University-wide",'EL scheme register'!$AJ$7:$AJ$610,"Yes") | J54: =COUNTIFS('EL scheme register'!$A$7:$A$610,$A54,'EL scheme register'!$C$7:$C$610,"Cross-faculty",'EL scheme register'!$AJ$7:$AJ$610,"Yes") | K54: =COUNTIFS('EL scheme register'!$A$7:$A$610,$A54,'EL scheme register'!$C$7:$C$610,"Faculty/school",'EL scheme register'!$AJ$7:$AJ$610,"Yes") | L54: =COUNTIFS('EL scheme register'!$A$7:$A$610,$A54,'EL scheme register'!$C$7:$C$610,"Programme/course",'EL scheme register'!$AJ$7:$AJ$610,"Yes") | M54: =COUNTIFS('EL scheme register'!$A$7:$A$610,$A54,'EL scheme register'!$C$7:$C$610,"Unclear",'EL scheme register'!$AJ$7:$AJ$610,"Yes") | N54: =SUM(I54:M54) | O54: =COUNTIFS('EL scheme register'!$A$7:$A$610,$A54,'EL scheme register'!$AF$7:$AF$610,"Potentially relevant; evidence incomplete",'EL scheme register'!$AI$7:$AI$610,"Yes") | P54: =COUNTIFS('EL scheme register'!$A$7:$A$610,$A54,'EL scheme register'!$AF$7:$AF$610,"Outside strict definition") | Q54: =COUNTIF('EL exclusions & gaps'!$B$7:$B$5000,$A54) | R54: Not evidenced | S54: Not evidenced | T54: Civil Engineering MEng Level 7 group design exercise (Probably EG-M360 / EG-M390 Integrated Industrial Project - Preliminary / Technical Design (20 credits each); link to the 'year-long group design exercise' inferred from titles, not stated) [Programme/course] | U54: Engineering/computing: 1 | V54: Isolated departmental provision | W54: Swansea University (reduced-depth review, all six areas queried). - Strongest route: Civil Engineering MEng (Level 7) 'year-long group design exercise' where students 'select from full design projects currently being carried out in industry' (course page text, 2026/27 module listing, with Integrated Industrial Project modules EG-M360/EG-M390). Meets A/B/C on the page wording; module mapping, firms' assessment role and named partners are not stated. BEng Level 6 design project uses a task set by industry engineers, but group working is not evidenced. - Business: BSc Economics and Business advertises a Business Consultancy Project on a 'live client real-world challenge', but group format, credits and status are not stated and it is not in the module tables. BSc Marketing offers a consultancy-project dissertation alternative (client unclear). MSc Project Management mentions live project challenges and partner dissertations (Tata Steel, Siemens, NHS) without separating routes. - Central/other: an extracurricular hackathon for Swansea City FC; Law Clinic casework is a near-miss (advice to the public, not a client project). Awards, Discovery volunteering and GO Wales are excluded. Provis | X54: Group format unverified for S2-S5; MBA 'Research in Action' client project uncited; other engineering disciplines, Computer Science group projects and wider Science, HSS and Health not explored beyond one query each; Formula Student unsourced. Further departmental instances likely.
A55: UK15 | B55: Essex | C55: UK | D55: Additional UK sample | E55: UK – additional | F55: 2027 | G55: 438 | H55: Complete | I55: =COUNTIFS('EL scheme register'!$A$7:$A$610,$A55,'EL scheme register'!$C$7:$C$610,"University-wide",'EL scheme register'!$AJ$7:$AJ$610,"Yes") | J55: =COUNTIFS('EL scheme register'!$A$7:$A$610,$A55,'EL scheme register'!$C$7:$C$610,"Cross-faculty",'EL scheme register'!$AJ$7:$AJ$610,"Yes") | K55: =COUNTIFS('EL scheme register'!$A$7:$A$610,$A55,'EL scheme register'!$C$7:$C$610,"Faculty/school",'EL scheme register'!$AJ$7:$AJ$610,"Yes") | L55: =COUNTIFS('EL scheme register'!$A$7:$A$610,$A55,'EL scheme register'!$C$7:$C$610,"Programme/course",'EL scheme register'!$AJ$7:$AJ$610,"Yes") | M55: =COUNTIFS('EL scheme register'!$A$7:$A$610,$A55,'EL scheme register'!$C$7:$C$610,"Unclear",'EL scheme register'!$AJ$7:$AJ$610,"Yes") | N55: =SUM(I55:M55) | O55: =COUNTIFS('EL scheme register'!$A$7:$A$610,$A55,'EL scheme register'!$AF$7:$AF$610,"Potentially relevant; evidence incomplete",'EL scheme register'!$AI$7:$AI$610,"Yes") | P55: =COUNTIFS('EL scheme register'!$A$7:$A$610,$A55,'EL scheme register'!$AF$7:$AF$610,"Outside strict definition") | Q55: =COUNTIF('EL exclusions & gaps'!$B$7:$B$5000,$A55) | R55: Not evidenced | S55: Not evidenced | T55: Business Law Clinic (Essex Law School) [Faculty/school] | U55: Other (law, health, design, architecture…): 1 | V55: Several distributed routes | W55: Provision found so far at Essex is led by iTeams, an extracurricular programme run by Essex Startups in which multidisciplinary student teams tackle challenges set by external businesses, mentored by industry experts, and present a report and pitch to a panel. It is selective (limited places, application), not credit-bearing as evidenced, and the latest evidenced edition is February 2025 (7 weeks, three businesses, six teams); a bespoke Cyber Innovate to Elevate variant connecting MSc/PhD students with SMEs ran to February 2026 but its team structure and outputs are not confirmed. Within Essex Business School, the Marketing Management module has students undertake a consultancy project for a real-world business, but whether this is group-based and how clients participate is not established; the MBA consultancy project is individual. Computer Science has a team project module without external clients and an individual capstone that can use company briefs. The Industry and Placements team promotes employer-led project briefs and live-project work-based learning (cited on Science and Health degree pages) but specific modules were not identified. The Big Essex Award is an employability | X55: Further departmental instances likely (Health, Nursing, Economics, Art History not searched in depth). iTeams 2025/26 not confirmed; Marketing Management group/client status unknown; Business Law Clinic credit and partner coverage unclear; Human Rights Clinic partner role unclear; WBL project modules unidentified. Reduced-depth review.
A56: UK16 | B56: Kent | C56: UK | D56: Additional UK sample | E56: UK – additional | F56: 2027 | G56: 415 | H56: Complete | I56: =COUNTIFS('EL scheme register'!$A$7:$A$610,$A56,'EL scheme register'!$C$7:$C$610,"University-wide",'EL scheme register'!$AJ$7:$AJ$610,"Yes") | J56: =COUNTIFS('EL scheme register'!$A$7:$A$610,$A56,'EL scheme register'!$C$7:$C$610,"Cross-faculty",'EL scheme register'!$AJ$7:$AJ$610,"Yes") | K56: =COUNTIFS('EL scheme register'!$A$7:$A$610,$A56,'EL scheme register'!$C$7:$C$610,"Faculty/school",'EL scheme register'!$AJ$7:$AJ$610,"Yes") | L56: =COUNTIFS('EL scheme register'!$A$7:$A$610,$A56,'EL scheme register'!$C$7:$C$610,"Programme/course",'EL scheme register'!$AJ$7:$AJ$610,"Yes") | M56: =COUNTIFS('EL scheme register'!$A$7:$A$610,$A56,'EL scheme register'!$C$7:$C$610,"Unclear",'EL scheme register'!$AJ$7:$AJ$610,"Yes") | N56: =SUM(I56:M56) | O56: =COUNTIFS('EL scheme register'!$A$7:$A$610,$A56,'EL scheme register'!$AF$7:$AF$610,"Potentially relevant; evidence incomplete",'EL scheme register'!$AI$7:$AI$610,"Yes") | P56: =COUNTIFS('EL scheme register'!$A$7:$A$610,$A56,'EL scheme register'!$AF$7:$AF$610,"Outside strict definition") | Q56: =COUNTIF('EL exclusions & gaps'!$B$7:$B$5000,$A56) | R56: Not evidenced | S56: Not evidenced | T56: KBS Challenge (BUSB6514) [Faculty/school] | U56: Business/management: 1 | V56: Several distributed routes | W56: Kent's strongest verified route is the KBS Challenge (BUSB6514): a Level 6, 20-credit Kent Business School module where groups consult for real businesses. In 2026, 106 students in 15 teams worked on 10 live projects over eight weeks for Port of Dover, Macknade, Barretts Kent and Enterprise Mobility, presenting recommendations back to the organisations; assessment is a group report and presentation plus individual blog. It meets all three criteria with 2026/27 evidence, but only KBS students are evidently eligible and it is not shown to be compulsory. Other leads are weaker. i-Teams (Careers and Employability Service, multi-disciplinary teams, sponsor challenges, mentor, Grand Final) fits the criteria and is open beyond business students, but the latest evidenced cohort is 2023 and no current delivery was found. The Business Analytics Challenge (BUSB7032) and MSc Strategic Project Management Challenge are consultancy-style team modules whose client role is unclear. IT consultancy (KITC) modules involve external clients but are individually assessed and not running. Engineering and physics group projects show no confirmed external client; Law Clinic is casework. The legacy Employabi | X56: Compulsory status of KBS Challenge and its eligibility threshold; i-Teams current delivery; client role in BUSB7032 and Strategic Project Management Challenge; MSc International Business live consultancy; engineering/computing and Digital Arts projects with industry advisers (2019 pages only); further departmental instances likely. Reduced-depth: 11 searches, 12 fetches.
A57: UK17 | B57: Brunel | C57: UK | D57: Additional UK sample | E57: UK – additional | F57: 2027 | G57: 353 | H57: Complete | I57: =COUNTIFS('EL scheme register'!$A$7:$A$610,$A57,'EL scheme register'!$C$7:$C$610,"University-wide",'EL scheme register'!$AJ$7:$AJ$610,"Yes") | J57: =COUNTIFS('EL scheme register'!$A$7:$A$610,$A57,'EL scheme register'!$C$7:$C$610,"Cross-faculty",'EL scheme register'!$AJ$7:$AJ$610,"Yes") | K57: =COUNTIFS('EL scheme register'!$A$7:$A$610,$A57,'EL scheme register'!$C$7:$C$610,"Faculty/school",'EL scheme register'!$AJ$7:$AJ$610,"Yes") | L57: =COUNTIFS('EL scheme register'!$A$7:$A$610,$A57,'EL scheme register'!$C$7:$C$610,"Programme/course",'EL scheme register'!$AJ$7:$AJ$610,"Yes") | M57: =COUNTIFS('EL scheme register'!$A$7:$A$610,$A57,'EL scheme register'!$C$7:$C$610,"Unclear",'EL scheme register'!$AJ$7:$AJ$610,"Yes") | N57: =SUM(I57:M57) | O57: =COUNTIFS('EL scheme register'!$A$7:$A$610,$A57,'EL scheme register'!$AF$7:$AF$610,"Potentially relevant; evidence incomplete",'EL scheme register'!$AI$7:$AI$610,"Yes") | P57: =COUNTIFS('EL scheme register'!$A$7:$A$610,$A57,'EL scheme register'!$AF$7:$AF$610,"Outside strict definition") | Q57: =COUNTIF('EL exclusions & gaps'!$B$7:$B$5000,$A57) | R57: Not evidenced | S57: Not evidenced | V57: Several distributed routes | W57: Brunel's clearest employer-linked route is Brunel Business School's Co-Innovate: SMEs write a project brief, a contract is issued on matching, work runs over the academic year and ends in a final report; it can be the 30-credit final-year project (BSc Business Management with Entrepreneurship). The page states projects can be done "either as an individual or in a small team", so group working is Unclear, the pages are undated, and 2025/26 delivery is unverified. Other leads: Design+ (businesses work with students on Final Year Projects since 2004; Brompton Bikes, Hornby, BT, JLR named; group/individual not stated), Leadership for Change (Year 3, students with a community organisation; compulsory/optional status inconsistent), MSc Project Management live consultancy (no clients named), Global Challenges BASc 8-week placement or group project (page not retrievable) and the Feb 2025 Enterprise Mobility Challenge (detail truncated). Engineering, computing, science and law searches found group projects without external clients. No route is verified as meeting all three criteria with current delivery; provision is distributed and programme-level. | X57: No dated 2025/26 evidence for any route; Co-Innovate team vs individual not separable; Design+ group status unknown; Global Challenges and Enterprise Mobility Challenge pages truncated; MSc PM client detail missing; further departmental capstones likely; reduced-depth search.
A58: UK18 | B58: Aston | C58: UK | D58: Additional UK sample | E58: UK – additional | F58: 2027 | G58: 416 | H58: Complete | I58: =COUNTIFS('EL scheme register'!$A$7:$A$610,$A58,'EL scheme register'!$C$7:$C$610,"University-wide",'EL scheme register'!$AJ$7:$AJ$610,"Yes") | J58: =COUNTIFS('EL scheme register'!$A$7:$A$610,$A58,'EL scheme register'!$C$7:$C$610,"Cross-faculty",'EL scheme register'!$AJ$7:$AJ$610,"Yes") | K58: =COUNTIFS('EL scheme register'!$A$7:$A$610,$A58,'EL scheme register'!$C$7:$C$610,"Faculty/school",'EL scheme register'!$AJ$7:$AJ$610,"Yes") | L58: =COUNTIFS('EL scheme register'!$A$7:$A$610,$A58,'EL scheme register'!$C$7:$C$610,"Programme/course",'EL scheme register'!$AJ$7:$AJ$610,"Yes") | M58: =COUNTIFS('EL scheme register'!$A$7:$A$610,$A58,'EL scheme register'!$C$7:$C$610,"Unclear",'EL scheme register'!$AJ$7:$AJ$610,"Yes") | N58: =SUM(I58:M58) | O58: =COUNTIFS('EL scheme register'!$A$7:$A$610,$A58,'EL scheme register'!$AF$7:$AF$610,"Potentially relevant; evidence incomplete",'EL scheme register'!$AI$7:$AI$610,"Yes") | P58: =COUNTIFS('EL scheme register'!$A$7:$A$610,$A58,'EL scheme register'!$AF$7:$AF$610,"Outside strict definition") | Q58: =COUNTIF('EL exclusions & gaps'!$B$7:$B$5000,$A58) | R58: Not evidenced | S58: Not evidenced | V58: Several distributed routes | W58: Aston provision found is distributed and mostly Business School based. The Aston Business Clinic puts student teams (ABC Originals, 8 weeks, Masters; ABC for Placement, 20-30 weeks, undergraduates) in front of external businesses and charities with a coach, and meets all three criteria on page text, but it is optional, credit is unstated and the page is undated, so current delivery is unconfirmed. The Aston London Interdisciplinary Collaborative Project ends in two assessed business challenges set by external organisations with multi-disciplinary teams, but level, credit, output and partners are unstated. BSc Business Enterprise and Innovation has core 30-credit consultancy projects whose client is 'live or simulated'. The legacy Aston Global Advantage row was reassessed: it is a strand of postgraduate taught programmes (not MBA or MRes) listing team challenges and live briefs as possible activities, so it is an umbrella lead and not verified as a qualifying route, and is not university-wide. Industry Clubs, MBA consultancy, Design Factory and postgraduate Business Projects are leads without module-level evidence. No dated 2025/26 or 2026/27 evidence was found for any route. No qua | X58: Reduced-depth review (about 8 searches plus 9 fetches). No dated current-year evidence; credit and eligibility of Aston Business Clinic unclear; Aston London module detail; Industry Club module links and the CEPS student-led enterprise not identified; AGA stream-two page requires login (not retrievable); no law, health or science team-client modules found; further departmental instances likely. Retrieval was WebFetch (fetch-tool summaries, not verbatim page text) and WebSearch extracts.
A59: UK19 | B59: Stirling | C59: UK | D59: Additional UK sample | E59: UK – additional | F59: 2027 | G59: 560 | H59: Complete | I59: =COUNTIFS('EL scheme register'!$A$7:$A$610,$A59,'EL scheme register'!$C$7:$C$610,"University-wide",'EL scheme register'!$AJ$7:$AJ$610,"Yes") | J59: =COUNTIFS('EL scheme register'!$A$7:$A$610,$A59,'EL scheme register'!$C$7:$C$610,"Cross-faculty",'EL scheme register'!$AJ$7:$AJ$610,"Yes") | K59: =COUNTIFS('EL scheme register'!$A$7:$A$610,$A59,'EL scheme register'!$C$7:$C$610,"Faculty/school",'EL scheme register'!$AJ$7:$AJ$610,"Yes") | L59: =COUNTIFS('EL scheme register'!$A$7:$A$610,$A59,'EL scheme register'!$C$7:$C$610,"Programme/course",'EL scheme register'!$AJ$7:$AJ$610,"Yes") | M59: =COUNTIFS('EL scheme register'!$A$7:$A$610,$A59,'EL scheme register'!$C$7:$C$610,"Unclear",'EL scheme register'!$AJ$7:$AJ$610,"Yes") | N59: =SUM(I59:M59) | O59: =COUNTIFS('EL scheme register'!$A$7:$A$610,$A59,'EL scheme register'!$AF$7:$AF$610,"Potentially relevant; evidence incomplete",'EL scheme register'!$AI$7:$AI$610,"Yes") | P59: =COUNTIFS('EL scheme register'!$A$7:$A$610,$A59,'EL scheme register'!$AF$7:$AF$610,"Outside strict definition") | Q59: =COUNTIF('EL exclusions & gaps'!$B$7:$B$5000,$A59) | R59: Not evidenced | S59: Not evidenced | V59: Isolated departmental provision | W59: Stirling (UK19), reduced-depth review. Provision is concentrated in the Management School's postgraduate taught programmes. The clearest routes are the MSc Marketing Consultancy Project (described as a core module for over twenty years) and the MSc Digital Marketing and Brand Management project: in both, 'each group has a client organisation that sets a real-world task', and groups present solutions to the client over the summer. Past clients include Stirling Albion FC, Snowsports Scotland, National Wallace Monument and EASA Training Ltd, spanning private, public and third-sector bodies. A wider summer consultancy elective on seven Masters programmes (MBA, Business Analytics, etc.) matches students to host businesses, charities or public bodies with a university supervisor and client mentor, but the employer page says projects may be done by 'an individual or group', so group working is unclear. MANP005 Business Consulting (20 credits, 2026/7 listing) refers to an external client but shows no assessment or group detail. Careers lists 21 employer-facing placement schemes (arts, law, sport, computing, life sciences etc.); the pages examined are individual or placement-style and are n | X59: Reduced-depth. No dated 2025/26-2026/27 corroboration for S1-S3. Marketing module code, credit and assessment unknown. 21 Careers placement schemes only indexed. Group vs individual split in summer consultancy elective unresolved. Natural Sciences 'Projects with business' page returned 404. Retrieval: WebFetch page text (fetch tool returns a model-generated summary/quotes rather than raw page); searches via WebSearch.
A60: UK20 | B60: SOAS | C60: UK | D60: Additional UK sample | E60: UK – additional | F60: 2027 | G60: 458 | H60: Complete | I60: =COUNTIFS('EL scheme register'!$A$7:$A$610,$A60,'EL scheme register'!$C$7:$C$610,"University-wide",'EL scheme register'!$AJ$7:$AJ$610,"Yes") | J60: =COUNTIFS('EL scheme register'!$A$7:$A$610,$A60,'EL scheme register'!$C$7:$C$610,"Cross-faculty",'EL scheme register'!$AJ$7:$AJ$610,"Yes") | K60: =COUNTIFS('EL scheme register'!$A$7:$A$610,$A60,'EL scheme register'!$C$7:$C$610,"Faculty/school",'EL scheme register'!$AJ$7:$AJ$610,"Yes") | L60: =COUNTIFS('EL scheme register'!$A$7:$A$610,$A60,'EL scheme register'!$C$7:$C$610,"Programme/course",'EL scheme register'!$AJ$7:$AJ$610,"Yes") | M60: =COUNTIFS('EL scheme register'!$A$7:$A$610,$A60,'EL scheme register'!$C$7:$C$610,"Unclear",'EL scheme register'!$AJ$7:$AJ$610,"Yes") | N60: =SUM(I60:M60) | O60: =COUNTIFS('EL scheme register'!$A$7:$A$610,$A60,'EL scheme register'!$AF$7:$AF$610,"Potentially relevant; evidence incomplete",'EL scheme register'!$AI$7:$AI$610,"Yes") | P60: =COUNTIFS('EL scheme register'!$A$7:$A$610,$A60,'EL scheme register'!$AF$7:$AF$610,"Outside strict definition") | Q60: =COUNTIF('EL exclusions & gaps'!$B$7:$B$5000,$A60) | R60: Not evidenced | S60: Not evidenced | V60: Isolated departmental provision | W60: Reduced-depth review (about 10 searches plus page fetches). The strongest route is the SOAS Virtual Industry Project (legacy row), a Careers/Practera two-week extracurricular scheme open to all second- and final-year undergraduates (100 places a year). Assigned teams work remotely on one employer brief per team (startups, SMEs and NGOs, about 15 clients in the March 2025 news item) and submit a final report with recommendations. It meets project, group and employer criteria, but the pages are undated apart from the 2025 news story, so current delivery is unconfirmed, and it is only 25 hours long. Curricular routes are thin. The MSc Finance / International Business optional 30-credit Practical Industry Project embeds a Practera experience with groups of 5-6 on a client brief, but client identity is unverified and the source page could not be opened (HTTP 403), so evidence is a search extract. The optional International Development Placement puts teams of 2-9 with development partner organisations for 40 hours (capped at 75), but no project output is evidenced. SOAS Careers also advertises an employer-facing Student Consultancy Project with no team or cohort evidence. Law clinics, in | X60: Current 2025/26-2026/27 delivery of the Virtual Industry Project, Practical Industry Project and International Development Placement unverified; MSc Finance page returned 403 to WebFetch and curl; client identities for the MSc module unknown; other Practera-style or departmental projects (e.g. MSc International Marketing, BSc Management, Law, Economics) not researched in reduced-depth mode; Student Consultancy Project team structure unknown.
A61: UK21 | B61: Birkbeck | C61: UK | D61: Additional UK sample | E61: UK – additional | F61: 2027 | G61: 354 | H61: Complete | I61: =COUNTIFS('EL scheme register'!$A$7:$A$610,$A61,'EL scheme register'!$C$7:$C$610,"University-wide",'EL scheme register'!$AJ$7:$AJ$610,"Yes") | J61: =COUNTIFS('EL scheme register'!$A$7:$A$610,$A61,'EL scheme register'!$C$7:$C$610,"Cross-faculty",'EL scheme register'!$AJ$7:$AJ$610,"Yes") | K61: =COUNTIFS('EL scheme register'!$A$7:$A$610,$A61,'EL scheme register'!$C$7:$C$610,"Faculty/school",'EL scheme register'!$AJ$7:$AJ$610,"Yes") | L61: =COUNTIFS('EL scheme register'!$A$7:$A$610,$A61,'EL scheme register'!$C$7:$C$610,"Programme/course",'EL scheme register'!$AJ$7:$AJ$610,"Yes") | M61: =COUNTIFS('EL scheme register'!$A$7:$A$610,$A61,'EL scheme register'!$C$7:$C$610,"Unclear",'EL scheme register'!$AJ$7:$AJ$610,"Yes") | N61: =SUM(I61:M61) | O61: =COUNTIFS('EL scheme register'!$A$7:$A$610,$A61,'EL scheme register'!$AF$7:$AF$610,"Potentially relevant; evidence incomplete",'EL scheme register'!$AI$7:$AI$610,"Yes") | P61: =COUNTIFS('EL scheme register'!$A$7:$A$610,$A61,'EL scheme register'!$AF$7:$AF$610,"Outside strict definition") | Q61: =COUNTIF('EL exclusions & gaps'!$B$7:$B$5000,$A61) | R61: Not evidenced | S61: Not evidenced | T61: The Consultancy Challenge (MSc Management Consultancy and Organisational Change) (BUOB063D7) [Programme/course] | U61: Business/management: 1 | V61: Isolated departmental provision | W61: Birkbeck's one verified route meeting all three criteria is The Consultancy Challenge (BUOB063D7), a 60-credit final-project option on the MSc Management Consultancy and Organisational Change. In partnership with PA Consulting, students are assembled into teams to work on a real, live problem for a PA client over about 12 weeks, with a PA consultant mentoring each team. The programme page names Defra and the RSPCA as clients; a 2023 blog says two large UK charities. Assessment is mainly group-based (group status presentations 35%, group report 35%, individual reflective essay 30%). It is an alternative to an individual research project, selective with limited places, and open only to students on that one MSc. The 2025-26 programme specification lists it as a core option. Other provision is weaker. The central micro-placement module (CASC002H5) is an individual student-sourced placement. The PG Cert Applied Data Science project mentions a work-based project but group working and employer role are unclear. Applied Software Engineering has a group programming project with no external client evidenced. Pioneer is enterprise support, and law clinics are casework placements. No instituti | X61: Not verified: team sizes/number of Consultancy Challenge teams and 2025/26 client names (client names on undated pages); group status and employer role of the PG Cert Applied Data Science project; whether other BEI MSc programmes or UG business modules have live-client group projects; Birkbeck Business School UG modules not specifically queried. Reduced-depth review (about 10 searches); further departmental instances possible.
A62: UK22 | B62: Royal Holloway | C62: UK | D62: Additional UK sample | E62: UK – additional | F62: 2027 | G62: 485 | H62: Complete | I62: =COUNTIFS('EL scheme register'!$A$7:$A$610,$A62,'EL scheme register'!$C$7:$C$610,"University-wide",'EL scheme register'!$AJ$7:$AJ$610,"Yes") | J62: =COUNTIFS('EL scheme register'!$A$7:$A$610,$A62,'EL scheme register'!$C$7:$C$610,"Cross-faculty",'EL scheme register'!$AJ$7:$AJ$610,"Yes") | K62: =COUNTIFS('EL scheme register'!$A$7:$A$610,$A62,'EL scheme register'!$C$7:$C$610,"Faculty/school",'EL scheme register'!$AJ$7:$AJ$610,"Yes") | L62: =COUNTIFS('EL scheme register'!$A$7:$A$610,$A62,'EL scheme register'!$C$7:$C$610,"Programme/course",'EL scheme register'!$AJ$7:$AJ$610,"Yes") | M62: =COUNTIFS('EL scheme register'!$A$7:$A$610,$A62,'EL scheme register'!$C$7:$C$610,"Unclear",'EL scheme register'!$AJ$7:$AJ$610,"Yes") | N62: =SUM(I62:M62) | O62: =COUNTIFS('EL scheme register'!$A$7:$A$610,$A62,'EL scheme register'!$AF$7:$AF$610,"Potentially relevant; evidence incomplete",'EL scheme register'!$AI$7:$AI$610,"Yes") | P62: =COUNTIFS('EL scheme register'!$A$7:$A$610,$A62,'EL scheme register'!$AF$7:$AF$610,"Outside strict definition") | Q62: =COUNTIF('EL exclusions & gaps'!$B$7:$B$5000,$A62) | R62: Not evidenced | S62: Not evidenced | V62: Isolated departmental provision | W62: No scheme fully meeting all three criteria was verified through the documented search. The strongest lead is CS4825 MSci Team Project, a mandatory 60-credit final-year module on the Software Engineering MSci in which teams operate as a company on projects 'for real clients' (2025/26 programme specification). Group and project criteria are met, but sources do not say whether clients are external organisations or the department's in-house company CodeGroovers, and the programme outcome says 'realistic client', so employer connection is Unclear. In the School of Business and Management, MN5802 Consultancy in the Digital Era (mandatory, MSc Digital Business, 15 credits) is described in a search extract as team consultancy for a client, and MN5621 Digital Marketing Consultancy has a client-prescribed project with findings presented to the client; for both, client type, group basis (MN5621) and current delivery are unconfirmed. Other consulting capstones (AI for Business, Business Analytics) are individual. No central, university-wide employer-project route was found; the Careers Service offers placements and events, and the Volunteer Awards (legacy row) recognise individual volunteering | X62: Client identity for CS4825 and for MN5802/MN5621; MN5621 group basis; current delivery for the two business modules; CS2815 and Year 3 Geography/CIMA/Dragon's Den activities; Law, Psychology, Media, Health not exhaustively searched (reduced-depth mode, 11 searches); several PDFs read via local text extraction; search results note many Royal Holloway pages are several years old.
A63: UK23 | B63: City St George’s | C63: UK | D63: Additional UK sample | E63: UK – additional | F63: 2027 | G63: 361 | H63: Complete | I63: =COUNTIFS('EL scheme register'!$A$7:$A$610,$A63,'EL scheme register'!$C$7:$C$610,"University-wide",'EL scheme register'!$AJ$7:$AJ$610,"Yes") | J63: =COUNTIFS('EL scheme register'!$A$7:$A$610,$A63,'EL scheme register'!$C$7:$C$610,"Cross-faculty",'EL scheme register'!$AJ$7:$AJ$610,"Yes") | K63: =COUNTIFS('EL scheme register'!$A$7:$A$610,$A63,'EL scheme register'!$C$7:$C$610,"Faculty/school",'EL scheme register'!$AJ$7:$AJ$610,"Yes") | L63: =COUNTIFS('EL scheme register'!$A$7:$A$610,$A63,'EL scheme register'!$C$7:$C$610,"Programme/course",'EL scheme register'!$AJ$7:$AJ$610,"Yes") | M63: =COUNTIFS('EL scheme register'!$A$7:$A$610,$A63,'EL scheme register'!$C$7:$C$610,"Unclear",'EL scheme register'!$AJ$7:$AJ$610,"Yes") | N63: =SUM(I63:M63) | O63: =COUNTIFS('EL scheme register'!$A$7:$A$610,$A63,'EL scheme register'!$AF$7:$AF$610,"Potentially relevant; evidence incomplete",'EL scheme register'!$AI$7:$AI$610,"Yes") | P63: =COUNTIFS('EL scheme register'!$A$7:$A$610,$A63,'EL scheme register'!$AF$7:$AF$610,"Outside strict definition") | Q63: =COUNTIF('EL exclusions & gaps'!$B$7:$B$5000,$A63) | R63: Not evidenced | S63: Not evidenced | T63: Hewlett Packard Enterprise: Technology Consulting [Programme/course]; Sustainability and Climate Change (interdisciplinary module) [Programme/course] | U63: Engineering/computing: 1; Central provision: 1; Other (law, health, design, architecture…): 1 | V63: Several distributed routes | W63: City St George's has no single institution-wide route in the documented search. Several employer-linked group routes were found, mostly in final-year or master's modules. Central route. Industry Led Projects is a credit-bearing third-year undergraduate module family, run through the Corporate Relations & Employability Unit, for Bayes, City Law School, Policy & Global Affairs and Communication & Creativity. Degree pages describe small multi-disciplinary groups choosing one of five sector streams and working on briefs set by employers, who pay nothing. The central page also allows individual work, and no dated 2025/26 or 2026/27 evidence was found. Other routes. The 15-credit Hewlett Packard Enterprise: Technology Consulting module (computing and data science MSci, Year 3) has groups solving an assigned SME's technical challenge with HPE mentors. It is listed on 2026/27 course pages. The Sustainability and Climate Change module, launched in 2025 and first offered to law students, has teams on external-partner challenges, with 2026 award news. In Bayes, the MSc Consulting Challenge (teams of five, May-August) and the MBA Strategy Project involve live clients but rest on undated pages. | X63: Pages were not opened: WebFetch returned 403 and curl met a Cloudflare challenge on citystgeorges.ac.uk, so all sources are search-summary paraphrase and no verbatim quotes were obtained. Needed next: dated 2025/26 or 2026/27 evidence for Industry Led Projects and Bayes consulting routes; module specs (BM3003 Applied Industry Business Project, PO3100); compulsory vs optional status; named partners; St George's legacy health programmes (nursing, midwifery, physician associate, radiography) and School of Health & Medical Sciences were not probed beyond one query; further departmental instances likely.
A64: UK24 | B64: Oxford Brookes | C64: UK | D64: Additional UK sample | E64: UK – additional | F64: 2027 | G64: 411 | H64: Complete | I64: =COUNTIFS('EL scheme register'!$A$7:$A$610,$A64,'EL scheme register'!$C$7:$C$610,"University-wide",'EL scheme register'!$AJ$7:$AJ$610,"Yes") | J64: =COUNTIFS('EL scheme register'!$A$7:$A$610,$A64,'EL scheme register'!$C$7:$C$610,"Cross-faculty",'EL scheme register'!$AJ$7:$AJ$610,"Yes") | K64: =COUNTIFS('EL scheme register'!$A$7:$A$610,$A64,'EL scheme register'!$C$7:$C$610,"Faculty/school",'EL scheme register'!$AJ$7:$AJ$610,"Yes") | L64: =COUNTIFS('EL scheme register'!$A$7:$A$610,$A64,'EL scheme register'!$C$7:$C$610,"Programme/course",'EL scheme register'!$AJ$7:$AJ$610,"Yes") | M64: =COUNTIFS('EL scheme register'!$A$7:$A$610,$A64,'EL scheme register'!$C$7:$C$610,"Unclear",'EL scheme register'!$AJ$7:$AJ$610,"Yes") | N64: =SUM(I64:M64) | O64: =COUNTIFS('EL scheme register'!$A$7:$A$610,$A64,'EL scheme register'!$AF$7:$AF$610,"Potentially relevant; evidence incomplete",'EL scheme register'!$AI$7:$AI$610,"Yes") | P64: =COUNTIFS('EL scheme register'!$A$7:$A$610,$A64,'EL scheme register'!$AF$7:$AF$610,"Outside strict definition") | Q64: =COUNTIF('EL exclusions & gaps'!$B$7:$B$5000,$A64) | R64: Not evidenced | S64: Not evidenced | T64: Business Challenge Week (also called Impact Challenge Week) [Faculty/school] | U64: Business/management: 1 | V64: Isolated departmental provision | W64: Oxford Brookes has no university-wide employer project scheme found in this reduced-depth review; qualifying provision sits mainly in Oxford Brookes Business School. Qualifying routes. Business Challenge Week (also named Impact Challenge Week) is an intensive week in which teams of master's students tackle problems set by external organisations of any size, brief and receive feedback from the partners, and pitch to business judges; the partner page gives 8-12 June 2026 and a 2024 edition reportedly involved 45 students. The Summer Student Consultancy Scheme places teams of 2-3 business/accounting/marketing undergraduates with an organisation brief for four weeks (40-80 hours), with a client supervisor, university mentor, final report and showcase; the page evidences the 2027 round. Both appear extracurricular or co-curricular with no credit stated. Embedded routes with incomplete evidence. The Global MBA compulsory Client Project and the optional MSc Management Group Consultancy Project put cross-cultural teams on a real problem in a client organisation, but outputs, credit and client role are undocumented. The compulsory Year 2 Live Client Strategic Project on BA Business and Mana | X64: Module handbooks not accessed (credits, group size, client roles for MBA Client Project, MSc Management Group Consultancy Project, BA Live Client Strategic Project). Business Challenge Week 2024 news page returned 404 so 2024 figures rest on a search summary; 2026 edition outcome unverified. Summer scheme 2026 round unverified (2027 page only). Health (nursing, allied health), design, planning, and further departmental capstones were not individually researched; further instances likely. Retrieval for page text was WebFetch with a fetch-model summary, not raw HTML.
A65: UK25 | B65: Northumbria | C65: UK | D65: Additional UK sample | E65: UK – additional | F65: 2027 | G65: 528 | H65: Complete | I65: =COUNTIFS('EL scheme register'!$A$7:$A$610,$A65,'EL scheme register'!$C$7:$C$610,"University-wide",'EL scheme register'!$AJ$7:$AJ$610,"Yes") | J65: =COUNTIFS('EL scheme register'!$A$7:$A$610,$A65,'EL scheme register'!$C$7:$C$610,"Cross-faculty",'EL scheme register'!$AJ$7:$AJ$610,"Yes") | K65: =COUNTIFS('EL scheme register'!$A$7:$A$610,$A65,'EL scheme register'!$C$7:$C$610,"Faculty/school",'EL scheme register'!$AJ$7:$AJ$610,"Yes") | L65: =COUNTIFS('EL scheme register'!$A$7:$A$610,$A65,'EL scheme register'!$C$7:$C$610,"Programme/course",'EL scheme register'!$AJ$7:$AJ$610,"Yes") | M65: =COUNTIFS('EL scheme register'!$A$7:$A$610,$A65,'EL scheme register'!$C$7:$C$610,"Unclear",'EL scheme register'!$AJ$7:$AJ$610,"Yes") | N65: =SUM(I65:M65) | O65: =COUNTIFS('EL scheme register'!$A$7:$A$610,$A65,'EL scheme register'!$AF$7:$AF$610,"Potentially relevant; evidence incomplete",'EL scheme register'!$AI$7:$AI$610,"Yes") | P65: =COUNTIFS('EL scheme register'!$A$7:$A$610,$A65,'EL scheme register'!$AF$7:$AF$610,"Outside strict definition") | Q65: =COUNTIF('EL exclusions & gaps'!$B$7:$B$5000,$A65) | R65: Not evidenced | S65: Not evidenced | T65: NX9626 Undergraduate Consultancy Project (Business Clinic) (NX9626) [Faculty/school]; NX0479 Business Clinic PG Group Consultancy Project (also NX0477 NBS Masters Consultancy Project) (NX0479 (NX0477 on MSc International Finance and Investment)) [Faculty/school]; Advanced Practice Semester via Engineering and Environment Live Projects Hub (KB7056 (Mechanical Eng.), KA7057 (Construction PM with BIM) and equivalents) [Faculty/school] | U65: Business/management: 2; Engineering/computing: 1; Science: 1 | V65: Several distributed routes | W65: Northumbria runs employer-linked group projects through faculty-hosted routes rather than one institution-wide scheme. The strongest is the Newcastle Business School Business Clinic: NX9626 (final-year UG, self-selected groups of typically four working 'on behalf of an external organisation') and NX0479/NX0477 (PG Advanced Practice group consultancy for a host organisation). A July 2026 release documents a four-student team advising a parish church; the Clinic reports over 950 projects and 3,820+ students since 2013, mostly pro bono for SMEs, charities and larger firms. The Faculty of Engineering and Environment Live Projects Hub procures 12-week industry projects (around 100 businesses) which Advanced Practice Masters students deliver in small teams in the 60-credit Advanced Practice Semester (e.g. KB7056, 2026 listing). Computing offers KV5037 Computing Consultancy Project and 12-week undergraduate live projects, but group basis and compulsory status are unclear. The central experiential-learning page claims about 700 students per year complete a live project or clinic module (2021/22 audit) and the Projects page lists Film Live Briefs, Sport Outreach, Student Law Office and Buil | X65: Compulsory/optional status for NX9626, KV5037 and Advanced Practice Semester modules; Live Projects Hub page last reviewed 2023; NX0477 and London campus clinic only from search summaries; Film Live Briefs, Sport Event Management, design live-brief modules and the Computing school's 'every undergraduate' live-project claim not verified at module level; no module-level evidence found for Applied Sciences, Geography/Environmental Sciences or Social Sciences; further departmental instances likely. Reduced-depth mode: 10 searches, 9 page fetches.
A66: UK26 | B66: Portsmouth | C66: UK | D66: Additional UK sample | E66: UK – additional | F66: 2027 | G66: 662 | H66: Complete | I66: =COUNTIFS('EL scheme register'!$A$7:$A$610,$A66,'EL scheme register'!$C$7:$C$610,"University-wide",'EL scheme register'!$AJ$7:$AJ$610,"Yes") | J66: =COUNTIFS('EL scheme register'!$A$7:$A$610,$A66,'EL scheme register'!$C$7:$C$610,"Cross-faculty",'EL scheme register'!$AJ$7:$AJ$610,"Yes") | K66: =COUNTIFS('EL scheme register'!$A$7:$A$610,$A66,'EL scheme register'!$C$7:$C$610,"Faculty/school",'EL scheme register'!$AJ$7:$AJ$610,"Yes") | L66: =COUNTIFS('EL scheme register'!$A$7:$A$610,$A66,'EL scheme register'!$C$7:$C$610,"Programme/course",'EL scheme register'!$AJ$7:$AJ$610,"Yes") | M66: =COUNTIFS('EL scheme register'!$A$7:$A$610,$A66,'EL scheme register'!$C$7:$C$610,"Unclear",'EL scheme register'!$AJ$7:$AJ$610,"Yes") | N66: =SUM(I66:M66) | O66: =COUNTIFS('EL scheme register'!$A$7:$A$610,$A66,'EL scheme register'!$AF$7:$AF$610,"Potentially relevant; evidence incomplete",'EL scheme register'!$AI$7:$AI$610,"Yes") | P66: =COUNTIFS('EL scheme register'!$A$7:$A$610,$A66,'EL scheme register'!$AF$7:$AF$610,"Outside strict definition") | Q66: =COUNTIF('EL exclusions & gaps'!$B$7:$B$5000,$A66) | R66: Not evidenced | S66: Not evidenced | T66: Business Consultancy Project (BCP) [Faculty/school] | U66: Business/management: 1 | V66: Several distributed routes | W66: Portsmouth has a clear, long-established flagship route in the Business School: the 20-credit Business Consultancy Project, where final-year undergraduate teams of 3-4 spend about ten weeks on a live challenge for a local SME or public/third-sector organisation, producing a consultancy report and a presentation with Q&A to the client. Past clients named on the course page include Santander, Inovolt and Express FM, and the client page says applications for 2026 projects had closed, which supports current delivery. A separate Global MBA route runs 10-week team projects (June-September) for local SMEs, but its cohort dates and module are not evidenced. In computing, Computer Science lists a core 30-credit Industrial Team Project with an external client and an optional 20-credit Complex Problem Solving module using an industry partner's brief, though the pages are for September 2027 entry and give no duration, assessment or named partners. Law in Action has teams presenting to community organisations but the client role is unclear. Leads for the Architecture Project Office (extracurricular), Accounting Clinic, Marketing Consultancy Project and Creative Computing live briefs were not ve | X66: Business Consultancy Project module code, courses offering it and enrolment numbers not found. MBA route and the two Computer Science modules lack dated 2025/26-2026/27 corroboration (course pages show September 2027 entry). Architecture Project Office, Accounting Clinic, Marketing Consultancy Project and Creative Computing live-brief modules unverified. Health faculties (nursing, dentistry etc.) not searched in reduced-depth mode. Further departmental instances likely.
A67: UK27 | B67: Coventry | C67: UK | D67: Additional UK sample | E67: UK – additional | F67: 2027 | G67: 581 | H67: Complete | I67: =COUNTIFS('EL scheme register'!$A$7:$A$610,$A67,'EL scheme register'!$C$7:$C$610,"University-wide",'EL scheme register'!$AJ$7:$AJ$610,"Yes") | J67: =COUNTIFS('EL scheme register'!$A$7:$A$610,$A67,'EL scheme register'!$C$7:$C$610,"Cross-faculty",'EL scheme register'!$AJ$7:$AJ$610,"Yes") | K67: =COUNTIFS('EL scheme register'!$A$7:$A$610,$A67,'EL scheme register'!$C$7:$C$610,"Faculty/school",'EL scheme register'!$AJ$7:$AJ$610,"Yes") | L67: =COUNTIFS('EL scheme register'!$A$7:$A$610,$A67,'EL scheme register'!$C$7:$C$610,"Programme/course",'EL scheme register'!$AJ$7:$AJ$610,"Yes") | M67: =COUNTIFS('EL scheme register'!$A$7:$A$610,$A67,'EL scheme register'!$C$7:$C$610,"Unclear",'EL scheme register'!$AJ$7:$AJ$610,"Yes") | N67: =SUM(I67:M67) | O67: =COUNTIFS('EL scheme register'!$A$7:$A$610,$A67,'EL scheme register'!$AF$7:$AF$610,"Potentially relevant; evidence incomplete",'EL scheme register'!$AI$7:$AI$610,"Yes") | P67: =COUNTIFS('EL scheme register'!$A$7:$A$610,$A67,'EL scheme register'!$AF$7:$AF$610,"Outside strict definition") | Q67: =COUNTIF('EL exclusions & gaps'!$B$7:$B$5000,$A67) | R67: Not evidenced | S67: Not evidenced | T67: Industrial Group Project (MEng/BEng Mechanical Engineering) [Programme/course] | U67: Engineering/computing: 1 | V67: Isolated departmental provision | W67: Reduced-depth review (about 12 searches plus page fetches). The strongest verified provision is in engineering: 60-credit Industrial Group Projects in MEng/BEng Computer Systems Engineering (compulsory in the MEng additional year; projects from industry collaborators or research groups, presented to academic staff and industry professionals) and Mechanical Engineering (groups define and solve a problem with industry collaborators and present to an industry client). Neither page states that every project has an external client, and the Computer Systems page mixes in internal research-group projects, so employer connection is rated Unclear for that route; the Mechanical page's course listing is for 2026-27 entry. In business, the Postgraduate Consultancy Project gives genuine company-set briefs but is individual (excluded); the Group Consulting Project at Coventry University London is a team format but an undated employer-facing offer with no credit or cohort evidence. Media, design and business-degree pages refer to real clients or live briefs, but group basis, client role and standard-ness are unevidenced. No university-wide or central route qualifies: Global Opportunities and Glob | X67: Not researched in depth: Manufacturing Engineering IGP Initiation/Execution (search summary only); Interactive Media Integrative Project; MA Product Design Innovation live briefs; Business Analytics and Marketing consultancy options; health and nursing; Coventry Law School beyond clinic; module specifications/handbooks (not fetched); Computer Science/Software Engineering group projects (no client evidence). Further departmental instances likely. WebFetch returned model-summarised extracts, not raw page text. Search results show 'Coventry Business School' and 'College of Business and Law' naming variants.
A68: UK28 | B68: Nottingham Trent | C68: UK | D68: Additional UK sample | E68: UK – additional | F68: 2027 | G68: 639 | H68: Complete | I68: =COUNTIFS('EL scheme register'!$A$7:$A$610,$A68,'EL scheme register'!$C$7:$C$610,"University-wide",'EL scheme register'!$AJ$7:$AJ$610,"Yes") | J68: =COUNTIFS('EL scheme register'!$A$7:$A$610,$A68,'EL scheme register'!$C$7:$C$610,"Cross-faculty",'EL scheme register'!$AJ$7:$AJ$610,"Yes") | K68: =COUNTIFS('EL scheme register'!$A$7:$A$610,$A68,'EL scheme register'!$C$7:$C$610,"Faculty/school",'EL scheme register'!$AJ$7:$AJ$610,"Yes") | L68: =COUNTIFS('EL scheme register'!$A$7:$A$610,$A68,'EL scheme register'!$C$7:$C$610,"Programme/course",'EL scheme register'!$AJ$7:$AJ$610,"Yes") | M68: =COUNTIFS('EL scheme register'!$A$7:$A$610,$A68,'EL scheme register'!$C$7:$C$610,"Unclear",'EL scheme register'!$AJ$7:$AJ$610,"Yes") | N68: =SUM(I68:M68) | O68: =COUNTIFS('EL scheme register'!$A$7:$A$610,$A68,'EL scheme register'!$AF$7:$AF$610,"Potentially relevant; evidence incomplete",'EL scheme register'!$AI$7:$AI$610,"Yes") | P68: =COUNTIFS('EL scheme register'!$A$7:$A$610,$A68,'EL scheme register'!$AF$7:$AF$610,"Outside strict definition") | Q68: =COUNTIF('EL exclusions & gaps'!$B$7:$B$5000,$A68) | R68: Not evidenced | S68: Not evidenced | T68: Postgraduate Consultancy Projects (Consultancy Experience Project) [Faculty/school]; Community Engaged Learning (CEL) [Cross-faculty] | U68: Business/management: 1; Central provision: 1; Arts/humanities/social sciences: 1 | V68: Several distributed routes | W68: Nottingham Trent University has distributed employer-linked group provision, strongest in Nottingham Business School (NBS). - Business: NBS postgraduate consultancy projects put MSc/MBA teams with external clients (businesses, a primary school, charities), with client meetings, a final presentation with Q&A and, for MSc, a 3,000-4,000 word report (current: Nov 2025 case news). NBSBright pairs final-year undergraduates with business challenges over about seven weeks, with 2026 dates (21 Sept-mid Nov 2026); team working is not stated in the extract. A core undergraduate module text describes teams addressing a live brief set by a real organisation (undated). - Central: Community Engaged Learning assigns student groups (a team of five in Sociology) to community partners on course-linked projects, with a 2026/27 timetable. Grads4Nottm is an extracurricular two-week employer-hosted group challenge; latest evidence is 2024. - Design: Product Design BA live group briefs with named industry clients; Co Lab cross-disciplinary projects set by charities or industry partners (both undated). - Engineering: Year 1 Design Challenge 'set by industry' in groups; external involvement unclear. Compul | X68: Direct page access blocked (403 / Cloudflare challenge), so no 'page text' retrieval. Science, Law, health, Computing and humanities live-brief modules not evidenced; further departmental instances likely. Credits, module codes and compulsory status mostly unresolved. Grads4Nottm has no 2025/26 evidence.
A69: UK29 | B69: Manchester Metropolitan | C69: UK | D69: Additional UK sample | E69: UK – additional | F69: 2027 | G69: 600 | H69: Complete | I69: =COUNTIFS('EL scheme register'!$A$7:$A$610,$A69,'EL scheme register'!$C$7:$C$610,"University-wide",'EL scheme register'!$AJ$7:$AJ$610,"Yes") | J69: =COUNTIFS('EL scheme register'!$A$7:$A$610,$A69,'EL scheme register'!$C$7:$C$610,"Cross-faculty",'EL scheme register'!$AJ$7:$AJ$610,"Yes") | K69: =COUNTIFS('EL scheme register'!$A$7:$A$610,$A69,'EL scheme register'!$C$7:$C$610,"Faculty/school",'EL scheme register'!$AJ$7:$AJ$610,"Yes") | L69: =COUNTIFS('EL scheme register'!$A$7:$A$610,$A69,'EL scheme register'!$C$7:$C$610,"Programme/course",'EL scheme register'!$AJ$7:$AJ$610,"Yes") | M69: =COUNTIFS('EL scheme register'!$A$7:$A$610,$A69,'EL scheme register'!$C$7:$C$610,"Unclear",'EL scheme register'!$AJ$7:$AJ$610,"Yes") | N69: =SUM(I69:M69) | O69: =COUNTIFS('EL scheme register'!$A$7:$A$610,$A69,'EL scheme register'!$AF$7:$AF$610,"Potentially relevant; evidence incomplete",'EL scheme register'!$AI$7:$AI$610,"Yes") | P69: =COUNTIFS('EL scheme register'!$A$7:$A$610,$A69,'EL scheme register'!$AF$7:$AF$610,"Outside strict definition") | Q69: =COUNTIF('EL exclusions & gaps'!$B$7:$B$5000,$A69) | R69: Not evidenced | S69: Not evidenced | V69: Several distributed routes | W69: Reduced-depth review (about 11 searches plus page fetches). Manchester Met advertises live-project learning in several places, but no route could be verified as meeting group, project and external-client criteria together with current delivery. The strongest lead is Engaging the Humanities, a 15-credit Level 5 unit compulsory since 2023/24 for History, Politics, IR and Philosophy students, in which interdisciplinary groups work on live briefs co-developed with DEFRA, the National Archives and Manchester Histories (164 students in 2024). External coverage per cohort is unclear because internal teams also co-develop briefs, and 2025/26 delivery is undated. Central routes: the Student projects and consultancy service (organisations commission staff-supervised student projects, reported as report/presentation) and Rise project challenges (problems posed by city advocates) involve external bodies, but team structure is not stated. Rise itself is a co-curricular points framework and is not counted. The Faculty of Health and Education WIL offer allows live briefs individually or in small groups (not separable). Engineering lists a core Year 2 Group Project and employer-set live projects b | X69: Unit specifications for Engineering Group Project, MSc Management/MBA live client projects, Art and Design live briefs, Law clinics not retrieved. The Innovate blog and department collaborative-projects page were not openable (403/404); Engaging the Humanities evidence is search extract only. Rise project-challenge listings, team structure and dates not obtained. Further departmental instances likely.
A70: UK30 | B70: Plymouth | C70: UK | D70: Additional UK sample | E70: UK – additional | F70: 2027 | G70: 691 | H70: Complete | I70: =COUNTIFS('EL scheme register'!$A$7:$A$610,$A70,'EL scheme register'!$C$7:$C$610,"University-wide",'EL scheme register'!$AJ$7:$AJ$610,"Yes") | J70: =COUNTIFS('EL scheme register'!$A$7:$A$610,$A70,'EL scheme register'!$C$7:$C$610,"Cross-faculty",'EL scheme register'!$AJ$7:$AJ$610,"Yes") | K70: =COUNTIFS('EL scheme register'!$A$7:$A$610,$A70,'EL scheme register'!$C$7:$C$610,"Faculty/school",'EL scheme register'!$AJ$7:$AJ$610,"Yes") | L70: =COUNTIFS('EL scheme register'!$A$7:$A$610,$A70,'EL scheme register'!$C$7:$C$610,"Programme/course",'EL scheme register'!$AJ$7:$AJ$610,"Yes") | M70: =COUNTIFS('EL scheme register'!$A$7:$A$610,$A70,'EL scheme register'!$C$7:$C$610,"Unclear",'EL scheme register'!$AJ$7:$AJ$610,"Yes") | N70: =SUM(I70:M70) | O70: =COUNTIFS('EL scheme register'!$A$7:$A$610,$A70,'EL scheme register'!$AF$7:$AF$610,"Potentially relevant; evidence incomplete",'EL scheme register'!$AI$7:$AI$610,"Yes") | P70: =COUNTIFS('EL scheme register'!$A$7:$A$610,$A70,'EL scheme register'!$AF$7:$AF$610,"Outside strict definition") | Q70: =COUNTIF('EL exclusions & gaps'!$B$7:$B$5000,$A70) | R70: Not evidenced | S70: Not evidenced | V70: Several distributed routes | W70: Plymouth shows distributed, programme-level provision rather than an institution-wide scheme. The clearest route is the core 30-credit MBA module Leading Change, People and Projects: teams spend 10-14 weeks on a real organisational brief and present to the client organisation. Architecture runs live design-build projects for external clients (Dartington Hall Trust; a primary school) with student groups, though the page is undated. Photography (Year 1 core MEDI423) has teams tackle a live brief from a creative-industry client, and Creative Media has core external-partner modules, but deliverables are unspecified. Inspiring Futures, the Faculty of Arts, Humanities and Business knowledge-exchange scheme, hosts named businesses and charities, but group versus individual routes cannot be separated. Business Management with Foundation Year BUSM3004 (team, real business or community project) and MEng PROJ500 (team prototype, problems from industry, commerce or research) lack evidence of an external organisation's role. Careers-run BOOST and Challenge Connect events could not be confirmed. Delivery years are mostly undated, so current status is unclear for most routes. No science, social s | X70: Most pages undated (only BUSM3004 corroborated by 2026-27 fee tables); module handbooks and assessment details not opened; BOOST/Challenge Connect, Year 2 Business Challenge, STO6005, STO312 (partner-delivered) unverified; further departmental instances likely (design, media, engineering, nursing/health); reduced-depth mode with about 10 searches plus page fetches.
A71: US01 | B71: Massachusetts Institute of Technology | C71: US | D71: US sample | E71: US | F71: 2027 | G71: 1 | H71: Complete | I71: =COUNTIFS('EL scheme register'!$A$7:$A$610,$A71,'EL scheme register'!$C$7:$C$610,"University-wide",'EL scheme register'!$AJ$7:$AJ$610,"Yes") | J71: =COUNTIFS('EL scheme register'!$A$7:$A$610,$A71,'EL scheme register'!$C$7:$C$610,"Cross-faculty",'EL scheme register'!$AJ$7:$AJ$610,"Yes") | K71: =COUNTIFS('EL scheme register'!$A$7:$A$610,$A71,'EL scheme register'!$C$7:$C$610,"Faculty/school",'EL scheme register'!$AJ$7:$AJ$610,"Yes") | L71: =COUNTIFS('EL scheme register'!$A$7:$A$610,$A71,'EL scheme register'!$C$7:$C$610,"Programme/course",'EL scheme register'!$AJ$7:$AJ$610,"Yes") | M71: =COUNTIFS('EL scheme register'!$A$7:$A$610,$A71,'EL scheme register'!$C$7:$C$610,"Unclear",'EL scheme register'!$AJ$7:$AJ$610,"Yes") | N71: =SUM(I71:M71) | O71: =COUNTIFS('EL scheme register'!$A$7:$A$610,$A71,'EL scheme register'!$AF$7:$AF$610,"Potentially relevant; evidence incomplete",'EL scheme register'!$AI$7:$AI$610,"Yes") | P71: =COUNTIFS('EL scheme register'!$A$7:$A$610,$A71,'EL scheme register'!$AF$7:$AF$610,"Outside strict definition") | Q71: =COUNTIF('EL exclusions & gaps'!$B$7:$B$5000,$A71) | R71: Not evidenced | S71: Not evidenced | T71: MIT Sloan Action Learning Labs (Multiple labs (e.g. Asia/ASEAN Lab, GO-Lab, Finance Lab, Sustainable Business Lab, Work Lab 15.679)) [Faculty/school] | U71: Business/management: 1 | V71: Several distributed routes | W71: MIT's employer-linked group project provision is concentrated in graduate professional programmes, with no institute-wide scheme verified. The clearest route is MIT Sloan Action Learning: four-person teams with a faculty mentor tackle a host organisation's real problem and deliver options and recommendations; hosts name an executive sponsor and contact and fund travel, and Sloan reports work with over 2,700 organisations. Further Sloan routes are the MBA-core OP Team Project (teams of six, live company case, all first-year MBAs) and the Master of Business Analytics capstone (38 external sponsors in 2025, mostly student pairs, sponsors provide a staff mentor and data). Engineering-side master's routes are the Supply Chain Management capstone (10-month sponsor-defined projects) and the SDM spring project (industry, government and non-profit partners), and D-Lab and DUSP offer partner/client semester projects. Undergraduate options are thin: NEET is team- and project-based with industry sponsorship but no employer-set group project was evidenced, and UROP is individual research. Most records rest on undated pages, so current delivery is confirmed only for Action Learning (Work Lab, sp | X71: Session limit stopped further fetches: SCM page not opened by WebFetch (summary only); undergraduate departmental capstones (1.013, 16.82, 6.UAP etc.), Gordon Engineering Leadership, UPOP, MISTI, Media Lab and Architecture not researched; science area had only one query; further departmental instances likely. Credit, compulsory status and dated delivery missing for S2-S7. WebFetch summaries (small model) rather than verbatim quotes.
A72: US02 | B72: Harvard | C72: US | D72: US sample | E72: US | F72: 2027 | G72: 5 | H72: Complete | I72: =COUNTIFS('EL scheme register'!$A$7:$A$610,$A72,'EL scheme register'!$C$7:$C$610,"University-wide",'EL scheme register'!$AJ$7:$AJ$610,"Yes") | J72: =COUNTIFS('EL scheme register'!$A$7:$A$610,$A72,'EL scheme register'!$C$7:$C$610,"Cross-faculty",'EL scheme register'!$AJ$7:$AJ$610,"Yes") | K72: =COUNTIFS('EL scheme register'!$A$7:$A$610,$A72,'EL scheme register'!$C$7:$C$610,"Faculty/school",'EL scheme register'!$AJ$7:$AJ$610,"Yes") | L72: =COUNTIFS('EL scheme register'!$A$7:$A$610,$A72,'EL scheme register'!$C$7:$C$610,"Programme/course",'EL scheme register'!$AJ$7:$AJ$610,"Yes") | M72: =COUNTIFS('EL scheme register'!$A$7:$A$610,$A72,'EL scheme register'!$C$7:$C$610,"Unclear",'EL scheme register'!$AJ$7:$AJ$610,"Yes") | N72: =SUM(I72:M72) | O72: =COUNTIFS('EL scheme register'!$A$7:$A$610,$A72,'EL scheme register'!$AF$7:$AF$610,"Potentially relevant; evidence incomplete",'EL scheme register'!$AI$7:$AI$610,"Yes") | P72: =COUNTIFS('EL scheme register'!$A$7:$A$610,$A72,'EL scheme register'!$AF$7:$AF$610,"Outside strict definition") | Q72: =COUNTIF('EL exclusions & gaps'!$B$7:$B$5000,$A72) | R72: Not evidenced | S72: Not evidenced | T72: FIELD Global Capstone (CAP), formerly FIELD Global Immersion (CAP) [Programme/course]; Computational Science and Engineering Capstone Project (APCOMP 297R) (APCOMP 297R) [Programme/course] | U72: Business/management: 1; Engineering/computing: 1 | V72: Several distributed routes | W72: Harvard's verified employer-linked group provision sits in separate professional-school and programme routes rather than a central scheme. The strongest is the HBS FIELD Global Capstone: a required first-year MBA course in which teams of six work with a partner company abroad to design a new product or service for local consumers (immersion 11-18 May 2026). The SEAS/IACS Computational Science and Engineering Capstone (APCOMP 297R) puts groups of 3-4 on real-world projects for partner organizations, with a Fall 2026 section listed and named past partners such as Biogen, Spotify and Unspace; whether it is compulsory is unknown. The Harvard Law School Dispute Systems Design Clinic fits all three criteria (teams of 2-3, weekly client meetings, final report) but is undated, so current delivery is unclear. The Kennedy School Policy Analysis Exercise is a compulsory MPP capstone for public or nonprofit clients, but sources conflict on whether students work alone or in small groups. The legacy lead, the Mindich Program in Engaged Scholarship, offers about 60 community-engaged undergraduate courses a year, but its pages do not show group projects with partner organizations, so it is recorde | X72: Reduced-depth review (about 14 searches plus page fetches). Several Harvard pages returned 403/404 to WebFetch (iacs.seas capstone, designfair, HBS handbook), so some evidence is search-index text. Not covered: Mindich course-level projects (GOV 1022 etc.), Harvard Innovation Labs, HGSE, HSPH, Harvard Medical School, GSD studios, Harvard Law SPOs/other clinics, Harvard Extension, further SEAS and FAS undergraduate courses; further departmental instances likely.
A73: US03 | B73: Stanford | C73: US | D73: US sample | E73: US | F73: 2027 | G73: 2 | H73: Not started | I73: =COUNTIFS('EL scheme register'!$A$7:$A$610,$A73,'EL scheme register'!$C$7:$C$610,"University-wide",'EL scheme register'!$AJ$7:$AJ$610,"Yes") | J73: =COUNTIFS('EL scheme register'!$A$7:$A$610,$A73,'EL scheme register'!$C$7:$C$610,"Cross-faculty",'EL scheme register'!$AJ$7:$AJ$610,"Yes") | K73: =COUNTIFS('EL scheme register'!$A$7:$A$610,$A73,'EL scheme register'!$C$7:$C$610,"Faculty/school",'EL scheme register'!$AJ$7:$AJ$610,"Yes") | L73: =COUNTIFS('EL scheme register'!$A$7:$A$610,$A73,'EL scheme register'!$C$7:$C$610,"Programme/course",'EL scheme register'!$AJ$7:$AJ$610,"Yes") | M73: =COUNTIFS('EL scheme register'!$A$7:$A$610,$A73,'EL scheme register'!$C$7:$C$610,"Unclear",'EL scheme register'!$AJ$7:$AJ$610,"Yes") | N73: =SUM(I73:M73) | O73: =COUNTIFS('EL scheme register'!$A$7:$A$610,$A73,'EL scheme register'!$AF$7:$AF$610,"Potentially relevant; evidence incomplete",'EL scheme register'!$AI$7:$AI$610,"Yes") | P73: =COUNTIFS('EL scheme register'!$A$7:$A$610,$A73,'EL scheme register'!$AF$7:$AF$610,"Outside strict definition") | Q73: =COUNTIF('EL exclusions & gaps'!$B$7:$B$5000,$A73) | R73: Not reviewed | S73: Not reviewed | V73: Not reviewed
A74: US04 | B74: California Institute of Technology | C74: US | D74: US sample | E74: US | F74: 2027 | G74: 7 | H74: Not started | I74: =COUNTIFS('EL scheme register'!$A$7:$A$610,$A74,'EL scheme register'!$C$7:$C$610,"University-wide",'EL scheme register'!$AJ$7:$AJ$610,"Yes") | J74: =COUNTIFS('EL scheme register'!$A$7:$A$610,$A74,'EL scheme register'!$C$7:$C$610,"Cross-faculty",'EL scheme register'!$AJ$7:$AJ$610,"Yes") | K74: =COUNTIFS('EL scheme register'!$A$7:$A$610,$A74,'EL scheme register'!$C$7:$C$610,"Faculty/school",'EL scheme register'!$AJ$7:$AJ$610,"Yes") | L74: =COUNTIFS('EL scheme register'!$A$7:$A$610,$A74,'EL scheme register'!$C$7:$C$610,"Programme/course",'EL scheme register'!$AJ$7:$AJ$610,"Yes") | M74: =COUNTIFS('EL scheme register'!$A$7:$A$610,$A74,'EL scheme register'!$C$7:$C$610,"Unclear",'EL scheme register'!$AJ$7:$AJ$610,"Yes") | N74: =SUM(I74:M74) | O74: =COUNTIFS('EL scheme register'!$A$7:$A$610,$A74,'EL scheme register'!$AF$7:$AF$610,"Potentially relevant; evidence incomplete",'EL scheme register'!$AI$7:$AI$610,"Yes") | P74: =COUNTIFS('EL scheme register'!$A$7:$A$610,$A74,'EL scheme register'!$AF$7:$AF$610,"Outside strict definition") | Q74: =COUNTIF('EL exclusions & gaps'!$B$7:$B$5000,$A74) | R74: Not reviewed | S74: Not reviewed | V74: Not reviewed
A75: US05 | B75: California Berkeley | C75: US | D75: US sample | E75: US | F75: 2027 | G75: 20 | H75: Partial | I75: =COUNTIFS('EL scheme register'!$A$7:$A$610,$A75,'EL scheme register'!$C$7:$C$610,"University-wide",'EL scheme register'!$AJ$7:$AJ$610,"Yes") | J75: =COUNTIFS('EL scheme register'!$A$7:$A$610,$A75,'EL scheme register'!$C$7:$C$610,"Cross-faculty",'EL scheme register'!$AJ$7:$AJ$610,"Yes") | K75: =COUNTIFS('EL scheme register'!$A$7:$A$610,$A75,'EL scheme register'!$C$7:$C$610,"Faculty/school",'EL scheme register'!$AJ$7:$AJ$610,"Yes") | L75: =COUNTIFS('EL scheme register'!$A$7:$A$610,$A75,'EL scheme register'!$C$7:$C$610,"Programme/course",'EL scheme register'!$AJ$7:$AJ$610,"Yes") | M75: =COUNTIFS('EL scheme register'!$A$7:$A$610,$A75,'EL scheme register'!$C$7:$C$610,"Unclear",'EL scheme register'!$AJ$7:$AJ$610,"Yes") | N75: =SUM(I75:M75) | O75: =COUNTIFS('EL scheme register'!$A$7:$A$610,$A75,'EL scheme register'!$AF$7:$AF$610,"Potentially relevant; evidence incomplete",'EL scheme register'!$AI$7:$AI$610,"Yes") | P75: =COUNTIFS('EL scheme register'!$A$7:$A$610,$A75,'EL scheme register'!$AF$7:$AF$610,"Outside strict definition") | Q75: =COUNTIF('EL exclusions & gaps'!$B$7:$B$5000,$A75) | R75: Not evidenced | S75: Not evidenced | V75: Several distributed routes | W75: Berkeley's documented employer-linked group project routes are distributed across graduate schools rather than institution-wide. The Goldman School's Introduction to Policy Analysis (S1) places teams of four to six first-year MPP students with public-sector agencies and NGOs, producing a report and presentation (Spring 2027 call open). Engineering's MEng Capstone (S2) runs nine-month teams of three to five on industry-proposed projects, but the page also describes faculty-involved projects, so external sponsorship across all teams is unproven. Data Science Discovery (S3) offers mentor-set projects with teams of 1-5, partly academic mentors, so group and employer criteria are unclear. Haas offers Social Sector Solutions (nonprofit client teams of 5-7), Haas@Work (firm challenges) and Startup Lab, all MBA or graduate-led with weak current-year evidence. The legacy Berkeley Discovery framework is a platform, not a scheme. No undergraduate curricular route meeting all three criteria was verified; participation is optional or programme-specific, with no institution-wide route found. No participation numbers were located. | X75: Undergraduate humanities/social science and EECS/Data Science routes not searched (limit). Current-year evidence absent for most Haas routes. Compulsory status of IPA and MEng capstone unconfirmed. Further departmental capstones likely exist. | PARTIAL REVIEW — remaining: Session search limit hit after about 12 searches/fetches. Not run: a humanities/social-science undergraduate query and an EECS/Data Science undergraduate industry-project query; also Fung Fellowship, Deep Tech Innovation Lab, MSSE capstone and Haas IBD need opening; current-year (2025/26-2026/27) evidence for S1, S2, S4-S6 still needed.
A76: US06 | B76: Chicago | C76: US | D76: US sample | E76: US | F76: 2027 | G76: 24 | H76: Not started | I76: =COUNTIFS('EL scheme register'!$A$7:$A$610,$A76,'EL scheme register'!$C$7:$C$610,"University-wide",'EL scheme register'!$AJ$7:$AJ$610,"Yes") | J76: =COUNTIFS('EL scheme register'!$A$7:$A$610,$A76,'EL scheme register'!$C$7:$C$610,"Cross-faculty",'EL scheme register'!$AJ$7:$AJ$610,"Yes") | K76: =COUNTIFS('EL scheme register'!$A$7:$A$610,$A76,'EL scheme register'!$C$7:$C$610,"Faculty/school",'EL scheme register'!$AJ$7:$AJ$610,"Yes") | L76: =COUNTIFS('EL scheme register'!$A$7:$A$610,$A76,'EL scheme register'!$C$7:$C$610,"Programme/course",'EL scheme register'!$AJ$7:$AJ$610,"Yes") | M76: =COUNTIFS('EL scheme register'!$A$7:$A$610,$A76,'EL scheme register'!$C$7:$C$610,"Unclear",'EL scheme register'!$AJ$7:$AJ$610,"Yes") | N76: =SUM(I76:M76) | O76: =COUNTIFS('EL scheme register'!$A$7:$A$610,$A76,'EL scheme register'!$AF$7:$AF$610,"Potentially relevant; evidence incomplete",'EL scheme register'!$AI$7:$AI$610,"Yes") | P76: =COUNTIFS('EL scheme register'!$A$7:$A$610,$A76,'EL scheme register'!$AF$7:$AF$610,"Outside strict definition") | Q76: =COUNTIF('EL exclusions & gaps'!$B$7:$B$5000,$A76) | R76: Not reviewed | S76: Not reviewed | V76: Not reviewed
A77: US07 | B77: Pennsylvania | C77: US | D77: US sample | E77: US | F77: 2027 | G77: 15 | H77: Not started | I77: =COUNTIFS('EL scheme register'!$A$7:$A$610,$A77,'EL scheme register'!$C$7:$C$610,"University-wide",'EL scheme register'!$AJ$7:$AJ$610,"Yes") | J77: =COUNTIFS('EL scheme register'!$A$7:$A$610,$A77,'EL scheme register'!$C$7:$C$610,"Cross-faculty",'EL scheme register'!$AJ$7:$AJ$610,"Yes") | K77: =COUNTIFS('EL scheme register'!$A$7:$A$610,$A77,'EL scheme register'!$C$7:$C$610,"Faculty/school",'EL scheme register'!$AJ$7:$AJ$610,"Yes") | L77: =COUNTIFS('EL scheme register'!$A$7:$A$610,$A77,'EL scheme register'!$C$7:$C$610,"Programme/course",'EL scheme register'!$AJ$7:$AJ$610,"Yes") | M77: =COUNTIFS('EL scheme register'!$A$7:$A$610,$A77,'EL scheme register'!$C$7:$C$610,"Unclear",'EL scheme register'!$AJ$7:$AJ$610,"Yes") | N77: =SUM(I77:M77) | O77: =COUNTIFS('EL scheme register'!$A$7:$A$610,$A77,'EL scheme register'!$AF$7:$AF$610,"Potentially relevant; evidence incomplete",'EL scheme register'!$AI$7:$AI$610,"Yes") | P77: =COUNTIFS('EL scheme register'!$A$7:$A$610,$A77,'EL scheme register'!$AF$7:$AF$610,"Outside strict definition") | Q77: =COUNTIF('EL exclusions & gaps'!$B$7:$B$5000,$A77) | R77: Not reviewed | S77: Not reviewed | V77: Not reviewed
A78: US08 | B78: Cornell | C78: US | D78: US sample | E78: US | F78: 2027 | G78: 16 | H78: Not started | I78: =COUNTIFS('EL scheme register'!$A$7:$A$610,$A78,'EL scheme register'!$C$7:$C$610,"University-wide",'EL scheme register'!$AJ$7:$AJ$610,"Yes") | J78: =COUNTIFS('EL scheme register'!$A$7:$A$610,$A78,'EL scheme register'!$C$7:$C$610,"Cross-faculty",'EL scheme register'!$AJ$7:$AJ$610,"Yes") | K78: =COUNTIFS('EL scheme register'!$A$7:$A$610,$A78,'EL scheme register'!$C$7:$C$610,"Faculty/school",'EL scheme register'!$AJ$7:$AJ$610,"Yes") | L78: =COUNTIFS('EL scheme register'!$A$7:$A$610,$A78,'EL scheme register'!$C$7:$C$610,"Programme/course",'EL scheme register'!$AJ$7:$AJ$610,"Yes") | M78: =COUNTIFS('EL scheme register'!$A$7:$A$610,$A78,'EL scheme register'!$C$7:$C$610,"Unclear",'EL scheme register'!$AJ$7:$AJ$610,"Yes") | N78: =SUM(I78:M78) | O78: =COUNTIFS('EL scheme register'!$A$7:$A$610,$A78,'EL scheme register'!$AF$7:$AF$610,"Potentially relevant; evidence incomplete",'EL scheme register'!$AI$7:$AI$610,"Yes") | P78: =COUNTIFS('EL scheme register'!$A$7:$A$610,$A78,'EL scheme register'!$AF$7:$AF$610,"Outside strict definition") | Q78: =COUNTIF('EL exclusions & gaps'!$B$7:$B$5000,$A78) | R78: Not reviewed | S78: Not reviewed | V78: Not reviewed
A79: US09 | B79: Yale | C79: US | D79: US sample | E79: US | F79: 2027 | G79: 16 | H79: Not started | I79: =COUNTIFS('EL scheme register'!$A$7:$A$610,$A79,'EL scheme register'!$C$7:$C$610,"University-wide",'EL scheme register'!$AJ$7:$AJ$610,"Yes") | J79: =COUNTIFS('EL scheme register'!$A$7:$A$610,$A79,'EL scheme register'!$C$7:$C$610,"Cross-faculty",'EL scheme register'!$AJ$7:$AJ$610,"Yes") | K79: =COUNTIFS('EL scheme register'!$A$7:$A$610,$A79,'EL scheme register'!$C$7:$C$610,"Faculty/school",'EL scheme register'!$AJ$7:$AJ$610,"Yes") | L79: =COUNTIFS('EL scheme register'!$A$7:$A$610,$A79,'EL scheme register'!$C$7:$C$610,"Programme/course",'EL scheme register'!$AJ$7:$AJ$610,"Yes") | M79: =COUNTIFS('EL scheme register'!$A$7:$A$610,$A79,'EL scheme register'!$C$7:$C$610,"Unclear",'EL scheme register'!$AJ$7:$AJ$610,"Yes") | N79: =SUM(I79:M79) | O79: =COUNTIFS('EL scheme register'!$A$7:$A$610,$A79,'EL scheme register'!$AF$7:$AF$610,"Potentially relevant; evidence incomplete",'EL scheme register'!$AI$7:$AI$610,"Yes") | P79: =COUNTIFS('EL scheme register'!$A$7:$A$610,$A79,'EL scheme register'!$AF$7:$AF$610,"Outside strict definition") | Q79: =COUNTIF('EL exclusions & gaps'!$B$7:$B$5000,$A79) | R79: Not reviewed | S79: Not reviewed | V79: Not reviewed
A80: US10 | B80: Princeton | C80: US | D80: US sample | E80: US | F80: 2027 | G80: 27 | H80: Not started | I80: =COUNTIFS('EL scheme register'!$A$7:$A$610,$A80,'EL scheme register'!$C$7:$C$610,"University-wide",'EL scheme register'!$AJ$7:$AJ$610,"Yes") | J80: =COUNTIFS('EL scheme register'!$A$7:$A$610,$A80,'EL scheme register'!$C$7:$C$610,"Cross-faculty",'EL scheme register'!$AJ$7:$AJ$610,"Yes") | K80: =COUNTIFS('EL scheme register'!$A$7:$A$610,$A80,'EL scheme register'!$C$7:$C$610,"Faculty/school",'EL scheme register'!$AJ$7:$AJ$610,"Yes") | L80: =COUNTIFS('EL scheme register'!$A$7:$A$610,$A80,'EL scheme register'!$C$7:$C$610,"Programme/course",'EL scheme register'!$AJ$7:$AJ$610,"Yes") | M80: =COUNTIFS('EL scheme register'!$A$7:$A$610,$A80,'EL scheme register'!$C$7:$C$610,"Unclear",'EL scheme register'!$AJ$7:$AJ$610,"Yes") | N80: =SUM(I80:M80) | O80: =COUNTIFS('EL scheme register'!$A$7:$A$610,$A80,'EL scheme register'!$AF$7:$AF$610,"Potentially relevant; evidence incomplete",'EL scheme register'!$AI$7:$AI$610,"Yes") | P80: =COUNTIFS('EL scheme register'!$A$7:$A$610,$A80,'EL scheme register'!$AF$7:$AF$610,"Outside strict definition") | Q80: =COUNTIF('EL exclusions & gaps'!$B$7:$B$5000,$A80) | R80: Not reviewed | S80: Not reviewed | V80: Not reviewed
A81: US11 | B81: Columbia | C81: US | D81: US sample | E81: US | F81: 2027 | G81: 43 | H81: Not started | I81: =COUNTIFS('EL scheme register'!$A$7:$A$610,$A81,'EL scheme register'!$C$7:$C$610,"University-wide",'EL scheme register'!$AJ$7:$AJ$610,"Yes") | J81: =COUNTIFS('EL scheme register'!$A$7:$A$610,$A81,'EL scheme register'!$C$7:$C$610,"Cross-faculty",'EL scheme register'!$AJ$7:$AJ$610,"Yes") | K81: =COUNTIFS('EL scheme register'!$A$7:$A$610,$A81,'EL scheme register'!$C$7:$C$610,"Faculty/school",'EL scheme register'!$AJ$7:$AJ$610,"Yes") | L81: =COUNTIFS('EL scheme register'!$A$7:$A$610,$A81,'EL scheme register'!$C$7:$C$610,"Programme/course",'EL scheme register'!$AJ$7:$AJ$610,"Yes") | M81: =COUNTIFS('EL scheme register'!$A$7:$A$610,$A81,'EL scheme register'!$C$7:$C$610,"Unclear",'EL scheme register'!$AJ$7:$AJ$610,"Yes") | N81: =SUM(I81:M81) | O81: =COUNTIFS('EL scheme register'!$A$7:$A$610,$A81,'EL scheme register'!$AF$7:$AF$610,"Potentially relevant; evidence incomplete",'EL scheme register'!$AI$7:$AI$610,"Yes") | P81: =COUNTIFS('EL scheme register'!$A$7:$A$610,$A81,'EL scheme register'!$AF$7:$AF$610,"Outside strict definition") | Q81: =COUNTIF('EL exclusions & gaps'!$B$7:$B$5000,$A81) | R81: Not reviewed | S81: Not reviewed | V81: Not reviewed
A82: US12 | B82: Johns Hopkins | C82: US | D82: US sample | E82: US | F82: 2027 | G82: 20 | H82: Not started | I82: =COUNTIFS('EL scheme register'!$A$7:$A$610,$A82,'EL scheme register'!$C$7:$C$610,"University-wide",'EL scheme register'!$AJ$7:$AJ$610,"Yes") | J82: =COUNTIFS('EL scheme register'!$A$7:$A$610,$A82,'EL scheme register'!$C$7:$C$610,"Cross-faculty",'EL scheme register'!$AJ$7:$AJ$610,"Yes") | K82: =COUNTIFS('EL scheme register'!$A$7:$A$610,$A82,'EL scheme register'!$C$7:$C$610,"Faculty/school",'EL scheme register'!$AJ$7:$AJ$610,"Yes") | L82: =COUNTIFS('EL scheme register'!$A$7:$A$610,$A82,'EL scheme register'!$C$7:$C$610,"Programme/course",'EL scheme register'!$AJ$7:$AJ$610,"Yes") | M82: =COUNTIFS('EL scheme register'!$A$7:$A$610,$A82,'EL scheme register'!$C$7:$C$610,"Unclear",'EL scheme register'!$AJ$7:$AJ$610,"Yes") | N82: =SUM(I82:M82) | O82: =COUNTIFS('EL scheme register'!$A$7:$A$610,$A82,'EL scheme register'!$AF$7:$AF$610,"Potentially relevant; evidence incomplete",'EL scheme register'!$AI$7:$AI$610,"Yes") | P82: =COUNTIFS('EL scheme register'!$A$7:$A$610,$A82,'EL scheme register'!$AF$7:$AF$610,"Outside strict definition") | Q82: =COUNTIF('EL exclusions & gaps'!$B$7:$B$5000,$A82) | R82: Not reviewed | S82: Not reviewed | V82: Not reviewed
A83: US13 | B83: Michigan Ann Arbor | C83: US | D83: US sample | E83: US | F83: 2027 | G83: 51 | H83: Not started | I83: =COUNTIFS('EL scheme register'!$A$7:$A$610,$A83,'EL scheme register'!$C$7:$C$610,"University-wide",'EL scheme register'!$AJ$7:$AJ$610,"Yes") | J83: =COUNTIFS('EL scheme register'!$A$7:$A$610,$A83,'EL scheme register'!$C$7:$C$610,"Cross-faculty",'EL scheme register'!$AJ$7:$AJ$610,"Yes") | K83: =COUNTIFS('EL scheme register'!$A$7:$A$610,$A83,'EL scheme register'!$C$7:$C$610,"Faculty/school",'EL scheme register'!$AJ$7:$AJ$610,"Yes") | L83: =COUNTIFS('EL scheme register'!$A$7:$A$610,$A83,'EL scheme register'!$C$7:$C$610,"Programme/course",'EL scheme register'!$AJ$7:$AJ$610,"Yes") | M83: =COUNTIFS('EL scheme register'!$A$7:$A$610,$A83,'EL scheme register'!$C$7:$C$610,"Unclear",'EL scheme register'!$AJ$7:$AJ$610,"Yes") | N83: =SUM(I83:M83) | O83: =COUNTIFS('EL scheme register'!$A$7:$A$610,$A83,'EL scheme register'!$AF$7:$AF$610,"Potentially relevant; evidence incomplete",'EL scheme register'!$AI$7:$AI$610,"Yes") | P83: =COUNTIFS('EL scheme register'!$A$7:$A$610,$A83,'EL scheme register'!$AF$7:$AF$610,"Outside strict definition") | Q83: =COUNTIF('EL exclusions & gaps'!$B$7:$B$5000,$A83) | R83: Not reviewed | S83: Not reviewed | V83: Not reviewed
A84: US14 | B84: California Los Angeles | C84: US | D84: US sample | E84: US | F84: 2027 | G84: 49 | H84: Not started | I84: =COUNTIFS('EL scheme register'!$A$7:$A$610,$A84,'EL scheme register'!$C$7:$C$610,"University-wide",'EL scheme register'!$AJ$7:$AJ$610,"Yes") | J84: =COUNTIFS('EL scheme register'!$A$7:$A$610,$A84,'EL scheme register'!$C$7:$C$610,"Cross-faculty",'EL scheme register'!$AJ$7:$AJ$610,"Yes") | K84: =COUNTIFS('EL scheme register'!$A$7:$A$610,$A84,'EL scheme register'!$C$7:$C$610,"Faculty/school",'EL scheme register'!$AJ$7:$AJ$610,"Yes") | L84: =COUNTIFS('EL scheme register'!$A$7:$A$610,$A84,'EL scheme register'!$C$7:$C$610,"Programme/course",'EL scheme register'!$AJ$7:$AJ$610,"Yes") | M84: =COUNTIFS('EL scheme register'!$A$7:$A$610,$A84,'EL scheme register'!$C$7:$C$610,"Unclear",'EL scheme register'!$AJ$7:$AJ$610,"Yes") | N84: =SUM(I84:M84) | O84: =COUNTIFS('EL scheme register'!$A$7:$A$610,$A84,'EL scheme register'!$AF$7:$AF$610,"Potentially relevant; evidence incomplete",'EL scheme register'!$AI$7:$AI$610,"Yes") | P84: =COUNTIFS('EL scheme register'!$A$7:$A$610,$A84,'EL scheme register'!$AF$7:$AF$610,"Outside strict definition") | Q84: =COUNTIF('EL exclusions & gaps'!$B$7:$B$5000,$A84) | R84: Not reviewed | S84: Not reviewed | V84: Not reviewed
A85: US15 | B85: Duke | C85: US | D85: US sample | E85: US | F85: 2027 | G85: 70 | H85: Not started | I85: =COUNTIFS('EL scheme register'!$A$7:$A$610,$A85,'EL scheme register'!$C$7:$C$610,"University-wide",'EL scheme register'!$AJ$7:$AJ$610,"Yes") | J85: =COUNTIFS('EL scheme register'!$A$7:$A$610,$A85,'EL scheme register'!$C$7:$C$610,"Cross-faculty",'EL scheme register'!$AJ$7:$AJ$610,"Yes") | K85: =COUNTIFS('EL scheme register'!$A$7:$A$610,$A85,'EL scheme register'!$C$7:$C$610,"Faculty/school",'EL scheme register'!$AJ$7:$AJ$610,"Yes") | L85: =COUNTIFS('EL scheme register'!$A$7:$A$610,$A85,'EL scheme register'!$C$7:$C$610,"Programme/course",'EL scheme register'!$AJ$7:$AJ$610,"Yes") | M85: =COUNTIFS('EL scheme register'!$A$7:$A$610,$A85,'EL scheme register'!$C$7:$C$610,"Unclear",'EL scheme register'!$AJ$7:$AJ$610,"Yes") | N85: =SUM(I85:M85) | O85: =COUNTIFS('EL scheme register'!$A$7:$A$610,$A85,'EL scheme register'!$AF$7:$AF$610,"Potentially relevant; evidence incomplete",'EL scheme register'!$AI$7:$AI$610,"Yes") | P85: =COUNTIFS('EL scheme register'!$A$7:$A$610,$A85,'EL scheme register'!$AF$7:$AF$610,"Outside strict definition") | Q85: =COUNTIF('EL exclusions & gaps'!$B$7:$B$5000,$A85) | R85: Not reviewed | S85: Not reviewed | V85: Not reviewed
A86: US16 | B86: New York University | C86: US | D86: US sample | E86: US | F86: 2027 | G86: 58 | H86: Not started | I86: =COUNTIFS('EL scheme register'!$A$7:$A$610,$A86,'EL scheme register'!$C$7:$C$610,"University-wide",'EL scheme register'!$AJ$7:$AJ$610,"Yes") | J86: =COUNTIFS('EL scheme register'!$A$7:$A$610,$A86,'EL scheme register'!$C$7:$C$610,"Cross-faculty",'EL scheme register'!$AJ$7:$AJ$610,"Yes") | K86: =COUNTIFS('EL scheme register'!$A$7:$A$610,$A86,'EL scheme register'!$C$7:$C$610,"Faculty/school",'EL scheme register'!$AJ$7:$AJ$610,"Yes") | L86: =COUNTIFS('EL scheme register'!$A$7:$A$610,$A86,'EL scheme register'!$C$7:$C$610,"Programme/course",'EL scheme register'!$AJ$7:$AJ$610,"Yes") | M86: =COUNTIFS('EL scheme register'!$A$7:$A$610,$A86,'EL scheme register'!$C$7:$C$610,"Unclear",'EL scheme register'!$AJ$7:$AJ$610,"Yes") | N86: =SUM(I86:M86) | O86: =COUNTIFS('EL scheme register'!$A$7:$A$610,$A86,'EL scheme register'!$AF$7:$AF$610,"Potentially relevant; evidence incomplete",'EL scheme register'!$AI$7:$AI$610,"Yes") | P86: =COUNTIFS('EL scheme register'!$A$7:$A$610,$A86,'EL scheme register'!$AF$7:$AF$610,"Outside strict definition") | Q86: =COUNTIF('EL exclusions & gaps'!$B$7:$B$5000,$A86) | R86: Not reviewed | S86: Not reviewed | V86: Not reviewed
